Workbook

Sheet RESUMEN
A1: TRAMO_INI | B1: (Varios elementos)
A3: Suma de SALDO_INSOLUTO_INI | B3: Etiquetas de columna
A4: Etiquetas de fila | B4: CASTIGO | C4: VIGENTE | D4: Total general
A5: Apr | B5: 98266240 | C5: 2254105721 | D5: 2352371961
A6: Jun | B6: 1607206191 | D6: 1607206191
A7: Total general | B7: 1705472431 | C7: 2254105721 | D7: 3959578152
A10: TRAMO_INI | B10: (Varios elementos)
A12: Cuenta de SALDO_INSOLUTO_INI | B12: Etiquetas de columna
A13: Etiquetas de fila | B13: CASTIGO | C13: VIGENTE | D13: Total general
A14: Apr | B14: 9 | C14: 302 | D14: 311
A15: Jun | B15: 171 | D15: 171
A16: Total general | B16: 180 | C16: 302 | D16: 482
A20: Cuenta de SALDO_INSOLUTO_INI | B20: Etiquetas de columna | E20: Suma de SALDO_INSOLUTO_INI | F20: Etiquetas de columna
A21: Etiquetas de fila | B21: CASTIGO | C21: VIGENTE | D21: Total general | E21: Etiquetas de fila | F21: CASTIGO | G21: VIGENTE | H21: Total general
A22: Apr | B22: 9 | C22: 302 | D22: 311 | E22: Apr | F22: 98266240 | G22: 2254105721 | H22: 2352371961
A23: 0-365 | B23: 9 | D23: 9 | E23: 0-365 | F23: 98266240 | H23: 98266240
A24: 121-150 | C24: 24 | D24: 24 | E24: 121-150 | G24: 211511353 | H24: 211511353
A25: 151-180 | C25: 39 | D25: 39 | E25: 151-180 | G25: 270077139 | H25: 270077139
A26: 181-210 | C26: 31 | D26: 31 | E26: 181-210 | G26: 235826485 | H26: 235826485
A27: 211-240 | C27: 21 | D27: 21 | E27: 211-240 | G27: 264288632 | H27: 264288632
A28: 241-270 | C28: 30 | D28: 30 | E28: 241-270 | G28: 236386021 | H28: 236386021
A29: 271-300 | C29: 25 | D29: 25 | E29: 271-300 | G29: 170650233 | H29: 170650233
A30: 301-330 | C30: 21 | D30: 21 | E30: 301-330 | G30: 162708140 | H30: 162708140
A31: 31-60 | C31: 41 | D31: 41 | E31: 31-60 | G31: 261949003 | H31: 261949003
A32: 331-360 | C32: 13 | D32: 13 | E32: 331-360 | G32: 92105312 | H32: 92105312
A33: 361-390 | C33: 4 | D33: 4 | E33: 361-390 | G33: 30915537 | H33: 30915537
A34: 61-90 | C34: 37 | D34: 37 | E34: 61-90 | G34: 196467819 | H34: 196467819
A35: 91-120 | C35: 16 | D35: 16 | E35: 91-120 | G35: 121220047 | H35: 121220047
A36: Jun | B36: 171 | D36: 171 | E36: Jun | F36: 1607206191 | H36: 1607206191
A37: Total general | B37: 180 | C37: 302 | D37: 482 | E37: Total general | F37: 1705472431 | G37: 2254105721 | H37: 3959578152

Sheet Export
A1: ID_CREDITO | B1: DIAS_MORA | C1: CUOTAS_MOROSAS_ACTUAL | D1: SALDO_INSOLUTO_INI | E1: PRIORIDAD_GESTION | F1: GESTOR | G1: TIPO_COBRANZA | H1: TRAMO_INI | I1: TRAMO_ACT | J1: TIPO_CARTERA | K1: TIPO_GESTION | L1: FECHA_ASIGNACION | M1: SEGMENTO_CLIENTE | N1: RUT | O1: DV | P1: RAZON_SOCIAL | Q1: PERSONA_NATURAL | R1: VALOR_CUOTA | S1: FECHA_PROX_VCTO | T1: CUOTAS_PAGADAS_ACTUAL | U1: CUOTAS_PAGADAS_INI | V1: PLAZO | W1: CANAL_VENTA | X1: CAMPANAS | Y1: INT_MORA_TOTAL | Z1: GC_TOTAL | AA1: ESTADO_PAT_PAC | AB1: FECHA_FIRMA_PAGARE | AC1: MONTO_ADEUDADO | AD1: TASA_INTERES_CRED | AE1: CONVENIO_CASTIGO | AF1: GESTOR_PLAN_PAGO | AG1: MARCA_CLIENTE | AH1: ESTADO_COBRANZA | AI1: TELEFONO_1 | AJ1: TELEFONO_2 | AK1: TELEFONO_3 | AL1: EMAIL_1 | AM1: EMAIL_2 | AN1: EMAIL_3 | AO1: DIRECCION | AP1: COMUNA | AQ1: REGION | AR1: ROL | AS1: TRIBUNAL | AT1: ESTADO_JUDICIAL | AU1: TIPO_JUDICIAL | AV1: DUAL | AW1: SUSP_ESTADO_JUDICIAL | AX1: SUSP_MOTIVO | AY1: SUSP_FECHA | AZ1: NOTIFICADO | BA1: ESTADO_JUICIO | BB1: VEHICULO_1_PATENTE | BC1: VEHICULO_1_MARCA | BD1: VEHICULO_1_MODELO | BE1: VEHICULO_1_ANIO | BF1: VEHICULO_1_ANIO
A2: 134218 | B2: 3638 | D2: 9957095 | F2: PHOENIX | G2: JUDICIAL | H2: 1096+ | I2: 1096+ | J2: CASTIGO | K2: COBRANZA | L2: 46180 | N2: 12269228 | O2: 0 | P2: CLAUDIO GERMAN ALEGRIA GONZALEZ | R2: 331.459 | S2: 31-07-2016 | W2: TANNER | X2: DACIÓN | Y2: 0 | Z2: 0 | AC2: 5018962 | AH2: CASTIGO | AI2: 09 7 2632839 | AL2: CALEGRIA193@GMAIL.COM | AO2: AV LA HACIENDA N 2776 | AP2: LAMPA | AQ2: REGION METROPOLITANA | AR2: SIN ROL | AS2: SIN TRIBUNAL | AT2: ASIGNACION | AU2: MANTIENE | AV2: NULL | AZ2: NO | BA2: ACTIVO | BB2: DFBY26 | BC2: MITSUBISHI | BD2: L-200 | BE2: 2012 | BF2: 2012
A3: 585590 | B3: 1081 | D3: 5293774 | F3: PHOENIX | G3: JUDICIAL | H3: 731-1095 | I3: 731-1095 | J3: CASTIGO | K3: COBRANZA | L3: 46180 | N3: 14191047 | O3: 7 | P3: FRANCISCO JAVIER LEPIN NEICO | R3: 232.332 | S3: 44934 | W3: TANNER | Y3: 0 | Z3: 0 | AC3: 2393774 | AH3: CASTIGO | AI3: 988631685 | AL3: F.LEPIN@PROFESOR.DUOC.CL | AO3: TUCAPEL JIMENEZ | AP3: SANTIAGO | AQ3: REGION METROPOLITANA | AR3: C-5981-2020 | AS3: 24° Juzgado Civil de Santiago | AT3: REMATADO | AU3: MANTIENE | AZ3: SI | BA3: ACTIVO | BB3: HRJF70 | BC3: KIA MOTORS | BD3: RIO 5 EX 1.4 | BE3: 2016 | BF3: 2016
A4: 1344919 | B4: 411 | D4: 6716000 | F4: PHOENIX | G4: JUDICIAL | H4: 366-730 | I4: 366-730 | J4: CASTIGO | K4: COBRANZA | L4: 46180 | N4: 16746764 | O4: 4 | P4: GERALDINE KAROL VIVAR ARGOMEDO | R4: 292.847 | S4: 45663 | W4: TANNER | X4: DACIÓN | Y4: 0 | Z4: 0 | AC4: 6716000 | AH4: CASTIGO | AI4: 999134883 | AL4: gvivar20@gmail.com | AO4: DECIMA AVENIDA 1430 | AP4: SAN MIGUEL | AQ4: REGION METROPOLITANA | AR4: C-19084-2024 | AS4: 19º Juzgado Civil de Santiago | AT4: EMBARGADO | AU4: MANTIENE | AZ4: SI | BA4: ACTIVO | BB4: PTSS82 | BC4: OPEL | BD4: CROSSLAND TD MT6 1.5 | BE4: 2021 | BF4: 2021
A5: 1371362 | B5: 381 | D5: 8434800 | F5: PHOENIX | G5: JUDICIAL | H5: 366-730 | I5: 366-730 | J5: CASTIGO | K5: COBRANZA | L5: 46180 | N5: 17777736 | O5: 6 | P5: MATIAS IGNACIO RIVEROS ORREGO RIVEROS ORREGO | R5: 486.859 | S5: 45664 | W5: TANNER | X5: DACIÓN | Y5: 0 | Z5: 0 | AC5: 8434800 | AH5: CASTIGO | AI5: 228544308 | AL5: matias.ro@hotmail.com | AO5: HERIBERTO COBARRUBIAS 679 | AP5: ÑUÑOA | AQ5: REGION METROPOLITANA | AR5: C-20304-2024 | AS5: 28º Juzgado Civil de Santiago | AT5: NOTIFICADO | AU5: MANTIENE | AZ5: SI | BA5: ACTIVO | BB5: PYCC10 | BC5: MAZDA | BD5: ALL NEW CX-30 GTX 2.0 2WD 6AT 7G | BE5: 2021 | BF5: 2021
A6: 1421319 | B6: 411 | D6: 4230316 | F6: PHOENIX | G6: JUDICIAL | H6: 366-730 | I6: 366-730 | J6: CASTIGO | K6: COBRANZA | L6: 46180 | N6: 9386766 | O6: 1 | P6: AVELINO DEL TRÁNSITO REYES ESCOBAR | R6: 283.17 | S6: 45663 | W6: TANNER | X6: DACIÓN | Y6: 0 | Z6: 0 | AC6: 4230316 | AH6: CASTIGO | AI6: 998656951 | AL6: avelinoreyesescobar@gmail.com | AO6: Calle Ictinos 1663 | AP6: PEÑALOLEN | AQ6: REGION METROPOLITANA | AR6: C-19072-2024 | AS6: 8º JUZGADO CIVIL DE SANTIAGO | AT6: INGRESADO | AU6: MANTIENE | AZ6: NO | BA6: ACTIVO | BB6: RBDK38 | BC6: JETOUR | BD6: X70 1.5 AUT | BE6: 2021 | BF6: 2021
A7: 1444864 | B7: 411 | D7: 5112777 | F7: PHOENIX | G7: JUDICIAL | H7: 366-730 | I7: 366-730 | J7: CASTIGO | K7: COBRANZA | L7: 46180 | N7: 18135936 | O7: 6 | P7: MILKO ANDRÉS VALLADARES ASTUDILLO | R7: 207.859 | S7: 45663 | W7: TANNER | X7: DACIÓN | Y7: 0 | Z7: 0 | AC7: 5112777 | AH7: CASTIGO | AI7: 956375289 | AL7: milkovalladares1@gmail.com | AO7: ALMIRANTE SIMSON, 1218 | AP7: LOTA | AQ7: VIII REGION | AR7: C-19069-2024 | AS7: 16º Juzgado Civil de Santiago | AT7: EMBARGADO | AU7: MANTIENE | AZ7: SI | BA7: ACTIVO | BB7: RHHH87 | BC7: HAVAL | BD7: HAVAL JOLION 1.5T MT 4X2 ACTIVE | BE7: 2022 | BF7: 2022
A8: 1446743 | B8: 319 | D8: 3879999 | F8: PHOENIX | G8: JUDICIAL | H8: 0-365 | I8: 0-365 | J8: CASTIGO | K8: COBRANZA | L8: 46180 | N8: 14463964 | O8: 2 | P8: MARCELO ALEJANDRO MELLADO SÁNCHEZ | R8: 260.396 | S8: 45666 | W8: CREDINISSAN | X8: DACIÓN | Y8: 0 | Z8: 0 | AC8: 3879999 | AH8: CASTIGO | AI8: 964062894 | AL8: PATHY_JANA86@HOTMAIL.COM | AO8: TALCA 161 | AP8: OSORNO | AQ8: X REGION | AR8: C-22129-2024 | AS8: 15º Juzgado Civil de Santiago | AT8: INGRESADO | AU8: MANTIENE | AZ8: NO | BA8: ACTIVO | BB8: RBYP22 | BC8: NISSAN | BD8: KICKS 1.6 | BE8: 2021 | BF8: 2021
A9: 1447663 | B9: 442 | D9: 8889221 | F9: PHOENIX | G9: JUDICIAL | H9: 366-730 | I9: 366-730 | J9: CASTIGO | K9: COBRANZA | L9: 46180 | N9: 12756661 | O9: 5 | P9: RODRIGO HERNÁN COVARRUBIAS NANNIG | R9: 337.74 | S9: 45662 | W9: TANNER | X9: DACIÓN | Y9: 0 | Z9: 0 | AC9: 8889221 | AH9: CASTIGO | AI9: 995471634 | AL9: rodrigo.covarrubias75@gmail.com | AO9: PASAJE VALENZUELA 75 | AP9: FRUTILLAR | AQ9: X REGION | AR9: C-19067-2024 | AS9: 5º Juzgado Civil de Santiago | AT9: EMBARGADO | AU9: MANTIENE | AZ9: SI | BA9: ACTIVO | BB9: PZTC67 | BC9: OPEL | BD9: GRANDLAND 1.6 AUT | BE9: 2021 | BF9: 2021
A10: 1479919 | B10: 258 | D10: 4032000 | F10: PHOENIX | G10: JUDICIAL | H10: 0-365 | I10: 0-365 | J10: CASTIGO | K10: COBRANZA | L10: 46180 | N10: 8878648 | O10: 3 | P10: JORGE ORLANDO CIFUENTES LARA CIFUENTES LARA | R10: 209.325 | S10: 45668 | W10: TANNER | X10: DACIÓN | Y10: 0 | Z10: 0 | AC10: 4032000 | AH10: CASTIGO | AI10: 997950973 | AL10: YOHAIROCIFUENTES@GMAIL.COM | AO10: PASAJE ANCALLE 0372 | AP10: TEMUCO | AQ10: IX REGION | AR10: C-3900-2025 | AS10: 2º Juzgado Civil de Santiago | AT10: INGRESADO | AU10: MANTIENE | AZ10: NO | BA10: ACTIVO | BB10: RBRC21 | BC10: CHANGAN | BD10: NEW CS15 ELITE HB 1.5 AUT | BE10: 2021 | BF10: 2021
A11: 1493544 | B11: 228 | D11: 10161255 | F11: PHOENIX | G11: JUDICIAL | H11: 0-365 | I11: 0-365 | J11: CASTIGO | K11: COBRANZA | L11: 46180 | N11: 15621497 | O11: 3 | P11: PAULINA ANDREA HENRÍQUEZ TELLO | R11: 497.856 | S11: 45669 | W11: TANNER | X11: DACIÓN | Y11: 0 | Z11: 0 | AC11: 10161255 | AH11: CASTIGO | AI11: 968731785 | AL11: PHENRIQUEZTELLO@GMAIL.COM | AO11: Lomas de Catapilco sito 58, Zapallar | AP11: ZAPALLAR | AQ11: V REGION | AR11: C-3900-2025 | AS11: 27º Juzgado Civil de Santiago | AT11: EMBARGADO | AU11: MANTIENE | AZ11: SI | BA11: ACTIVO | BB11: KVJW91 | BC11: PEUGEOT | BD11: 3008 GT LINE 1.6 | BE11: 2019 | BF11: 2019
A12: 1494440 | B12: 138 | D12: 3819552 | F12: PHOENIX | G12: JUDICIAL | H12: 0-365 | I12: 0-365 | J12: CASTIGO | K12: COBRANZA | L12: 46180 | M12: E | N12: 14085342 | O12: 9 | P12: MIGUEL ANGEL VERA LOPEZ | R12: 155.319 | S12: 46025 | W12: TANNER | X12: DACIÓN | Y12: 0 | Z12: 0 | AC12: 3819552 | AH12: CASTIGO | AI12: 978991743 | AL12: ANGEL.VERA.LOPEZ797@GMAIL.COM | AO12: BILBAO 654 | AP12: OSORNO | AQ12: X REGION | AR12: C-8325-2025 | AS12: 20º Juzgado Civil de Santiago | AT12: EMBARGADO | AU12: MANTIENE | AZ12: SI | BA12: ACTIVO | BB12: RFVK52 | BC12: JAC | BD12: JS2 1.5 | BE12: 2022 | BF12: 2022
A13: 1524638 | B13: 228 | D13: 3499999 | F13: PHOENIX | G13: JUDICIAL | H13: 0-365 | I13: 0-365 | J13: CASTIGO | K13: COBRANZA | L13: 46180 | N13: 12712897 | O13: 9 | P13: DENISE DE LOURDES ARTEAGA GÓMEZ | R13: 358.441 | S13: 45669 | W13: CREDINISSAN | X13: DACIÓN | Y13: 0 | Z13: 0 | AC13: 2624999 | AE13: PUT EN CUOTAS | AF13: PHOENIX | AH13: CASTIGO | AI13: 998656256 | AL13: DENISEARTEAGA@GMAIL.COM | AO13: SANTA INES 1060 | AP13: PUERTO MONTT | AQ13: X REGION | AR13: C-19078-2024 | AS13: 26º Juzgado Civil de Santiago | AT13: INGRESADO | AU13: MANTIENE | AZ13: NO | BA13: ACTIVO | BB13: RHPP76 | BC13: NISSAN | BD13: X TRAIL CVT 2.5 AT | BE13: 2022 | BF13: 2022
A14: 1530466 | B14: 411 | D14: 4391250 | F14: PHOENIX | G14: JUDICIAL | H14: 366-730 | I14: 366-730 | J14: CASTIGO | K14: COBRANZA | L14: 46180 | N14: 15741073 | O14: 3 | P14: YANIRA ANDREA CHELMES ARAYA | R14: 201.502 | S14: 45663 | W14: TANNER | X14: DACIÓN | Y14: 0 | Z14: 0 | AC14: 4391250 | AH14: CASTIGO | AI14: 948905338 | AL14: YANIRACHELMES38@GMAIL.COM | AO14: PUERTO VARAS 1144 | AP14: COQUIMBO | AQ14: IV REGION | AR14: C-19095-2024 | AS14: 30º JUZGADO CIVIL DE SANTIAGO | AT14: EMBARGADO | AU14: MANTIENE | AW14: TERMINADO | AX14: PAGO TOTAL | AY14: 13-07-2026 | AZ14: SI | BA14: CERRADO | BB14: RHZV90 | BC14: JAC | BD14: JS2 1.5 | BE14: 2021 | BF14: 2021
A15: 1540238 | B15: 77 | D15: 6394950 | F15: PHOENIX | G15: JUDICIAL | H15: 0-365 | I15: 0-365 | J15: CASTIGO | K15: COBRANZA | L15: 46180 | M15: E | N15: 16552562 | O15: 0 | P15: GUILLERMO ANDRES BAHAMONDES LORCA | R15: 344.325 | S15: 46027 | W15: TANNER | X15: DACIÓN | Y15: 0 | Z15: 0 | AC15: 6394950 | AH15: CASTIGO | AI15: 948571269 | AL15: GUILLERMOBAHAMONDESLORCA@GMAIL.COM | AO15: LOS ATACAMEÑOS 2577 | AP15: RENCA | AQ15: REGION METROPOLITANA | AR15: C-20327-2024 | AS15: 23º JUZGADO CIVIL DE SANTIAGO | AT15: EMBARGADO | AU15: MANTIENE | AZ15: SI | BA15: ACTIVO | BB15: RFYY61 | BC15: RENAULT | BD15: OROCH OTTO 2.0 | BE15: 2022 | BF15: 2022
A16: 1542074 | B16: 319 | D16: 6733739 | F16: PHOENIX | G16: JUDICIAL | H16: 0-365 | I16: 0-365 | J16: CASTIGO | K16: COBRANZA | L16: 46180 | N16: 10887679 | O16: 4 | P16: ELIZABETH CRISTINA ROSALES HEREDIA | R16: 268.871 | S16: 45666 | W16: CREDINISSAN | X16: DACIÓN | Y16: 0 | Z16: 0 | AC16: 6733739 | AH16: CASTIGO | AI16: 995635971 | AL16: ELITA.ROSA@HOTMAIL.COM | AO16: PASAJE RIO BLANCO 1376 | AP16: COQUIMBO | AQ16: IV REGION | AR16: C-20314-2024 | AS16: 9º Juzgado Civil de Santiago | AT16: INGRESADO | AU16: MANTIENE | AZ16: NO | BA16: ACTIVO | BB16: RFVW10 | BC16: NISSAN | BD16: QASHQAI J11 2.0 | BE16: 2022 | BF16: 2022
A17: 1563013 | B17: 411 | D17: 4818807 | F17: PHOENIX | G17: JUDICIAL | H17: 366-730 | I17: 366-730 | J17: CASTIGO | K17: COBRANZA | L17: 46180 | N17: 19902496 | O17: 5 | P17: DIEGO FRANCISCO OLGUIN TARIFEÑO | R17: 223.059 | S17: 45663 | W17: TANNER | Y17: 0 | Z17: 0 | AC17: 794218 | AH17: CASTIGO | AI17: 988691761 | AL17: DIEGOOLGUIN01@GMAIL.COM | AO17: SAN ALFONSO 741 | AQ17: REGION METROPOLITANA | AR17: C-19061-2024 | AS17: 1º Juzgado Civil de Santiago | AT17: GIRO CHEQUE | AU17: MANTIENE | AZ17: SI | BA17: ACTIVO | BB17: RKBZ50 | BC17: JAC | BD17: JS2 HATCHBACK 1.5 | BE17: 2022 | BF17: 2022
A18: 1571122 | B18: 258 | D18: 5920000 | F18: PHOENIX | G18: JUDICIAL | H18: 0-365 | I18: 0-365 | J18: CASTIGO | K18: COBRANZA | L18: 46180 | N18: 11641745 | O18: 6 | P18: ANA PAULA GUAJARDO CORDOVA | R18: 275.628 | S18: 45668 | W18: TANNER | Y18: 0 | Z18: 0 | AC18: 676430 | AE18: PLAN DE PAGO | AF18: PHOENIX | AH18: CASTIGO | AI18: 959863045 | AL18: ANA.GUA.COR29@GMAIL.COM | AO18: PASAJE DANCING 5875 | AQ18: REGION METROPOLITANA | AR18: C-3908-2025 | AS18: 26º Juzgado Civil de Santiago | AT18: INGRESADO | AU18: MANTIENE | AZ18: NO | BA18: ACTIVO | BB18: RGZP22 | BC18: CHANGAN | BD18: CS55 ELITE 1.5 AUT | BE18: 2022 | BF18: 2022
A19: 1579447 | B19: 258 | D19: 3774859 | F19: PHOENIX | G19: JUDICIAL | H19: 0-365 | I19: 0-365 | J19: CASTIGO | K19: COBRANZA | L19: 46180 | N19: 18563424 | O19: 8 | P19: ALBERTO FERNANDO MANUEL ALVAREZ VICENCIO | R19: 218.859 | S19: 45668 | W19: TANNER | X19: DACIÓN | Y19: 0 | Z19: 0 | AC19: 3774859 | AH19: CASTIGO | AI19: 962903608 | AL19: lhise.alisdy5@gmail.com | AO19: LAS COIMAS SECTOR LA CANCHA N 4 | AQ19: V REGION | AR19: C-3899-2025 | AS19: 2º Juzgado Civil de Santiago | AT19: EMBARGADO | AU19: MANTIENE | AZ19: SI | BA19: ACTIVO | BB19: RJRF92 | BC19: CHANGAN | BD19: NEW CS 15 LUXURY MT | BE19: 2022 | BF19: 2022
A20: 1585963 | B20: 381 | D20: 6878855 | F20: PHOENIX | G20: JUDICIAL | H20: 366-730 | I20: 366-730 | J20: CASTIGO | K20: COBRANZA | L20: 46180 | N20: 18051143 | O20: 1 | P20: ANGELA ALEJANDRA REBECO PEREZ | R20: 209.574 | S20: 45664 | W20: TANNER | X20: DACIÓN | Y20: 0 | Z20: 0 | AC20: 6878855 | AH20: CASTIGO | AI20: 971792389 | AL20: ANGELAREBECOF@GMAIL.COM | AO20: PASAJE ANTOFAGASTA 2161 | AQ20: REGION METROPOLITANA | AR20: C-20323-2024 | AS20: 26º Juzgado Civil de Santiago | AT20: EMBARGADO | AU20: MANTIENE | AZ20: SI | BA20: ACTIVO | BB20: RHJR26 | BC20: JAC | BD20: JS4 LUXURY HB 1.5 | BE20: 2022 | BF20: 2022
A21: 1603752 | B21: 228 | D21: 3882712 | F21: PHOENIX | G21: JUDICIAL | H21: 0-365 | I21: 0-365 | J21: CASTIGO | K21: COBRANZA | L21: 46180 | N21: 26445123 | O21: K | P21: EDDY SIMON . 0 | R21: 206.712 | S21: 45669 | W21: TANNER | X21: DACIÓN | Y21: 0 | Z21: 0 | AC21: 3882712 | AH21: CASTIGO | AI21: 985379739 | AL21: EDDYSIMON413@GMAIL.COM | AO21: LOS INGLESES 166 | AQ21: REGION METROPOLITANA | AR21: C-5510-2025 | AS21: 17º Juzgado Civil de Santiago | AT21: EMBARGADO | AU21: MANTIENE | AZ21: SI | BA21: ACTIVO | BB21: RLCK51 | BC21: JAC | BD21: JS2 HATCHBACK 1.5 | BE21: 2022 | BF21: 2022
A22: 1609974 | B22: 197 | D22: 3596000 | F22: PHOENIX | G22: JUDICIAL | H22: 0-365 | I22: 0-365 | J22: CASTIGO | K22: COBRANZA | L22: 46180 | N22: 26454470 | O22: K | P22: JORGE ANTONIO SERRANO HERNANDEZ | R22: 182.095 | S22: 46023 | W22: TANNER | X22: DACIÓN | Y22: 0 | Z22: 0 | AC22: 3596000 | AH22: CASTIGO | AI22: 933189626 | AL22: JORGESE1806@GMAIL.COM | AO22: BALMACEDA 749 | AQ22: V REGION | AR22: C-6726-2025 | AS22: 19º Juzgado Civil de Santiago | AT22: INGRESADO | AU22: MANTIENE | AZ22: NO | BA22: ACTIVO | BB22: RJTL81 | BC22: HYUNDAI | BD22: VERNA CB 1.4 | BE22: 2022 | BF22: 2022
A23: 1638465 | B23: 411 | D23: 3871396 | F23: PHOENIX | G23: JUDICIAL | H23: 366-730 | I23: 366-730 | J23: CASTIGO | K23: COBRANZA | L23: 46180 | N23: 27070326 | O23: 7 | P23: LIBIA ROSA VERA TUBIÑEZ | R23: 198.55 | S23: 45663 | W23: TANNER | Y23: 0 | Z23: 0 | AC23: 1254198 | AE23: PLAN DE PAGO | AF23: PHOENIX | AH23: CASTIGO | AI23: 962588898 | AL23: LIBIA.VERA1@GMAIL.COM | AO23: ALCALDE MANUEL HUICHIPOCO 422 | AQ23: REGION METROPOLITANA | AR23: C-19071-2024 | AS23: 3º Juzgado Civil de Santiago | AT23: INGRESADO | AU23: SUSPENDIDO | AZ23: NO | BA23: SUSPENDIDO | BB23: RKHK18 | BC23: SUZUKI | BD23: S PRESSO HB 1.0 | BE23: 2022 | BF23: 2022
A24: 1642440 | B24: 381 | D24: 14121919 | F24: PHOENIX | G24: JUDICIAL | H24: 366-730 | I24: 366-730 | J24: CASTIGO | K24: COBRANZA | L24: 46180 | N24: 16121390 | O24: K | P24: NICOLAS PATRICIO ARRAU SOTO | R24: 460.816 | S24: 45664 | W24: TANNER | X24: DACIÓN | Y24: 0 | Z24: 0 | AC24: 14121919 | AH24: CASTIGO | AI24: 994898377 | AL24: nicoarrau@gmail.com | AO24: MANQUEHUE NORTE 1635 DPTO 104 | AQ24: REGION METROPOLITANA | AR24: C-21660-2024 | AS24: 24º Juzgado Civil de Santiago | AT24: EMBARGADO | AU24: MANTIENE | AZ24: SI | BA24: ACTIVO | BB24: RKXF13 | BC24: MAZDA | BD24: NEW CX 5 R 2.0 AWD 6A | BE24: 2022 | BF24: 2022
A25: 1644932 | B25: 442 | D25: 4868802 | F25: PHOENIX | G25: JUDICIAL | H25: 366-730 | I25: 366-730 | J25: CASTIGO | K25: COBRANZA | L25: 46180 | N25: 16002296 | O25: 5 | P25: MIGUEL ANGEL ACEVEDO ARAVENA | R25: 196.978 | S25: 45662 | W25: TANNER | X25: DACIÓN | Y25: 0 | Z25: 0 | AC25: 2974002 | AE25: PLAN DE PAGO | AF25: PHOENIX | AH25: CASTIGO | AI25: 9987229864 | AL25: MACEVEDOAR@GMAIL.COM | AO25: 30 SUR 19 PONIENTE NÂ°38 | AQ25: VII REGION | AR25: 4º Juzgado Civil de Santiago | AS25: C-16642-2024 | AT25: EMBARGADO | AU25: SUSPENDIDO | AZ25: SI | BA25: SUSPENDIDO | BB25: RJSW95 | BC25: CHANGAN | BD25: ALSVIN LUXURY MT | BE25: 2022 | BF25: 2022
A26: 1645952 | B26: 1 | D26: 9019928 | F26: PHOENIX | G26: JUDICIAL | H26: 0-365 | I26: 0-365 | J26: CASTIGO | K26: COBRANZA | L26: 46180 | M26: E | N26: 15189992 | O26: 7 | P26: ERIK MARCELO ABURTO MORAGA | R26: 381.241 | S26: 46028 | W26: TANNER | Y26: 0 | Z26: 0 | AC26: 9019928 | AH26: CASTIGO | AI26: 977573123 | AL26: ERIK.SERVICIOSCAMIONGRUA@GMAIL.COM | AO26: AVENIDA FEDERICO SCHWAGER 2835 | AQ26: VIII REGION | AR26: C-4685-2025 | AS26: 24º Juzgado Civil de Santiago | AT26: INGRESADO | AU26: MANTIENE | AZ26: NO | BA26: ACTIVO | BB26: RSWR55 | BC26: GREAT WALL | BD26: POER 4X4 2.0 | BE26: 2022 | BF26: 2022
A27: 1670767 | B27: 166 | D27: 6378399 | F27: PHOENIX | G27: JUDICIAL | H27: 0-365 | I27: 0-365 | J27: CASTIGO | K27: COBRANZA | L27: 46180 | N27: 17484899 | O27: 8 | P27: ANGÉLICA ESTER NARVÁEZ CASTRO | R27: 337.109 | S27: 46024 | W27: CREDINISSAN | Y27: 0 | Z27: 0 | AC27: 2385892 | AH27: CASTIGO | AI27: 945865081 | AL27: ANGELICA.NAR.CAS@GMAIL.COM | AO27: VIOLETA PARRA 1954 DPTO. I 212 | AP27: LA PINTANA | AQ27: REGION METROPOLITANA | AR27: C-8323-2025 | AS27: 28º Juzgado Civil de Santiago | AT27: GIRO CHEQUE | AU27: MANTIENE | AZ27: SI | BA27: ACTIVO | BB27: RRJV47 | BC27: NISSAN | BD27: SENTRA MT 2.0 | BE27: 2022 | BF27: 2022
A28: 1700218 | B28: 166 | D28: 6879999 | F28: PHOENIX | G28: JUDICIAL | H28: 0-365 | I28: 0-365 | J28: CASTIGO | K28: COBRANZA | L28: 46180 | N28: 12218160 | O28: K | P28: JUAN ALEX OLIVARES ALANO | R28: 362.214 | S28: 46024 | W28: CREDINISSAN | X28: DACIÓN | Y28: 0 | Z28: 0 | AC28: 5108469 | AE28: PLAN DE PAGO | AF28: PHOENIX | AH28: CASTIGO | AI28: 957500333 | AL28: OLIVARESALANO@GMAIL.COM | AO28: FERNANDO DE AGUIRRE 850 POBLACIÓN CARTAVIO | AP28: COPIAPO | AQ28: III REGION | AR28: 25º Juzgado Civil de Santiago | AS28: C-15693-2024 | AT28: INGRESADO | AU28: MANTIENE | AZ28: NO | BA28: ACTIVO | BB28: RKRY65 | BC28: NISSAN | BD28: KICKS CVT 1.6 AUT | BE28: 2022 | BF28: 2022
A29: 1721051 | B29: 350 | D29: 9984524 | F29: PHOENIX | G29: JUDICIAL | H29: 0-365 | I29: 0-365 | J29: CASTIGO | K29: COBRANZA | L29: 46180 | N29: 16409957 | O29: 1 | P29: ROBERTO CARLOS NEER CERDA | R29: 313.969 | S29: 45665 | W29: TANNER | X29: DACIÓN | Y29: 0 | Z29: 0 | AC29: 9984524 | AH29: CASTIGO | AI29: 93241652 | AL29: rc.neer@gmail.com | AO29: PASAJE LOS ARAUCANOS 01351 | AP29: PUENTE ALTO | AQ29: REGION METROPOLITANA | AR29: C-22132-2024 | AS29: 25º Juzgado Civil de Santiago | AT29: EMBARGADO | AU29: MANTIENE | AZ29: SI | BA29: ACTIVO | BB29: RRRF12 | BC29: JAC | BD29: T8 XE ADVANCE 2.0 | BE29: 2022 | BF29: 2022
A30: 1729656 | B30: 411 | D30: 4994124 | F30: PHOENIX | G30: JUDICIAL | H30: 366-730 | I30: 366-730 | J30: CASTIGO | K30: COBRANZA | L30: 46180 | N30: 13621515 | O30: 9 | P30: VERÓNICA DE LAS MERCEDES SAN MARTÍN LAGOS | R30: 256.836 | S30: 45663 | W30: TANNER | X30: DACIÓN | Y30: 0 | Z30: 0 | AC30: 4994124 | AH30: CASTIGO | AI30: 991355756 | AL30: VERONICASANMARTINLAGOS@GMAIL.COM | AO30: CONDE DEL MAULE 668 | AP30: CHILLAN VIEJO | AQ30: XVI REGION | AR30: C-19071-2024 | AS30: 29º Juzgado Civil de Santiago | AT30: INGRESADO | AU30: MANTIENE | AZ30: NO | BA30: ACTIVO | BB30: HYCV69 | BC30: HYUNDAI | BD30: ACCENT RB 1.4 | BE30: 2016 | BF30: 2016
A31: 1735638 | B31: 197 | D31: 4850702 | F31: PHOENIX | G31: JUDICIAL | H31: 0-365 | I31: 0-365 | J31: CASTIGO | K31: COBRANZA | L31: 46180 | N31: 15656935 | O31: 6 | P31: RAMÓN ALONSO VÁSQUEZ BUSTOS | R31: 347.26 | S31: 46023 | W31: TANNER | X31: DACIÓN | Y31: 0 | Z31: 0 | AC31: 4850702 | AE31: PLAN DE PAGO | AF31: PHOENIX | AH31: CASTIGO | AI31: 9930097642 | AL31: Herramientasramon1@gmail.com | AO31: LOS CULTIVADORES 0563 | AP31: TEMUCO | AQ31: IX REGION | AR31: C-19068-2024 | AS31: 21º Juzgado Civil de Santiago | AT31: INGRESADO | AU31: MANTIENE | AZ31: NO | BA31: ACTIVO | BB31: GWYT99 | BC31: FORD | BD31: ESCAPE 2.5 AUT | BE31: 2015 | BF31: 2015
A32: 1746743 | B32: 472 | D32: 4502714 | F32: PHOENIX | G32: JUDICIAL | H32: 366-730 | I32: 366-730 | J32: CASTIGO | K32: COBRANZA | L32: 46180 | N32: 26896838 | O32: 5 | P32: GERMAN ANTONIO GONZALEZ SANCHEZ | R32: 197.007 | S32: 45661 | W32: TANNER | X32: DACIÓN | Y32: 0 | Z32: 0 | AC32: 4502714 | AH32: CASTIGO | AI32: 9935804367 | AL32: iramandarcia@gmail.com | AO32: AV. ESCUELA AGRICOLA 1710 DEPTO 1605 | AP32: MACUL | AQ32: REGION METROPOLITANA | AR32: 19º Juzgado Civil de Santiago | AS32: C-15713-2024 | AT32: EMBARGADO | AU32: MANTIENE | AZ32: SI | BA32: ACTIVO | BB32: RRKJ66 | BC32: SUZUKI | BD32: ALTO 800 GLX AC | BE32: 2022 | BF32: 2022
A33: 1749842 | B33: 166 | D33: 4940063 | F33: PHOENIX | G33: JUDICIAL | H33: 0-365 | I33: 0-365 | J33: CASTIGO | K33: COBRANZA | L33: 46180 | N33: 16823710 | O33: 3 | P33: REINALDO DAVID ALCAMÁN HUENULAF | R33: 380.198 | S33: 46024 | W33: CREDINISSAN | X33: DACIÓN | Y33: 0 | Z33: 0 | AC33: 4940063 | AH33: CASTIGO | AI33: 981496520 | AL33: reypausa@gmail.com | AO33: PATRICIO LINCH 1040 DEPARTAMENTO 105 | AP33: TEMUCO | AQ33: IX REGION | AR33: C-8327-2025 | AS33: 16º Juzgado Civil de Santiago | AT33: EMBARGADO | AU33: MANTIENE | AZ33: SI | BA33: ACTIVO | BB33: RRYZ76 | BC33: NISSAN | BD33: SENTRA MT 2.0 | BE33: 2022 | BF33: 2022
A34: 1752476 | B34: 411 | D34: 6198242 | F34: PHOENIX | G34: JUDICIAL | H34: 366-730 | I34: 366-730 | J34: CASTIGO | K34: COBRANZA | L34: 46180 | N34: 18957719 | O34: 2 | P34: PEDRO GERMAN ESPINOZA MUÑOZ | R34: 190.562 | S34: 45663 | W34: TANNER | X34: DACIÓN | Y34: 0 | Z34: 0 | AC34: 6198242 | AH34: CASTIGO | AI34: 978819922 | AL34: pedro_name@hotmail.com | AO34: CALLE 2 CASA 749 BOCA SUR | AP34: SAN PEDRO DE LA PAZ | AQ34: VIII REGION | AR34: C-19074-2024 | AS34: 10º Juzgado Civil de Santiago | AT34: EMBARGADO | AU34: MANTIENE | AZ34: SI | BA34: ACTIVO | BB34: RTRZ90 | BC34: CHANGAN | BD34: ALSVIN 1.4 | BE34: 2022 | BF34: 2022
A35: 1763682 | B35: 228 | D35: 6001534 | F35: PHOENIX | G35: JUDICIAL | H35: 0-365 | I35: 0-365 | J35: CASTIGO | K35: COBRANZA | L35: 46180 | N35: 17941976 | O35: 9 | P35: HANS ALEXANDER BÓRQUEZ CHACANA | R35: 401.782 | S35: 45669 | W35: TANNER | X35: DACIÓN | Y35: 0 | Z35: 0 | AC35: 6001534 | AH35: CASTIGO | AI35: 965291697 | AL35: THRON.7@LIVE.COM | AO35: AVENIDA CARLOS VALDOVINOS 1055 DEPTO. 187 | AP35: SAN MIGUEL | AQ35: REGION METROPOLITANA | AR35: C-5508-2025 | AS35: 3º Juzgado Civil de Santiago | AT35: EMBARGADO | AU35: MANTIENE | AZ35: SI | BA35: ACTIVO | BB35: JCRV58 | BC35: MERCEDES BENZ | BD35: A200 D | BE35: 2016 | BF35: 2016
A36: 1769156 | B36: 472 | D36: 7241243 | F36: PHOENIX | G36: JUDICIAL | H36: 366-730 | I36: 366-730 | J36: CASTIGO | K36: COBRANZA | L36: 46180 | N36: 7710884 | O36: K | P36: MARÍA ANGÉLICA VERGARA SILVA | R36: 330.069 | S36: 45661 | W36: TANNER | X36: DACIÓN | Y36: 0 | Z36: 0 | AC36: 2765723 | AE36: PLAN DE PAGO | AF36: PHOENIX | AH36: CASTIGO | AI36: 944758247 | AL36: janomarver1974@gmail.com | AO36: HORNILLAS 01651 | AP36: PUNTA ARENAS | AQ36: XII REGION | AR36: 9º Juzgado Civil de Santiago | AS36: C-16645-2024 | AT36: INGRESADO | AU36: SUSPENDIDO | AZ36: NO | BA36: SUSPENDIDO | BB36: RPYY87 | BC36: HYUNDAI | BD36: SANTA FE 2.0 AUT | BE36: 2014 | BF36: 2014
A37: 1777539 | B37: 166 | D37: 9123246 | F37: PHOENIX | G37: JUDICIAL | H37: 0-365 | I37: 0-365 | J37: CASTIGO | K37: COBRANZA | L37: 46180 | N37: 12002438 | O37: 8 | P37: LUIS FRANCISCO JAVIER ESCOBAR MUÑOZ | R37: 375.18 | S37: 46024 | W37: TANNER | X37: DACIÓN | Y37: 0 | Z37: 0 | AC37: 9123246 | AH37: CASTIGO | AI37: 56995083890 | AL37: LFJAVIER69@HOTMAIL.COM | AO37: ANDES 1506 | AQ37: III REGION | AR37: C-8325-2025 | AS37: 4º JUZGADO CIVIL DE SANTIAGO | AT37: INGRESADO | AU37: MANTIENE | AZ37: NO | BA37: ACTIVO | BB37: KSRX96 | BC37: JEEP | BD37: RENEGADE SPORT 1.8 | BE37: 2019 | BF37: 2019
A38: 1782538 | B38: 350 | D38: 5247436 | F38: PHOENIX | G38: JUDICIAL | H38: 0-365 | I38: 0-365 | J38: CASTIGO | K38: COBRANZA | L38: 46180 | N38: 16174268 | O38: 6 | P38: JACQUELINE ANDREA GONZÁLEZ CALDERON | R38: 258.197 | S38: 45665 | W38: TANNER | X38: DACIÓN | Y38: 0 | Z38: 0 | AC38: 5247436 | AH38: CASTIGO | AI38: 953673166 | AL38: JAGONZALEZC@MALLCENTER.CL | AO38: AFLUENTE 1932 | AQ38: REGION METROPOLITANA | AR38: C-22302-2024 | AS38: 22º Juzgado Civil de Santiago | AT38: EMBARGADO | AU38: MANTIENE | AZ38: SI | BA38: ACTIVO | BB38: LPFT73 | BC38: KIA MOTORS | BD38: MORNING EX 1.2 | BE38: 2019 | BF38: 2019
A39: 1783098 | B39: 411 | D39: 5978132 | F39: PHOENIX | G39: JUDICIAL | H39: 366-730 | I39: 366-730 | J39: CASTIGO | K39: COBRANZA | L39: 46180 | N39: 15642246 | O39: 0 | P39: EVELYN ALEJANDRA AHUMADA PADILLA | R39: 272.819 | S39: 45663 | W39: TANNER | Y39: 0 | Z39: 0 | AC39: 2471892 | AH39: CASTIGO | AI39: 958355504 | AL39: e.ahumadapadilla@gmail.com | AO39: romerillo 3735 | AP39: PUENTE ALTO | AQ39: REGION METROPOLITANA | AR39: 2º Juzgado Civil de Santiago | AS39: C-16646-2024 | AT39: GIRO CHEQUE | AU39: MANTIENE | AZ39: SI | BA39: ACTIVO | BB39: JJTF54 | BC39: NISSAN | BD39: VERSA SENSE 1.6 AUT | BE39: 2017 | BF39: 2017
A40: 1791083 | B40: 503 | D40: 7569433 | F40: PHOENIX | G40: JUDICIAL | H40: 366-730 | I40: 366-730 | J40: CASTIGO | K40: COBRANZA | L40: 46180 | N40: 15236244 | O40: 7 | P40: RUBÉN ANER CARILAO BARRA | R40: 322.355 | S40: 45660 | W40: TANNER | X40: DACIÓN | Y40: 0 | Z40: 0 | AC40: 5474529 | AE40: PLAN DE PAGO | AF40: PHOENIX | AH40: CASTIGO | AI40: 968259519 | AL40: rubenaner@gmail.com | AO40: La Huasca 10834 | AP40: LA FLORIDA | AQ40: REGION METROPOLITANA | AR40: 16º Juzgado Civil de Santiago | AS40: C-16644-2024 | AT40: EMBARGADO | AU40: SUSPENDIDO | AW40: SUSPENDER | AX40: PLAN DE PAGO | AY40: 13-07-2026 | AZ40: SI | BA40: SUSPENDIDO | BB40: RTFH40 | BC40: KYC | BD40: X5 DCAB 1.5 | BE40: 2022 | BF40: 2022
A41: 1797742 | B41: 442 | D41: 6783925 | F41: PHOENIX | G41: JUDICIAL | H41: 366-730 | I41: 366-730 | J41: CASTIGO | K41: COBRANZA | L41: 46180 | N41: 9082995 | O41: 5 | P41: JOSÉ ENRIQUE HUENCHUCHEO REMOLCOY | R41: 310.22 | S41: 45662 | W41: TANNER | X41: DACIÓN | Y41: 0 | Z41: 0 | AC41: 6783925 | AH41: CASTIGO | AI41: 959935957 | AL41: electricidad.joseh@gmail.com | AO41: POB. CORVI CALLE JOSE ABELARDO NUÑEZ 127 | AP41: LLANQUIHUE | AQ41: X REGION | AR41: 11º Juzgado Civil de Santiago | AS41: C-16643-2024 | AT41: INGRESADO | AU41: MANTIENE | AZ41: NO | BA41: ACTIVO | BB41: RRTS57 | BC41: FOTON | BD41: TM3 1.5 | BE41: 2022 | BF41: 2022
A42: 1811663 | B42: 350 | D42: 8662240 | F42: PHOENIX | G42: JUDICIAL | H42: 0-365 | I42: 0-365 | J42: CASTIGO | K42: COBRANZA | L42: 46180 | N42: 26030033 | O42: 4 | P42: ANDRE TERTULIEN 0 TERTULIEN 0 | R42: 285.382 | S42: 45665 | W42: TANNER | X42: DACIÓN | Y42: 0 | Z42: 0 | AC42: 8662240 | AH42: CASTIGO | AI42: 950665878 | AL42: andrestertu@gmail.com | AO42: CALLE TRES MONTE 714 DPTO 306 | AP42: QUILICURA | AQ42: REGION METROPOLITANA | AR42: C-22134-2024 | AS42: 1º Juzgado Civil de Santiago | AT42: EMBARGADO | AU42: MANTIENE | AZ42: SI | BA42: ACTIVO | BB42: RVDH69 | BC42: HYUNDAI | BD42: VERNA CB 1.4 MT PLUS | BE42: 2022 | BF42: 2022
A43: 1811675 | B43: 381 | D43: 7827655 | F43: PHOENIX | G43: JUDICIAL | H43: 366-730 | I43: 366-730 | J43: CASTIGO | K43: COBRANZA | L43: 46180 | N43: 16347411 | O43: 5 | P43: OSCAR HERNAN ORTIZ GEELL | R43: 263.906 | S43: 45664 | W43: TANNER | Y43: 0 | Z43: 0 | AC43: 4052835 | AH43: CASTIGO | AI43: 986990937 | AL43: oscarhortiz@gmail.com | AO43: OFICINA LASTENIA 11850 | AP43: ANTOFAGASTA | AQ43: II REGION | AR43: C-20314-2024 | AS43: 22º Juzgado Civil de Santiago | AT43: GIRO CHEQUE | AU43: MANTIENE | AZ43: SI | BA43: ACTIVO | BB43: RVZW70 | BC43: RENAULT | BD43: KWID 1.0 | BE43: 2022 | BF43: 2022
A44: 1813320 | B44: 166 | D44: 5190592 | F44: PHOENIX | G44: JUDICIAL | H44: 0-365 | I44: 0-365 | J44: CASTIGO | K44: COBRANZA | L44: 46180 | N44: 12699843 | O44: 0 | P44: RODRIGO ALEJANDRO PEREZ BIZAMA | R44: 348.444 | S44: 46024 | W44: TANNER | X44: DACIÓN | Y44: 0 | Z44: 0 | AC44: 5190592 | AH44: CASTIGO | AI44: 972660024 | AL44: horion237@gmail.com | AO44: PASAJE PEDRO AGUIRRE CERDA S/N | AP44: PENCO | AQ44: VIII REGION | AR44: 3º Juzgado Civil de Santiago | AS44: C-15709-2024 | AT44: EMBARGADO | AU44: MANTIENE | AZ44: SI | BA44: ACTIVO | BB44: RTYF80 | BC44: CHANGAN | BD44: CX70 OTTO 1.6 | BE44: 2022 | BF44: 2022
A45: 1819340 | B45: 289 | D45: 13794259 | F45: PHOENIX | G45: JUDICIAL | H45: 0-365 | I45: 0-365 | J45: CASTIGO | K45: COBRANZA | L45: 46180 | N45: 16520746 | O45: 7 | P45: MIGUEL EDUARDO CURIQUEO CARRILLO | R45: 439.563 | S45: 45667 | W45: TANNER | X45: DACIÓN | Y45: 0 | Z45: 0 | AC45: 13794259 | AH45: CASTIGO | AI45: 56967693054 | AL45: ecuriqueocarrillo@gmail.com | AO45: PUERTA DEL SOL 1620 | AP45: CERRO NAVIA | AQ45: REGION METROPOLITANA | AR45: C-4783-2025 | AS45: 13º Juzgado Civil de Santiago | AT45: EMBARGADO | AU45: MANTIENE | AZ45: SI | BA45: ACTIVO | BB45: JSXW20 | BC45: FORD | BD45: EXPLORER 2.3 | BE45: 2022 | BF45: 2022
A46: 1830966 | B46: 228 | D46: 3845322 | F46: PHOENIX | G46: JUDICIAL | H46: 0-365 | I46: 0-365 | J46: CASTIGO | K46: COBRANZA | L46: 46180 | N46: 18790483 | O46: 8 | P46: JOSÉ LUIS VIA DORADO ALFARO | R46: 229.367 | S46: 45669 | W46: TANNER | Y46: 0 | Z46: 0 | AC46: 3845322 | AH46: CASTIGO | AI46: 973758127 | AL46: jviadorado@hotmail.com | AO46: AVENIDA ANTILHUE 1250 DEPTO 312 PISO 3 | AP46: ANTOFAGASTA | AQ46: II REGION | AR46: 18º Juzgado Civil de Santiago | AS46: C-15718-2024 | AT46: GIRO CHEQUE | AU46: MANTIENE | AZ46: SI | BA46: ACTIVO | BB46: HJLV54 | BC46: KIA MOTORS | BD46: RIO 5 EX 1.4 | BE46: 2015 | BF46: 2015
A47: 1836390 | B47: 77 | D47: 4910610 | F47: PHOENIX | G47: JUDICIAL | H47: 0-365 | I47: 0-365 | J47: CASTIGO | K47: COBRANZA | L47: 46180 | M47: E | N47: 17608529 | O47: 0 | P47: DANIEL ROBERTO MAIRA ARIAS | R47: 244.581 | S47: 46027 | W47: TANNER | X47: DACIÓN | Y47: 0 | Z47: 0 | AC47: 4910610 | AH47: CASTIGO | AI47: 996418216 | AL47: daniel_trd@hotmail.com | AO47: CALLE CASTRO 4165 | AP47: PUENTE ALTO | AQ47: REGION METROPOLITANA | AR47: C-13009-2025 | AS47: 11º Juzgado Civil de Santiago | AT47: EMBARGADO | AU47: MANTIENE | AZ47: SI | BA47: ACTIVO | BB47: LGPG81 | BC47: HAVAL | BD47: H2 ELITE 1.5 | BE47: 2019 | BF47: 2019
A48: 1859462 | B48: 411 | D48: 5987860 | F48: PHOENIX | G48: JUDICIAL | H48: 366-730 | I48: 366-730 | J48: CASTIGO | K48: COBRANZA | L48: 46180 | N48: 8253225 | O48: 0 | P48: MARIO GALLARDO NORIEGA | R48: 271.576 | S48: 45663 | W48: TANNER | X48: DACIÓN | Y48: 0 | Z48: 0 | AC48: 5987860 | AH48: CASTIGO | AI48: 976093422 | AL48: consuelonoriega1967@gmail.com | AO48: TOMAS YAVAR 667 | AP48: CHILLAN VIEJO | AQ48: XVI REGION | AR48: C-19072-2024 | AS48: 17º Juzgado Civil de Santiago | AT48: INGRESADO | AU48: MANTIENE | AZ48: NO | BA48: ACTIVO | BB48: RVKV87 | BC48: BAIC | BD48: X55FLTMT COMFORT | BE48: 2022 | BF48: 2022
A49: 1865019 | B49: 289 | D49: 6723725 | F49: PHOENIX | G49: JUDICIAL | H49: 0-365 | I49: 0-365 | J49: CASTIGO | K49: COBRANZA | L49: 46180 | N49: 25013996 | O49: 9 | P49: DANIEL LOPEZ GARCIA | R49: 292.369 | S49: 45667 | W49: TANNER | X49: DACIÓN | Y49: 0 | Z49: 0 | AC49: 6723725 | AH49: CASTIGO | AI49: 988545434 | AL49: DANIEL.LOPEZ345@GMAIL.COM | AO49: OFICINA SAN GREGORIO 195 | AP49: ANTOFAGASTA | AQ49: II REGION | AR49: C-2598-2025 | AS49: 29º Juzgado Civil de Santiago | AT49: EMBARGADO | AU49: MANTIENE | AZ49: SI | BA49: ACTIVO | BB49: RVRH84 | BC49: KIA | BD49: MORNING MPI 1.2 | BE49: 2022 | BF49: 2022
A50: 1867963 | B50: 350 | D50: 15022221 | F50: PHOENIX | G50: JUDICIAL | H50: 0-365 | I50: 0-365 | J50: CASTIGO | K50: COBRANZA | L50: 46180 | N50: 10631400 | O50: 4 | P50: ISABEL DEL CARMEN SANTIBÁÑEZ NEIRA | R50: 425.136 | S50: 45665 | W50: TANNER | X50: DACIÓN | Y50: 0 | Z50: 0 | AC50: 15022221 | AH50: CASTIGO | AI50: 993012461 | AL50: isabelneira645@gmail.com | AM50: isaabelcoco09@gmail.com | AO50: F30 CAMPAMENTO LAS GAVIOTAS CASA 12 | AP50: QUINTERO | AQ50: V REGION | AR50: C-22126-2024 | AS50: 28º Juzgado Civil de Santiago | AT50: EMBARGADO | AU50: MANTIENE | AZ50: SI | BA50: ACTIVO | BB50: RWBB51 | BC50: KIA | BD50: SPORTAGE EX DSL 2.0 AUT | BE50: 2022 | BF50: 2022
A51: 1882519 | B51: 197 | D51: 5542324 | F51: PHOENIX | G51: JUDICIAL | H51: 0-365 | I51: 0-365 | J51: CASTIGO | K51: COBRANZA | L51: 46180 | N51: 17624476 | O51: 3 | P51: MARIA IGNACIA GONZALEZ GAMBOA | R51: 330.641 | S51: 46023 | W51: TANNER | Y51: 0 | Z51: 0 | AC51: 1959984 | AH51: CASTIGO | AI51: 964720331 | AL51: ignacia@sapublicidad.cl | AO51: RIQUELME 604 | AP51: MELIPILLA | AQ51: REGION METROPOLITANA | AR51: C-20316-2024 | AS51: 10º Juzgado Civil de Santiago | AT51: GIRO CHEQUE | AU51: MANTIENE | AZ51: SI | BA51: ACTIVO | BB51: PCYB62 | BC51: RENAULT | BD51: SYMBOL 1.6 | BE51: 2020 | BF51: 2020
A52: 1891178 | B52: 258 | D52: 6382600 | F52: PHOENIX | G52: JUDICIAL | H52: 0-365 | I52: 0-365 | J52: CASTIGO | K52: COBRANZA | L52: 46180 | N52: 26313552 | O52: 0 | P52: WILLIAMS JOSE CHACIN MARTINEZ | R52: 301.1 | S52: 45668 | W52: TANNER | X52: DACIÓN | Y52: 0 | Z52: 0 | AC52: 6382600 | AE52: PLAN DE PAGO | AF52: PHOENIX | AH52: CASTIGO | AI52: 979125999 | AL52: LUISANNAISABELL@GMAIL.COM | AO52: PDTE SANTA MARIA 289 | AQ52: REGION METROPOLITANA | AR52: C-5521-2025 | AS52: 23º JUZGADO CIVIL DE SANTIAGO | AT52: EMBARGADO | AU52: MANTIENE | AZ52: SI | BA52: ACTIVO | BB52: RWZK66 | BC52: SUZUKI | BD52: BALENO GLS HB 1.4 | BE52: 2022 | BF52: 2022
A53: 1895109 | B53: 350 | D53: 9670566 | F53: PHOENIX | G53: JUDICIAL | H53: 0-365 | I53: 0-365 | J53: CASTIGO | K53: COBRANZA | L53: 46180 | N53: 15074249 | O53: 8 | P53: ROBERTO JESÚS CISTERNAS NÚÑEZ | R53: 367.057 | S53: 45665 | W53: CREDINISSAN | Y53: 0 | Z53: 0 | AC53: 9670566 | AH53: CASTIGO | AI53: 993897867 | AL53: ROJECINUZ@GMAIL.COM | AO53: CALLE BALMACEDA 5 | AP53: LOS ANDES | AQ53: V REGION | AR53: C-22139-2024 | AS53: 22º Juzgado Civil de Santiago | AT53: INCAUTADO | AU53: MANTIENE | AZ53: SI | BA53: ACTIVO | BB53: RWVX82 | BC53: NISSAN | BD53: X TRAIL T32 CVT 2.5 AUT | BE53: 2022 | BF53: 2022
A54: 1906037 | B54: 411 | D54: 11820205 | F54: PHOENIX | G54: JUDICIAL | H54: 366-730 | I54: 366-730 | J54: CASTIGO | K54: COBRANZA | L54: 46180 | N54: 17989439 | O54: 4 | P54: JORGE ABRAHAM YÁÑEZ MERIÑO | R54: 469.793 | S54: 45663 | W54: CREDINISSAN | X54: DACIÓN | Y54: 0 | Z54: 0 | AC54: 11820205 | AH54: CASTIGO | AI54: 944348344 | AL54: JORGEYANEZM25@GMAIL.COM | AO54: CRUCERO 2746 | AP54: CHILLAN | AQ54: XVI REGION | AR54: 01º Juzgado Civil de Santiago | AS54: C-15834-2024 | AT54: INGRESADO | AU54: MANTIENE | AZ54: NO | BA54: ACTIVO | BB54: RWXY15 | BC54: NISSAN | BD54: KICKS SENSE MC 1.6 MT | BE54: 2022 | BF54: 2022
A55: 1923591 | B55: 350 | D55: 11082144 | F55: PHOENIX | G55: JUDICIAL | H55: 0-365 | I55: 0-365 | J55: CASTIGO | K55: COBRANZA | L55: 46180 | N55: 16647012 | O55: 9 | P55: FABRICIO ALEJANDRO VALENZUELA LEIVA | R55: 375.735 | S55: 45665 | W55: TANNER | X55: DACIÓN | Y55: 0 | Z55: 0 | AC55: 7544089 | AE55: PLAN DE PAGO | AF55: PHOENIX | AH55: CASTIGO | AI55: 977915708 | AL55: fabricio.valenzuela.leiva@gmail.com | AO55: EL LLANO 9 | AP55: SAN BERNARDO | AQ55: REGION METROPOLITANA | AR55: C-22141-2024 | AS55: 29º Juzgado Civil de Santiago | AT55: INGRESADO | AU55: SUSPENDIDO | AW55: SUSPENDER | AX55: PLAN DE PAGO | AY55: 16-07-2026 | AZ55: NO | BA55: SUSPENDIDO | BB55: RXTT99 | BC55: JAC | BD55: T8 PRO DIESEL ADVANCE 4X4 2.0 | BE55: 2022 | BF55: 2022
A56: 1966918 | B56: 77 | D56: 6520106 | F56: PHOENIX | G56: JUDICIAL | H56: 0-365 | I56: 0-365 | J56: CASTIGO | K56: COBRANZA | L56: 46180 | M56: E | N56: 15167058 | O56: K | P56: CRISTIAN ALBERTO REYES INZUNZA | R56: 437.354 | S56: 46027 | W56: CREDINISSAN | X56: DACIÓN | Y56: 0 | Z56: 0 | AC56: 5020106 | AE56: PLAN DE PAGO | AF56: PHOENIX | AH56: CASTIGO | AI56: 995151597 | AL56: CRISTIAN.REYES.Y@GMAIL.COM | AO56: PASAJE EL NOGAL 4 VILLA ESPERANZA | AP56: CABRERO | AQ56: VIII REGION | AR56: C-3910-2025 | AS56: 11º Juzgado Civil de Santiago | AT56: EMBARGADO | AU56: REACTIVA | AW56: SUSPENDER | AX56: PLAN DE PAGO | AY56: 16-07-2026 | AZ56: SI | BA56: SUSPENDIDO | BB56: GPZV82 | BC56: NISSAN | BD56: SENTRA NEW SENSE MT | BE56: 2022 | BF56: 2022
A57: 1983306 | B57: 350 | D57: 11020924 | F57: PHOENIX | G57: JUDICIAL | H57: 0-365 | I57: 0-365 | J57: CASTIGO | K57: COBRANZA | L57: 46180 | N57: 11421231 | O57: 8 | P57: JORGE LEANDRO HERRERA OPAZO | R57: 483.249 | S57: 45665 | W57: TANNER | Y57: 0 | Z57: 0 | AC57: 8583549 | AH57: CASTIGO | AI57: 965349720 | AL57: rpiucoluribe@hotmail.com | AO57: CNO AY CHACABUCO S/N | AP57: AYSEN | AQ57: XI REGION | AR57: C-22140-2024 | AS57: 21º Juzgado Civil de Santiago | AT57: GIRO CHEQUE | AU57: MANTIENE | AZ57: SI | BA57: ACTIVO | BB57: SBKK55 | BC57: GREAT WALL | BD57: POER DCAB 4X4 2.0 AUT | BE57: 2022 | BF57: 2022
A58: 1987553 | B58: 381 | D58: 10554087 | F58: PHOENIX | G58: JUDICIAL | H58: 366-730 | I58: 366-730 | J58: CASTIGO | K58: COBRANZA | L58: 46180 | N58: 15242687 | O58: 9 | P58: GIORGIO GENNARO SARTORI TORRES | R58: 317.14 | S58: 45664 | W58: TANNER | X58: DACIÓN | Y58: 0 | Z58: 0 | AC58: 5917478 | AE58: PLAN DE PAGO | AF58: PHOENIX | AH58: CASTIGO | AI58: 975171907 | AL58: giorgio.sartori.t@gmail.com | AO58: AVENIDA JARDINES DE RENACA 102 | AP58: VIÑA DEL MAR | AQ58: V REGION | AR58: 20º Juzgado Civil de Santiago | AS58: C-15706-2024 | AT58: INGRESADO | AU58: SUSPENDIDO | AZ58: NO | BA58: SUSPENDIDO | BB58: SBWB47 | BC58: MAZDA | BD58: NEW 3 HB 2.0 | BE58: 2022 | BF58: 2022
A59: 1993999 | B59: 472 | D59: 6480797 | F59: PHOENIX | G59: JUDICIAL | H59: 366-730 | I59: 366-730 | J59: CASTIGO | K59: COBRANZA | L59: 46180 | N59: 26689839 | O59: 8 | P59: ANDREY ADOLFO RODRIGUEZ PIRELA | R59: 256.561 | S59: 45661 | W59: TANNER | X59: DACIÓN | Y59: 0 | Z59: 0 | AC59: 6480797 | AH59: CASTIGO | AI59: 5694292242 | AL59: rodriguez.p.a@hotmail.com | AO59: PRIMERA TRANSVERSAL 5915 DEP 203 PISO 2 | AP59: SAN MIGUEL | AQ59: REGION METROPOLITANA | AR59: 15º Juzgado Civil de Santiago | AS59: C-16651-2024 | AT59: INGRESADO | AU59: MANTIENE | AZ59: NO | BA59: ACTIVO | BB59: LPCZ41 | BC59: CHERY | BD59: TIGGO 2 GLS 1.5 | BE59: 2019 | BF59: 2019
A60: 1996495 | B60: 411 | D60: 16285403 | F60: PHOENIX | G60: JUDICIAL | H60: 366-730 | I60: 366-730 | J60: CASTIGO | K60: COBRANZA | L60: 46180 | N60: 16552478 | O60: 0 | P60: FRANCISCO ANTONIO VENEGAS GATICA | R60: 659.354 | S60: 45663 | W60: TANNER | X60: DACIÓN | Y60: 0 | Z60: 0 | AC60: 16285403 | AH60: CASTIGO | AI60: 56936737903 | AL60: francisco.venegas.gatica@fmail.com | AO60: LAS COMPUERTAS 9 | AP60: CATEMU | AQ60: V REGION | AR60: C-19084-2024 | AS60: 7º JUZGADO CIVIL DE SANTIAGO | AT60: EMBARGADO | AU60: MANTIENE | AZ60: SI | BA60: ACTIVO | BB60: SCVY70 | BC60: JAC | BD60: T8 PRO LUXURY 4X4 2.0 | BE60: 2022 | BF60: 2022
A61: 1999968 | B61: 381 | D61: 10385444 | F61: PHOENIX | G61: JUDICIAL | H61: 366-730 | I61: 366-730 | J61: CASTIGO | K61: COBRANZA | L61: 46180 | N61: 25179124 | O61: 4 | P61: JOHANA VALENTINA LEON SILVA | R61: 353.014 | S61: 45664 | W61: TANNER | Y61: 0 | Z61: 0 | AC61: 5635994 | AH61: CASTIGO | AQ61: REGION METROPOLITANA | AR61: 6º Juzgado Civil de Santiago | AS61: C-15708-2024 | AT61: REMATADO | AU61: MANTIENE | AZ61: SI | BA61: CERRADO | BC61: MIGRADO | BD61: MIGRADO | BE61: 0 | BF61: 0
A62: 2003648 | B62: 442 | D62: 8935639 | F62: PHOENIX | G62: JUDICIAL | H62: 366-730 | I62: 366-730 | J62: CASTIGO | K62: COBRANZA | L62: 46180 | N62: 16148240 | O62: 4 | P62: JOCELYN FLOR LEON ACEVEDO | R62: 291.081 | S62: 45662 | W62: TANNER | Y62: 0 | Z62: 0 | AC62: 4386861 | AH62: CASTIGO | AI62: 999138721 | AL62: jocelyn_leon_27@hotmail.com | AO62: LA CONQUISTA 2865 | AP62: CONCHALI | AQ62: REGION METROPOLITANA | AR62: 22º Juzgado Civil de Santiago | AS62: C-16647-2024 | AT62: REMATADO | AU62: MANTIENE | AZ62: SI | BA62: CERRADO | BB62: RZTP17 | BC62: CHANGAN | BD62: CX70 1.6 | BE62: 2022 | BF62: 2022
A63: 2005901 | B63: 350 | D63: 7052588 | F63: PHOENIX | G63: JUDICIAL | H63: 0-365 | I63: 0-365 | J63: CASTIGO | K63: COBRANZA | L63: 46180 | N63: 76929091 | O63: 5 | P63: ÁNGELICA ARAYA VALENZUELA EXTRACCIÓN DE MINERALES E.I.R.L. | R63: 587.716 | S63: 45665 | W63: TANNER | X63: DACIÓN | Y63: 0 | Z63: 0 | AC63: 7052588 | AH63: CASTIGO | AI63: 958351240 | AL63: angelicaarayavalenzuela@gmail.com | AO63: JOSE ANTONIO MORENO 555 | AP63: ANTOFAGASTA | AQ63: II REGION | AR63: C-22169-2024 | AS63: 30º JUZGADO CIVIL DE SANTIAGO | AT63: INGRESADO | AU63: MANTIENE | AZ63: NO | BA63: ACTIVO | BB63: JHRZ96 | BC63: FORD | BD63: RANGER XLT 4X4 3.2 | BE63: 2017 | BF63: 2017
A64: 2013176 | B64: 1 | D64: 8209795 | F64: PHOENIX | G64: JUDICIAL | H64: 0-365 | I64: 0-365 | J64: CASTIGO | K64: COBRANZA | L64: 46180 | M64: E | N64: 12229234 | O64: 7 | P64: LEILA MARLENE BERRIOS CERDA | R64: 287.735 | S64: 46028 | W64: TANNER | Y64: 0 | Z64: 0 | AC64: 8209795 | AH64: CASTIGO | AI64: 949956384 | AL64: jaguilar72@gmail.com | AO64: INES DE SUAREZ 462 | AP64: QUILPUE | AQ64: V REGION | AR64: C-2589-2025 | AS64: 7º JUZGADO CIVIL DE SANTIAGO | AT64: INGRESADO | AU64: MANTIENE | AZ64: NO | BA64: ACTIVO | BB64: RZYJ33 | BC64: CHANGAN | BD64: CX70 ELITE 1.5 AUT | BE64: 2022 | BF64: 2022
A65: 2031096 | B65: 197 | D65: 7340602 | F65: PHOENIX | G65: JUDICIAL | H65: 0-365 | I65: 0-365 | J65: CASTIGO | K65: COBRANZA | L65: 46180 | N65: 12135832 | O65: 8 | P65: GISELA BETZABE MARTINEZ CAMPOS | R65: 255.698 | S65: 46023 | W65: TANNER | X65: DACIÓN | Y65: 0 | Z65: 0 | AC65: 7340602 | AH65: CASTIGO | AI65: 9978206577 | AL65: martinezcamposgisela@gmail.com | AO65: AV. LA FERIA 4927 | AP65: PEDRO AGUIRRE CERDA | AQ65: REGION METROPOLITANA | AR65: C-6730-2025 | AS65: 10º Juzgado Civil de Santiago | AT65: INGRESADO | AU65: MANTIENE | AZ65: NO | BA65: ACTIVO | BB65: SCBG91 | BC65: JAC | BD65: JS3 HB 1.6 | BE65: 2022 | BF65: 2022
A66: 2041907 | B66: 411 | D66: 8500246 | F66: PHOENIX | G66: JUDICIAL | H66: 366-730 | I66: 366-730 | J66: CASTIGO | K66: COBRANZA | L66: 46180 | N66: 12446328 | O66: 9 | P66: CLAUDIA LORENA ROJAS ARRIARÁN | R66: 344.179 | S66: 45663 | W66: TANNER | Y66: 0 | Z66: 0 | AC66: 5880646 | AE66: PLAN DE PAGO | AF66: PHOENIX | AH66: CASTIGO | AI66: 56953547488 | AL66: PAULETIGNACIA26@gmail.com | AO66: PASAJE CAPELLAN PABLO VALLIER 2880 | AP66: LA SERENA | AQ66: IV REGION | AR66: C-19064-2024 | AS66: 25º Juzgado Civil de Santiago | AT66: INGRESADO | AU66: SUSPENDIDO | AW66: SUSPENDER | AX66: PLAN DE PAGO | AY66: 46241 | AZ66: NO | BA66: SUSPENDIDO | BB66: GFCS66 | BC66: HYUNDAI | BD66: PORTER HR CRDI 2.5 | BE66: 2014 | BF66: 2014
A67: 2056023 | B67: 107 | D67: 13686046 | F67: PHOENIX | G67: JUDICIAL | H67: 0-365 | I67: 0-365 | J67: CASTIGO | K67: COBRANZA | L67: 46180 | M67: E | N67: 76823538 | O67: 4 | P67: COMERCIALIZADORA CORRALES DEL CAMPO CL SPA | R67: 817.312 | S67: 46026 | W67: TANNER | X67: DACIÓN | Y67: 0 | Z67: 0 | AC67: 13686046 | AH67: CASTIGO | AI67: 989904022 | AL67: fecrnegociocl@gmail.com | AO67: Hijuela Primera Venecia Lote 9 Depto. 20 | AP67: MAULE | AQ67: VII REGION | AR67: C-22135-2024 | AS67: 10º Juzgado Civil de Santiago | AT67: EMBARGADO | AU67: MANTIENE | AZ67: SI | BA67: ACTIVO | BB67: SCXD60 | BC67: FIAT | BD67: DUCATO MULTIJET CARGO 2.3 | BE67: 2022 | BF67: 2022
A68: 2061192 | B68: 1 | D68: 6574917 | F68: PHOENIX | G68: JUDICIAL | H68: 0-365 | I68: 0-365 | J68: CASTIGO | K68: COBRANZA | L68: 46180 | M68: E | N68: 26193808 | O68: 1 | P68: ANGELICA JULIET ORTIZ FRANCO | R68: 393.73 | S68: 46028 | W68: TANNER | Y68: 0 | Z68: 0 | AC68: 6574917 | AH68: CASTIGO | AI68: 936665640 | AL68: SRTAORTIZ99@GMAIL.COM | AO68: AVENIDA MARIA ROZAS VELAZQUES 51 DEPARTAMENTO 2115 | AP68: ESTACION CENTRAL | AQ68: REGION METROPOLITANA | AR68: C-9881-2025 | AS68: 27º Juzgado Civil de Santiago | AT68: EMBARGADO | AU68: MANTIENE | AZ68: SI | BA68: ACTIVO | BB68: SCTS72 | BC68: NISSAN | BD68: SENTRA MT 2.0 | BE68: 2022 | BF68: 2022
A69: 2068217 | B69: 166 | D69: 10163324 | F69: PHOENIX | G69: JUDICIAL | H69: 0-365 | I69: 0-365 | J69: CASTIGO | K69: COBRANZA | L69: 46180 | N69: 10337919 | O69: 9 | P69: PEDRO JOSE URQUIZA NAVARRO | R69: 544.237 | S69: 46024 | W69: TANNER | X69: DACIÓN | Y69: 0 | Z69: 0 | AC69: 10163324 | AH69: CASTIGO | AI69: 9766007470 | AL69: crecerpurquiza@gmail.com | AO69: LOS CRISANTEMOS 8136 | AP69: SAN RAMON | AQ69: REGION METROPOLITANA | AR69: C-8323-2025 | AS69: 21º Juzgado Civil de Santiago | AT69: EMBARGADO | AU69: MANTIENE | AZ69: SI | BA69: ACTIVO | BB69: SDFL43 | BC69: CHANGAN | BD69: HUNTER 1.9 | BE69: 2022 | BF69: 2022
A70: 2112138 | B70: 381 | D70: 7782305 | F70: PHOENIX | G70: JUDICIAL | H70: 366-730 | I70: 366-730 | J70: CASTIGO | K70: COBRANZA | L70: 46180 | N70: 17278930 | O70: 7 | P70: RODOLFO ANTONIO ARANEDA REYES | R70: 233.518 | S70: 45664 | W70: TANNER | X70: DACIÓN | Y70: 0 | Z70: 0 | AC70: 7782305 | AH70: CASTIGO | AI70: 94908673 | AJ70: 927651889 | AL70: rodolfoar360@gmail.com | AM70: rodolfoar360@gmail.com | AO70: AVENIDA EL PARRON 0444 | AP70: LA CISTERNA | AQ70: REGION METROPOLITANA | AR70: C-20329-2024 | AS70: 7º JUZGADO CIVIL DE SANTIAGO | AT70: INGRESADO | AU70: MANTIENE | AZ70: NO | BA70: ACTIVO | BB70: SDWR61 | BC70: JAC | BD70: JS2 HB 1.5 | BE70: 2022 | BF70: 2022
A71: 2124083 | B71: 442 | D71: 11608660 | F71: PHOENIX | G71: JUDICIAL | H71: 366-730 | I71: 366-730 | J71: CASTIGO | K71: COBRANZA | L71: 46180 | N71: 19578014 | O71: 5 | P71: JAVIER IGNACIO CHAPARRO GODOY | R71: 389.754 | S71: 45662 | W71: TANNER | X71: DACIÓN | Y71: 0 | Z71: 0 | AC71: 11608660 | AH71: CASTIGO | AQ71: REGION METROPOLITANA | AR71: C-19075-2024 | AS71: 27º Juzgado Civil de Santiago | AT71: EMBARGADO | AU71: MANTIENE | AZ71: SI | BA71: ACTIVO | BB71: SDRJ49 | BC71: JAC | BD71: JS4 HB 1.6 | BE71: 2022 | BF71: 2022
A72: 2126564 | B72: 319 | D72: 9343344 | F72: PHOENIX | G72: JUDICIAL | H72: 0-365 | I72: 0-365 | J72: CASTIGO | K72: COBRANZA | L72: 46180 | N72: 13489611 | O72: 6 | P72: ELIZABETH DEL CARMEN ARENAS ORELLANA | R72: 402.299 | S72: 45666 | W72: TANNER | X72: DACIÓN | Y72: 0 | Z72: 0 | AC72: 9343344 | AH72: CASTIGO | AI72: 962442886 | AL72: Elyarenas2709@gmail.com | AO72: ALMIRANTE LATORRE 0367 | AP72: PUENTE ALTO | AQ72: REGION METROPOLITANA | AR72: C-683-2025 | AS72: 10º Juzgado Civil de Santiago | AT72: EMBARGADO | AU72: MANTIENE | AZ72: SI | BA72: ACTIVO | BB72: KXTC55 | BC72: NISSAN | BD72: NP300 DCAB 2.3 | BE72: 2019 | BF72: 2019
A73: 2134165 | B73: 166 | D73: 3828549 | F73: PHOENIX | G73: JUDICIAL | H73: 0-365 | I73: 0-365 | J73: CASTIGO | K73: COBRANZA | L73: 46180 | N73: 12178968 | O73: K | P73: CÉSAR ANDRÉS MUÑOZ HERRERA | R73: 198.875 | S73: 46024 | W73: TANNER | X73: DACIÓN | Y73: 0 | Z73: 0 | AC73: 3828549 | AH73: CASTIGO | AI73: 989059720 | AJ73: 934381682 | AL73: Transporte.cmunoz@gmail.com | AM73: - | AO73: PASAJE ANTUCO 2550 | AP73: MELIPILLA | AQ73: REGION METROPOLITANA | AR73: C-8314-2025 | AS73: 2º Juzgado Civil de Santiago | AT73: EMBARGADO | AU73: MANTIENE | AZ73: SI | BA73: ACTIVO | BB73: RPWP65 | BC73: JAC | BD73: T8 CE 2.0 | BE73: 2022 | BF73: 2022
A74: 2143882 | B74: 319 | D74: 6093246 | F74: PHOENIX | G74: JUDICIAL | H74: 0-365 | I74: 0-365 | J74: CASTIGO | K74: COBRANZA | L74: 46180 | N74: 11793560 | O74: 4 | P74: LORENA MARISOL ECHAURREN PEÑA | R74: 254.54 | S74: 45666 | W74: TANNER | X74: DACIÓN | Y74: 0 | Z74: 0 | AC74: 6093246 | AH74: CASTIGO | AI74: 977050378 | AL74: lorenaechaurren2@gmail.com | AO74: María Rosa 55 Depto 2610 | AP74: ESTACION CENTRAL | AQ74: REGION METROPOLITANA | AR74: C-683-2025 | AS74: 11º Juzgado Civil de Santiago | AT74: INGRESADO | AU74: MANTIENE | AZ74: NO | BA74: ACTIVO | BB74: KCWS56 | BC74: RENAULT | BD74: SYMBOL 1.6 | BE74: 2018 | BF74: 2018
A75: 2148996 | B75: 411 | D75: 8862930 | F75: PHOENIX | G75: JUDICIAL | H75: 366-730 | I75: 366-730 | J75: CASTIGO | K75: COBRANZA | L75: 46180 | N75: 17781952 | O75: 2 | P75: FELIPE FRANCISCO VALDIVIA MEDINA | R75: 274.574 | S75: 45663 | W75: TANNER | Y75: 0 | Z75: 0 | AC75: 8862930 | AH75: CASTIGO | AI75: 933839578 | AL75: f.valdivia.medina@gmail.com | AO75: DOS NORTE 1724 | AP75: CONCHALI | AQ75: REGION METROPOLITANA | AR75: C-20389-2024 | AS75: 2º Juzgado Civil de Santiago | AT75: INCAUTADO | AU75: MANTIENE | AZ75: SI | BA75: ACTIVO | BB75: PCSG29 | BC75: NISSAN | BD75: VERSA SEDAN 1.6 | BE75: 2020 | BF75: 2020
A76: 2170991 | B76: 472 | D76: 10100380 | F76: PHOENIX | G76: JUDICIAL | H76: 366-730 | I76: 366-730 | J76: CASTIGO | K76: COBRANZA | L76: 46180 | N76: 15743059 | O76: 9 | P76: DANIELA ANDREA ARIAS VALDIVIA | R76: 287.884 | S76: 45661 | W76: TANNER | Y76: 0 | Z76: 0 | AC76: 7300380 | AH76: CASTIGO | AI76: 9455054110 | AL76: daniela.arias.valdivia@gmail.com | AO76: PASAJE GETAFE 691 | AP76: QUILLOTA | AQ76: V REGION | AR76: C-20386-2024 | AS76: 21º Juzgado Civil de Santiago | AT76: GIRO CHEQUE | AU76: MANTIENE | AZ76: SI | BA76: ACTIVO | BB76: SGRW73 | BC76: BAIC | BD76: X35 MPI 1.5 | BE76: 2023 | BF76: 2023
A77: 2171993 | B77: 228 | D77: 8498727 | F77: PHOENIX | G77: JUDICIAL | H77: 0-365 | I77: 0-365 | J77: CASTIGO | K77: COBRANZA | L77: 46180 | N77: 18106130 | O77: 8 | P77: CAIN ANDRÉS RODRÍGUEZ VILLA | R77: 286.526 | S77: 45669 | W77: TANNER | X77: DACIÓN | Y77: 0 | Z77: 0 | AC77: 8498727 | AH77: CASTIGO | AI77: 920180512 | AL77: kainandres95@gmail.com | AO77: LAGUNA REDONDA 2 PASAJE. 4 CASA 675 | AP77: CONCEPCION | AQ77: VIII REGION | AR77: C-5502-2025 | AS77: 15º Juzgado Civil de Santiago | AT77: INGRESADO | AU77: MANTIENE | AZ77: NO | BA77: ACTIVO | BB77: SGLG63 | BC77: MG | BD77: 3 HATCH BACK 1.5 | BE77: 2023 | BF77: 2023
A78: 2177404 | B78: 107 | D78: 5574462 | F78: PHOENIX | G78: JUDICIAL | H78: 0-365 | I78: 0-365 | J78: CASTIGO | K78: COBRANZA | L78: 46180 | M78: E | N78: 26346582 | O78: 2 | P78: JOSE GREGORIO NAVA VILLALOBOS | R78: 254.066 | S78: 46026 | W78: TANNER | X78: DACIÓN | Y78: 0 | Z78: 0 | AC78: 5574442 | AH78: CASTIGO | AI78: 998336891 | AJ78: 998336891 | AL78: josenava.gaby@gmail.com | AO78: TRONCAL SAN FRANCISCO 2242 | AP78: PUENTE ALTO | AQ78: REGION METROPOLITANA | AR78: 20º Juzgado Civil de Santiago | AS78: C-16648-2024 | AT78: INGRESADO | AU78: MANTIENE | AZ78: NO | BA78: ACTIVO | BB78: SGFT11 | BC78: SUZUKI | BD78: SPRESSO GLX HB 1.0 | BE78: 2023 | BF78: 2023
A79: 2184639 | B79: 1 | D79: 5874992 | F79: PHOENIX | G79: JUDICIAL | H79: 0-365 | I79: 0-365 | J79: CASTIGO | K79: COBRANZA | L79: 46180 | M79: E | N79: 15444358 | O79: 4 | P79: ANDREA ALEJANDRA PIZARRO MIRANDA | R79: 226.053 | S79: 46028 | W79: TANNER | Y79: 0 | Z79: 0 | AC79: 5874992 | AH79: CASTIGO | AI79: 941062835 | AL79: pizarroandrea36@gmail.com | AO79: ALAMEDA A-1 | AP79: PIRQUE | AQ79: REGION METROPOLITANA | AR79: C-14430-2025 | AS79: 3º Juzgado Civil de Santiago | AT79: INGRESADO | AU79: MANTIENE | AZ79: NO | BA79: ACTIVO | BB79: HFWZ55 | BC79: PEUGEOT | BD79: 208 ALLURE HDI 1.4 | BE79: 2015 | BF79: 2015
A80: 2184893 | B80: 503 | D80: 8824246 | F80: PHOENIX | G80: JUDICIAL | H80: 366-730 | I80: 366-730 | J80: CASTIGO | K80: COBRANZA | L80: 46180 | N80: 15396541 | O80: 2 | P80: LUIS DAVID CORTES RAMIREZ | R80: 306.817 | S80: 45660 | W80: TANNER | Y80: 0 | Z80: 0 | AC80: 8824246 | AH80: CASTIGO | AI80: 939141645 | AL80: luis7cortes7@gmail.com | AO80: LOS OLIVOS 10622 DEPTO 201 | AP80: EL BOSQUE | AQ80: REGION METROPOLITANA | AR80: 5º Juzgado Civil de Santiago | AS80: C-15704-2024 | AT80: INCAUTADO | AU80: MANTIENE | AZ80: SI | BA80: ACTIVO | BB80: SHBP19 | BC80: JAC | BD80: JS3 HB 1.6 | BE80: 2023 | BF80: 2023
A81: 2200934 | B81: 381 | D81: 10210739 | F81: PHOENIX | G81: JUDICIAL | H81: 366-730 | I81: 366-730 | J81: CASTIGO | K81: COBRANZA | L81: 46180 | N81: 6738345 | O81: 1 | P81: ALBERTO ALEJANDRO BESNIER ABARZÚA | R81: 407.141 | S81: 45664 | W81: TANNER | X81: DACIÓN | Y81: 0 | Z81: 0 | AC81: 10210739 | AH81: CASTIGO | AI81: 941232612 | AL81: loventa09@gmail.com | AO81: LOS LLEUQUES 030 | AP81: TALCA | AQ81: VII REGION | AR81: C-19079-2024 | AS81: 26º Juzgado Civil de Santiago | AT81: EMBARGADO | AU81: MANTIENE | AZ81: SI | BA81: ACTIVO | BB81: HRVZ18 | BC81: MITSUBISHI | BD81: L200 KATANA CRM 2.5 | BE81: 2016 | BF81: 2016
A82: 2206128 | B82: 138 | D82: 8830213 | F82: PHOENIX | G82: JUDICIAL | H82: 0-365 | I82: 0-365 | J82: CASTIGO | K82: COBRANZA | L82: 46180 | M82: E | N82: 16075823 | O82: 6 | P82: ALEJANDRO ESTEBAN BEYTÍA OJEDA | R82: 342.759 | S82: 46025 | W82: TANNER | Y82: 0 | Z82: 0 | AC82: 8830213 | AH82: CASTIGO | AI82: 966812870 | AL82: BEYTIAALEJANDRO568@GMAIL.COM | AO82: MAR EGO | AP82: EL BOSQUE | AQ82: REGION METROPOLITANA | AR82: C-9896-2025 | AS82: 29º Juzgado Civil de Santiago | AT82: EMBARGADO | AU82: MANTIENE | AZ82: SI | BA82: ACTIVO | BC82: JETOUR | BD82: X 70 | BE82: 2023 | BF82: 2023
A83: 2206586 | B83: 1 | D83: 7207130 | F83: PHOENIX | G83: JUDICIAL | H83: 0-365 | I83: 0-365 | J83: CASTIGO | K83: COBRANZA | L83: 46180 | M83: E | N83: 17395256 | O83: 2 | P83: JULIO CESAR COÑOPAN ESPINOZA | R83: 251.845 | S83: 46028 | W83: TANNER | Y83: 0 | Z83: 0 | AC83: 7207130 | AH83: CASTIGO | AI83: 991627466 | AL83: jcmartespinoza@gmail.com | AO83: ALMIRANTE RIVERO NORTE 1875 BLOCK B DEPTO 203 | AP83: CONCEPCION | AQ83: VIII REGION | AR83: 4º Juzgado Civil de Santiago | AS83: C-16644-2024 | AT83: EMBARGADO | AU83: MANTIENE | AZ83: SI | BA83: ACTIVO | BB83: SHYD64 | BC83: CHANGAN | BD83: ALSVIN 1.4 | BE83: 2023 | BF83: 2023
A84: 2208275 | B84: 228 | D84: 9516314 | F84: PHOENIX | G84: JUDICIAL | H84: 0-365 | I84: 0-365 | J84: CASTIGO | K84: COBRANZA | L84: 46180 | N84: 18180465 | O84: 3 | P84: PAMELA IBETH BARRA FIGUEROA | R84: 291.745 | S84: 45669 | W84: TANNER | X84: DACIÓN | Y84: 0 | Z84: 0 | AC84: 9516314 | AH84: CASTIGO | AI84: 9789222730 | AL84: pamela.92.barra@gmail.com | AO84: CAMINO INTERNACIONAL 227 | AP84: TEMUCO | AQ84: IX REGION | AR84: C-3921-2025 | AS84: 30º JUZGADO CIVIL DE SANTIAGO | AT84: INGRESADO | AU84: MANTIENE | AZ84: NO | BA84: ACTIVO | BB84: SGFY37 | BC84: CHANGAN | BD84: ALSVIN ELITE AT | BE84: 2023 | BF84: 2023
A85: 2213431 | B85: 166 | D85: 2055650 | F85: PHOENIX | G85: JUDICIAL | H85: 0-365 | I85: 0-365 | J85: CASTIGO | K85: COBRANZA | L85: 46180 | N85: 8956095 | O85: 0 | P85: HUGO FELIPE VARGAS CIGNA | R85: 205.565 | S85: 46024 | W85: TANNER | X85: DACIÓN | Y85: 0 | Z85: 0 | AC85: 2055650 | AH85: CASTIGO | AI85: 91732330 | AL85: HUGOVARGASCIGNA@GMAIL.COM | AO85: VENTURA BLANCO VIEL | AP85: SAN MIGUEL | AQ85: REGION METROPOLITANA | AR85: C-678-2025 | AS85: 28º Juzgado Civil de Santiago | AT85: EMBARGADO | AU85: MANTIENE | AZ85: SI | BA85: ACTIVO | BB85: LSZF88 | BC85: NISSAN | BD85: X TRAIL CVT 2.5 AT | BE85: 2020 | BF85: 2020
A86: 2221834 | B86: 411 | D86: 3892558 | F86: PHOENIX | G86: JUDICIAL | H86: 366-730 | I86: 366-730 | J86: CASTIGO | K86: COBRANZA | L86: 46180 | N86: 26793032 | O86: 5 | P86: CARLOS ALBERTO GIANNOTTY MORENO | R86: 221.578 | S86: 45663 | W86: TANNER | X86: DACIÓN | Y86: 0 | Z86: 0 | AC86: 3642558 | AE86: PLAN DE PAGO | AF86: PHOENIX | AH86: CASTIGO | AI86: 959766639 | AL86: Carlosagiannotti@gmail.com | AO86: NUEVA LOS LEONES 0253 | AP86: PROVIDENCIA | AQ86: REGION METROPOLITANA | AR86: 24º Juzgado Civil de Santiago | AS86: C-15608-2024 | AT86: INGRESADO | AU86: MANTIENE | AZ86: NO | BA86: ACTIVO | BB86: WHP019 | BC86: YAMAHA | BD86: MT-03A | BE86: 2023 | BF86: 2023
A87: 2239559 | B87: 442 | D87: 9232528 | F87: PHOENIX | G87: JUDICIAL | H87: 366-730 | I87: 366-730 | J87: CASTIGO | K87: COBRANZA | L87: 46180 | N87: 18041239 | O87: 5 | P87: FABIOLA DEL CARMEN VARGAS GUTIERREZ | R87: 252.046 | S87: 45662 | W87: TANNER | X87: DACIÓN | Y87: 0 | Z87: 0 | AC87: 9232528 | AH87: CASTIGO | AI87: 9857862200 | AL87: fabi.guti@gmail.com | AO87: RAMIRO AGUILERA MOLINA 445 | AP87: RANCAGUA | AQ87: VI REGION | AR87: 16º Juzgado Civil de Santiago | AS87: C-16646-2024 | AT87: EMBARGADO | AU87: MANTIENE | AZ87: SI | BA87: ACTIVO | BB87: SHFL68 | BC87: JAC | BD87: JS2 1.5 | BE87: 2023 | BF87: 2023
A88: 2241494 | B88: 350 | D88: 10706135 | F88: PHOENIX | G88: JUDICIAL | H88: 0-365 | I88: 0-365 | J88: CASTIGO | K88: COBRANZA | L88: 46180 | N88: 15548788 | O88: 7 | P88: JOAN ANDREA CARES BARRA | R88: 402.939 | S88: 45665 | W88: TANNER | X88: DACIÓN | Y88: 0 | Z88: 0 | AC88: 10706135 | AH88: CASTIGO | AI88: 977326157 | AL88: joancitacares@gmail.com | AO88: MANUEL TELLEZ OYARZUN 439 | AP88: PUERTO MONTT | AQ88: X REGION | AR88: C-22137-2024 | AS88: 3º Juzgado Civil de Santiago | AT88: NOTIFICADO | AU88: MANTIENE | AZ88: SI | BA88: ACTIVO | BB88: SJVW75 | BC88: SUZUKI | BD88: XL7 1.5 | BE88: 2023 | BF88: 2023
A89: 2242697 | B89: 1 | D89: 14329489 | F89: PHOENIX | G89: JUDICIAL | H89: 0-365 | I89: 0-365 | J89: CASTIGO | K89: COBRANZA | L89: 46180 | M89: E | N89: 76478759 | O89: 5 | P89: SOLUCIONES DE INGENIERÍA CESAR CESPEDES SPA | R89: 626.935 | S89: 46028 | W89: TANNER | Y89: 0 | Z89: 0 | AC89: 11606269 | AH89: CASTIGO | AI89: 942987114 | AL89: CESARCESPEDES@INGENIERIACYR.CL | AO89: ISABEL LA CATOLICA 4398 OFICINA 617 | AP89: LAS CONDES | AQ89: REGION METROPOLITANA | AR89: C-14411-2025 | AS89: 4º JUZGADO CIVIL DE SANTIAGO | AT89: INGRESADO | AU89: MANTIENE | AZ89: NO | BA89: ACTIVO | BC89: NISSAN | BD89: NAVARA LE 4X4 MT | BE89: 2023 | BF89: 2023
A90: 2246738 | B90: 197 | D90: 7111666 | F90: PHOENIX | G90: JUDICIAL | H90: 0-365 | I90: 0-365 | J90: CASTIGO | K90: COBRANZA | L90: 46180 | N90: 8457326 | O90: 4 | P90: ALICIA DEL ROSARIO TARIS MÉNDEZ | R90: 318.465 | S90: 46023 | W90: TANNER | X90: DACIÓN | Y90: 0 | Z90: 0 | AC90: 7111666 | AH90: CASTIGO | AI90: 998503973 | AL90: ALICIADELROSARIO.TARIS@GMAIL.COM | AM90: aliciataris7@gmail.com | AO90: ORTIZ DE ROZAS 539 | AP90: RECOLETA | AQ90: REGION METROPOLITANA | AR90: C-6664-2025 | AS90: 24º Juzgado Civil de Santiago | AT90: INGRESADO | AU90: MANTIENE | AZ90: NO | BA90: ACTIVO | BB90: SKKP44 | BC90: FOTON | BD90: TM3 MAS 1.5 | BE90: 2023 | BF90: 2023
A91: 2253599 | B91: 258 | D91: 15121765 | F91: PHOENIX | G91: JUDICIAL | H91: 0-365 | I91: 0-365 | J91: CASTIGO | K91: COBRANZA | L91: 46180 | N91: 14390092 | O91: 4 | P91: SAUL NOE VILLAGRA PUENTES | R91: 561.66 | S91: 45668 | W91: TANNER | Y91: 0 | Z91: 0 | AC91: 15121765 | AH91: CASTIGO | AQ91: REGION METROPOLITANA | AR91: C-4036-2025 | AS91: 23º JUZGADO CIVIL DE SANTIAGO | AT91: NOTIFICADO | AU91: MANTIENE | AZ91: SI | BA91: ACTIVO | BC91: MIGRADO | BD91: MIGRADO | BE91: 0 | BF91: 0
A92: 2260525 | B92: 350 | D92: 11856692 | F92: PHOENIX | G92: JUDICIAL | H92: 0-365 | I92: 0-365 | J92: CASTIGO | K92: COBRANZA | L92: 46180 | N92: 13734460 | O92: 2 | P92: ROXANA MARCELA ROSAS SEPÚLVEDA | R92: 706.405 | S92: 45665 | W92: TANNER | X92: DACIÓN | Y92: 0 | Z92: 0 | AC92: 11856692 | AH92: CASTIGO | AI92: 964279394 | AL92: Roxana.rosas@gmail.com | AO92: AVENIDA MIRAMAR 5324 DPTO 404 | AP92: COQUIMBO | AQ92: IV REGION | AR92: C-22145-2024 | AS92: 14º Juzgado Civil de Santiago | AT92: INGRESADO | AU92: MANTIENE | AZ92: NO | BA92: ACTIVO | BB92: JJLC88 | BC92: MERCEDES BENZ | BD92: GLE 350D COUPE SPORT | BE92: 2017 | BF92: 2017
A93: 2277292 | B93: 319 | D93: 12565144 | F93: PHOENIX | G93: JUDICIAL | H93: 0-365 | I93: 0-365 | J93: CASTIGO | K93: COBRANZA | L93: 46180 | N93: 15970085 | O93: 2 | P93: DARIO JOSE FUENTES CANIO | R93: 431.948 | S93: 45666 | W93: TANNER | X93: DACIÓN | Y93: 0 | Z93: 0 | AC93: 12565144 | AH93: CASTIGO | AI93: 987559265 | AL93: dario_legalize@hotmail.com | AO93: PASAJE GENERAL EDUARDO BACHELET 2 263 | AP93: RANCAGUA | AQ93: VI REGION | AR93: C-686-2025 | AS93: 22º Juzgado Civil de Santiago | AT93: INGRESADO | AU93: MANTIENE | AZ93: NO | BA93: ACTIVO | BB93: SHZC70 | BC93: HAVAL | BD93: JOLION 1.5 | BE93: 2023 | BF93: 2023
A94: 2291099 | B94: 381 | D94: 3834831 | F94: PHOENIX | G94: JUDICIAL | H94: 366-730 | I94: 366-730 | J94: CASTIGO | K94: COBRANZA | L94: 46180 | N94: 16159997 | O94: 2 | P94: PAULA ELISA CÁRDENAS ALVARADO | R94: 208.126 | S94: 45664 | W94: TANNER | X94: DACIÓN | Y94: 0 | Z94: 0 | AC94: 3834831 | AH94: CASTIGO | AI94: 948923995 | AL94: Paulaelisa246@gmail.com | AO94: PASAJE LOS NARANJOS 954 | AP94: VALDIVIA | AQ94: XIV REGION | AR94: C-20346-2024 | AS94: 12º Juzgado Civil de Santiago | AT94: INGRESADO | AU94: MANTIENE | AZ94: NO | BA94: ACTIVO | BB94: JHGT70 | BC94: CHEVROLET | BD94: SPARK GT LT 1.2 | BE94: 2017 | BF94: 2017
A95: 2297687 | B95: 411 | D95: 10777648 | F95: PHOENIX | G95: JUDICIAL | H95: 366-730 | I95: 366-730 | J95: CASTIGO | K95: COBRANZA | L95: 46180 | N95: 15929792 | O95: 6 | P95: XAVIER ALEJANDRO LAVÍN VÁSQUEZ | R95: 375.948 | S95: 45663 | W95: TANNER | X95: DACIÓN | Y95: 0 | Z95: 0 | AC95: 10777648 | AH95: CASTIGO | AI95: 966605547 | AL95: xlavinvasquez@gmail.com | AO95: LOS TALLADORES 10407 | AP95: LA FLORIDA | AQ95: REGION METROPOLITANA | AR95: C-19071-2024 | AS95: 22º Juzgado Civil de Santiago | AT95: EMBARGADO | AU95: MANTIENE | AZ95: SI | BA95: ACTIVO | BB95: KKWD17 | BC95: BMW | BD95: 118I 1.5 AUT | BE95: 2018 | BF95: 2018
A96: 2298622 | B96: 228 | D96: 16869176 | F96: PHOENIX | G96: JUDICIAL | H96: 0-365 | I96: 0-365 | J96: CASTIGO | K96: COBRANZA | L96: 46180 | N96: 14276136 | O96: K | P96: LUIS ALBERTO AHUMADA ESCOBAR | R96: 478.849 | S96: 45669 | W96: TANNER | X96: DACIÓN | Y96: 0 | Z96: 0 | AC96: 16869176 | AH96: CASTIGO | AI96: 958107362 | AL96: lahumada01@hotmail.com | AO96: PRESBITERO GUSTAVO FELTEN 457 | AP96: VILLA ALEMANA | AQ96: V REGION | AR96: C-5504-2025 | AS96: 22º Juzgado Civil de Santiago | AT96: INGRESADO | AU96: MANTIENE | AZ96: NO | BA96: ACTIVO | BB96: SKDW78 | BC96: HAVAL | BD96: H6 ELITE 2.0 AUT | BE96: 2023 | BF96: 2023
A97: 2300266 | B97: 258 | D97: 6388538 | F97: PHOENIX | G97: JUDICIAL | H97: 0-365 | I97: 0-365 | J97: CASTIGO | K97: COBRANZA | L97: 46180 | N97: 17498345 | O97: 3 | P97: MANUEL ARMANDO YÁÑEZ YAÑEZ | R97: 259.282 | S97: 45668 | W97: TANNER | X97: DACIÓN | Y97: 0 | Z97: 0 | AC97: 6388538 | AH97: CASTIGO | AI97: 969098534 | AL97: manuelacuario1990@gmail.com | AO97: EL YODO 8170 DEPTO 126 | AP97: ANTOFAGASTA | AQ97: II REGION | AR97: C-2591-2025 | AS97: 15º Juzgado Civil de Santiago | AT97: EMBARGADO | AU97: MANTIENE | AZ97: SI | BA97: ACTIVO | BB97: HSKF15 | BC97: HYUNDAI | BD97: TUCSON 2.0 | BE97: 2016 | BF97: 2016
A98: 2310878 | B98: 1 | D98: 12635982 | F98: PHOENIX | G98: JUDICIAL | H98: 0-365 | I98: 0-365 | J98: CASTIGO | K98: COBRANZA | L98: 46180 | M98: E | N98: 16782801 | O98: 9 | P98: PATRICIO ESTEBAN GUTIÉRREZ VALENZUELA | R98: 656.333 | S98: 46028 | W98: TANNER | Y98: 0 | Z98: 0 | AC98: 12635982 | AH98: CASTIGO | AI98: 940839524 | AL98: valenzuela.pg@gmail.com | AO98: GACITUA 156 | AP98: CHILLAN VIEJO | AQ98: XVI REGION | AR98: C-13016-2025 | AS98: 19º Juzgado Civil de Santiago | AT98: INGRESADO | AU98: MANTIENE | AZ98: NO | BA98: ACTIVO | BB98: KFXW15 | BC98: JAGUAR | BD98: F PACE PRESTIGE 2.0 | BE98: 2018 | BF98: 2018
A99: 2316103 | B99: 411 | D99: 8882006 | F99: PHOENIX | G99: JUDICIAL | H99: 366-730 | I99: 366-730 | J99: CASTIGO | K99: COBRANZA | L99: 46180 | N99: 76287256 | O99: 0 | P99: COMERCIALIZADORA ALPES LIMITADA | R99: 234.347 | S99: 45663 | W99: TANNER | X99: DACIÓN | Y99: 0 | Z99: 0 | AC99: 8882006 | AE99: PUT EN CUOTAS | AF99: PHOENIX | AH99: CASTIGO | AI99: 942283930 | AL99: MPARADA@ALPESLTDA.CL | AO99: NIMES | AP99: Sin Comuna | AQ99: Sin Región | AR99: C-19082-2024 | AS99: 18º Juzgado Civil de Santiago | AT99: EMBARGADO | AU99: MANTIENE | AZ99: SI | BA99: ACTIVO | BB99: RFXS15 | BC99: CITROEN | BD99: BERLINGO 2 HDI 1.6 | BE99: 2022 | BF99: 2022
A100: 2317511 | B100: 1 | D100: 7166910 | F100: PHOENIX | G100: JUDICIAL | H100: 0-365 | I100: 0-365 | J100: CASTIGO | K100: COBRANZA | L100: 46180 | M100: E | N100: 11478052 | O100: 9 | P100: MIGUEL ANGEL MIDOLO ESCOBAR | R100: 356.728 | S100: 46028 | W100: TANNER | Y100: 0 | Z100: 0 | AC100: 7166910 | AH100: CASTIGO | AL100: RODRIGOMARPE94@GMIAL.COM | AO100: PASAJE ALCALA 326 | AP100: QUILICURA | AQ100: REGION METROPOLITANA | AR100: C-14431-2025 | AS100: 1º Juzgado Civil de Santiago | AT100: EMBARGADO | AU100: MANTIENE | AZ100: SI | BA100: ACTIVO | BB100: SFYZ15 | BC100: DFLM | BD100: JOYEAR SX6 1.6 | BE100: 2023 | BF100: 2023
...

Sheet PLAN-PUT
A1: ID_CREDITO | B1: DIAS_MORA | C1: CUOTAS_MOROSAS_ACTUAL | D1: SALDO_INSOLUTO_INI | E1: PRIORIDAD_GESTION | F1: GESTOR | G1: TIPO_COBRANZA | H1: TRAMO_INI | I1: TRAMO_ACT | J1: TIPO_CARTERA | K1: TIPO_GESTION | L1: FECHA_ASIGNACION | M1: SEGMENTO_CLIENTE | N1: RUT | O1: DV | P1: RAZON_SOCIAL | Q1: PERSONA_NATURAL | R1: VALOR_CUOTA | S1: FECHA_PROX_VCTO | T1: CUOTAS_PAGADAS_ACTUAL | U1: CUOTAS_PAGADAS_INI | V1: PLAZO | W1: CANAL_VENTA | X1: CAMPANAS | Y1: INT_MORA_TOTAL | Z1: GC_TOTAL | AA1: ESTADO_PAT_PAC | AB1: FECHA_FIRMA_PAGARE | AC1: MONTO_ADEUDADO | AD1: TASA_INTERES_CRED | AE1: CONVENIO_CASTIGO | AF1: GESTOR_PLAN_PAGO | AG1: MARCA_CLIENTE | AH1: ESTADO_COBRANZA | AI1: TELEFONO_1 | AJ1: TELEFONO_2 | AK1: TELEFONO_3 | AL1: EMAIL_1 | AM1: EMAIL_2 | AN1: EMAIL_3 | AO1: DIRECCION | AP1: COMUNA | AQ1: REGION | AR1: ROL | AS1: TRIBUNAL | AT1: ESTADO_JUDICIAL | AU1: TIPO_JUDICIAL | AV1: DUAL | AW1: SUSP_ESTADO_JUDICIAL | AX1: SUSP_MOTIVO | AY1: SUSP_FECHA | AZ1: NOTIFICADO | BA1: ESTADO_JUICIO | BB1: VEHICULO_1_PATENTE | BC1: VEHICULO_1_MARCA | BD1: VEHICULO_1_MODELO | BE1: VEHICULO_1_ANIO
A2: 1383598 | B2: 279 | D2: 3596000 | F2: PHOENIX | G2: JUDICIAL | H2: 0-365 | I2: 0-365 | J2: CASTIGO | K2: COBRANZA | L2: 46118 | N2: 15667044 | O2: 8 | P2: SEBASTIÁN ESTEBAN VILLAGRA CISTERNAS | R2: 225287 | S2: 45839 | W2: TANNER | Y2: 0 | Z2: 0 | AC2: 1548000 | AE2: PLAN DE PAGO | AF2: PHOENIX | AH2: CASTIGO | AI2: 933429038 | AL2: svillagra1984@gmail.com | AO2: SAN PABLO 4025, DEPTO 1814 | AP2: QUINTA NORMAL | AQ2: REGION METROPOLITANA | AR2: C-19083-2024 | AS2: 18º Juzgado Civil de Santiago | AT2: INGRESADO | AU2: SUSPENDIDO | AZ2: NO | BA2: CERRADO | BB2: PYSF60 | BC2: VOLKSWAGEN | BD2: NUEVO VOYAGE HIGHLINE 1.6 | BE2: 2021
A3: 1397586 | B3: 248 | D3: 5796000 | F3: PHOENIX | G3: JUDICIAL | H3: 0-365 | I3: 0-365 | J3: CASTIGO | K3: COBRANZA | L3: 46118 | N3: 16482560 | O3: 4 | P3: ITALO ADOLFO MUÑOZ PAREDES MUÑOZ PAREDES | R3: 266289 | S3: 45870 | W3: TANNER | Y3: 0 | Z3: 0 | AC3: 451088 | AE3: PUT EN CUOTAS | AF3: PHOENIX | AH3: CASTIGO | AI3: 971949267 | AL3: ITALOMPAREDES1987@ICLOUD.COM | AO3: PASAJE CASTELLÓN 1993 ALTO OSORNO | AP3: OSORNO | AQ3: X REGION | AR3: C-21976-2024 | AS3: 24º Juzgado Civil de Santiago | AT3: GIRO CHEQUE | AU3: MANTIENE | AZ3: SI | BA3: CERRADO | BB3: PZTC12 | BC3: RENAULT | BD3: OROCH OTTO 2.0 | BE3: 2021
A4: 1524638 | B4: 126 | D4: 3499999 | F4: PHOENIX | G4: JUDICIAL | H4: 0-365 | I4: 0-365 | J4: CASTIGO | K4: COBRANZA | L4: 46118 | N4: 12712897 | O4: 9 | P4: DENISE DE LOURDES ARTEAGA GÓMEZ | R4: 358441 | S4: 45992 | W4: CREDINISSAN | Y4: 0 | Z4: 0 | AC4: 2624999 | AE4: PUT EN CUOTAS | AF4: PHOENIX | AH4: CASTIGO | AI4: 998656256 | AL4: DENISEARTEAGA@GMAIL.COM | AO4: SANTA INES 1060 | AP4: PUERTO MONTT | AQ4: X REGION | AR4: C-19078-2024 | AS4: 26º Juzgado Civil de Santiago | AT4: INGRESADO | AU4: REACTIVA | AZ4: NO | BA4: ACTIVO | BB4: RHPP76 | BC4: NISSAN | BD4: X TRAIL CVT 2.5 AT | BE4: 2022
A5: 1571122 | B5: 156 | D5: 5920000 | F5: PHOENIX | G5: JUDICIAL | H5: 0-365 | I5: 0-365 | J5: CASTIGO | K5: COBRANZA | L5: 46118 | N5: 11641745 | O5: 6 | P5: ANA PAULA GUAJARDO CORDOVA | R5: 275628 | S5: 45962 | W5: TANNER | Y5: 0 | Z5: 0 | AC5: 676430 | AE5: PLAN DE PAGO | AF5: PHOENIX | AH5: CASTIGO | AI5: 959863045 | AL5: ANA.GUA.COR29@GMAIL.COM | AO5: PASAJE DANCING 5875 | AQ5: REGION METROPOLITANA | AR5: C-3908-2025 | AS5: 26º Juzgado Civil de Santiago | AT5: INGRESADO | AU5: MANTIENE | AZ5: NO | BA5: ACTIVO | BB5: RGZP22 | BC5: CHANGAN | BD5: CS55 ELITE 1.5 AUT | BE5: 2022
A6: 1638465 | B6: 309 | D6: 3871396 | F6: PHOENIX | G6: JUDICIAL | H6: 0-365 | I6: 0-365 | J6: CASTIGO | K6: COBRANZA | L6: 46118 | N6: 27070326 | O6: 7 | P6: LIBIA ROSA VERA TUBIÑEZ | R6: 198550 | S6: 45809 | W6: TANNER | Y6: 0 | Z6: 0 | AC6: 1942286 | AE6: PLAN DE PAGO | AF6: PHOENIX | AH6: CASTIGO | AI6: 962588898 | AL6: LIBIA.VERA1@GMAIL.COM | AO6: ALCALDE MANUEL HUICHIPOCO 422 | AQ6: REGION METROPOLITANA | AR6: C-19071-2024 | AS6: 3º Juzgado Civil de Santiago | AT6: INGRESADO | AU6: SUSPENDIDO | AZ6: NO | BA6: SUSPENDIDO | BB6: RKHK18 | BC6: SUZUKI | BD6: S PRESSO HB 1.0 | BE6: 2022
A7: 1644932 | B7: 340 | D7: 4868802 | F7: PHOENIX | G7: JUDICIAL | H7: 0-365 | I7: 0-365 | J7: CASTIGO | K7: COBRANZA | L7: 46118 | N7: 16002296 | O7: 5 | P7: MIGUEL ANGEL ACEVEDO ARAVENA | R7: 196978 | S7: 45778 | W7: TANNER | Y7: 0 | Z7: 0 | AC7: 3420102 | AE7: PLAN DE PAGO | AF7: PHOENIX | AH7: CASTIGO | AI7: 9987229864 | AL7: MACEVEDOAR@GMAIL.COM | AO7: 30 SUR 19 PONIENTE NÂ°38 | AQ7: VII REGION | AR7: 4º Juzgado Civil de Santiago | AS7: C-16642-2024 | AT7: EMBARGADO | AU7: SUSPENDIDO | AZ7: SI | BA7: SUSPENDIDO | BB7: RJSW95 | BC7: CHANGAN | BD7: ALSVIN LUXURY MT | BE7: 2022
A8: 1700218 | B8: 64 | D8: 6879999 | F8: PHOENIX | G8: JUDICIAL | H8: 0-365 | I8: 0-365 | J8: CASTIGO | K8: COBRANZA | L8: 46118 | M8: E | N8: 12218160 | O8: K | P8: JUAN ALEX OLIVARES ALANO | R8: 362214 | S8: 46054 | W8: CREDINISSAN | Y8: 0 | Z8: 0 | AC8: 6517785 | AE8: PLAN DE PAGO | AF8: PHOENIX | AH8: CASTIGO | AI8: 957500333 | AL8: OLIVARESALANO@GMAIL.COM | AO8: FERNANDO DE AGUIRRE 850 POBLACIÓN CARTAVIO | AP8: COPIAPO | AQ8: III REGION | AR8: 25º Juzgado Civil de Santiago | AS8: C-15693-2024 | AT8: INGRESADO | AU8: MANTIENE | AZ8: NO | BA8: ACTIVO | BB8: RKRY65 | BC8: NISSAN | BD8: KICKS CVT 1.6 AUT | BE8: 2022
A9: 1769156 | B9: 370 | D9: 7241243 | F9: PHOENIX | G9: JUDICIAL | H9: 366-730 | I9: 366-730 | J9: CASTIGO | K9: COBRANZA | L9: 46118 | N9: 7710884 | O9: K | P9: MARÍA ANGÉLICA VERGARA SILVA | R9: 330069 | S9: 45748 | W9: TANNER | Y9: 0 | Z9: 0 | AC9: 3160827 | AE9: PLAN DE PAGO | AF9: PHOENIX | AH9: CASTIGO | AI9: 944758247 | AL9: janomarver1974@gmail.com | AO9: HORNILLAS 01651 | AP9: PUNTA ARENAS | AQ9: XII REGION | AR9: 9º Juzgado Civil de Santiago | AS9: C-16645-2024 | AT9: INGRESADO | AU9: SUSPENDIDO | AZ9: NO | BA9: SUSPENDIDO | BB9: RPYY87 | BC9: HYUNDAI | BD9: SANTA FE 2.0 AUT | BE9: 2014
A10: 1791083 | B10: 401 | D10: 7569433 | F10: PHOENIX | G10: JUDICIAL | H10: 366-730 | I10: 366-730 | J10: CASTIGO | K10: COBRANZA | L10: 46118 | N10: 15236244 | O10: 7 | P10: RUBÉN ANER CARILAO BARRA | R10: 322355 | S10: 45717 | W10: TANNER | Y10: 0 | Z10: 0 | AC10: 6295707 | AE10: PLAN DE PAGO | AF10: PHOENIX | AH10: CASTIGO | AI10: 968259519 | AL10: rubenaner@gmail.com | AO10: La Huasca 10834 | AP10: LA FLORIDA | AQ10: REGION METROPOLITANA | AR10: 16º Juzgado Civil de Santiago | AS10: C-16644-2024 | AT10: EMBARGADO | AU10: SUSPENDIDO | AZ10: SI | BA10: SUSPENDIDO | BB10: RTFH40 | BC10: KYC | BD10: X5 DCAB 1.5 | BE10: 2022
A11: 1891178 | B11: 156 | D11: 6382600 | F11: PHOENIX | G11: JUDICIAL | H11: 0-365 | I11: 0-365 | J11: CASTIGO | K11: COBRANZA | L11: 46118 | N11: 26313552 | O11: 0 | P11: WILLIAMS JOSE CHACIN MARTINEZ | R11: 301100 | S11: 45962 | W11: TANNER | Y11: 0 | Z11: 0 | AC11: 6382600 | AE11: PLAN DE PAGO | AF11: PHOENIX | AH11: CASTIGO | AI11: 979125999 | AL11: LUISANNAISABELL@GMAIL.COM | AO11: PDTE SANTA MARIA 289 | AQ11: REGION METROPOLITANA | AR11: C-5521-2025 | AS11: 23º Juzgado Civil de Santiago | AT11: EMBARGADO | AU11: MANTIENE | AZ11: SI | BA11: ACTIVO | BB11: RWZK66 | BC11: SUZUKI | BD11: BALENO GLS HB 1.4 | BE11: 2022
A12: 1923591 | B12: 248 | D12: 11082144 | F12: PHOENIX | G12: JUDICIAL | H12: 0-365 | I12: 0-365 | J12: CASTIGO | K12: COBRANZA | L12: 46118 | N12: 16647012 | O12: 9 | P12: FABRICIO ALEJANDRO VALENZUELA LEIVA | R12: 375735 | S12: 45870 | W12: TANNER | Y12: 0 | Z12: 0 | AC12: 8056774 | AE12: PLAN DE PAGO | AF12: PHOENIX | AH12: CASTIGO | AI12: 977915708 | AL12: fabricio.valenzuela.leiva@gmail.com | AO12: EL LLANO 9 | AP12: SAN BERNARDO | AQ12: REGION METROPOLITANA | AR12: C-22141-2024 | AS12: 29º Juzgado Civil de Santiago | AT12: INGRESADO | AU12: SUSPENDIDO | AZ12: NO | BA12: SUSPENDIDO | BB12: RXTT99 | BC12: JAC | BD12: T8 PRO DIESEL ADVANCE 4X4 2.0 | BE12: 2022
A13: 1987553 | B13: 279 | D13: 10554087 | F13: PHOENIX | G13: JUDICIAL | H13: 0-365 | I13: 0-365 | J13: CASTIGO | K13: COBRANZA | L13: 46118 | N13: 15242687 | O13: 9 | P13: GIORGIO GENNARO SARTORI TORRES | R13: 317140 | S13: 45839 | W13: TANNER | Y13: 0 | Z13: 0 | AC13: 7309826 | AE13: PLAN DE PAGO | AF13: PHOENIX | AH13: CASTIGO | AI13: 975171907 | AL13: giorgio.sartori.t@gmail.com | AO13: AVENIDA JARDINES DE RENACA 102 | AP13: VIÑA DEL MAR | AQ13: V REGION | AR13: 20º Juzgado Civil de Santiago | AS13: C-15706-2024 | AT13: INGRESADO | AU13: SUSPENDIDO | AZ13: NO | BA13: SUSPENDIDO | BB13: SBWB47 | BC13: MAZDA | BD13: NEW 3 HB 2.0 | BE13: 2022
A14: 2041907 | B14: 309 | D14: 8500246 | F14: PHOENIX | G14: JUDICIAL | H14: 0-365 | I14: 0-365 | J14: CASTIGO | K14: COBRANZA | L14: 46118 | N14: 12446328 | O14: 9 | P14: CLAUDIA LORENA ROJAS ARRIARÁN | R14: 344179 | S14: 45809 | W14: TANNER | Y14: 0 | Z14: 0 | AC14: 6286246 | AE14: PLAN DE PAGO | AF14: PHOENIX | AH14: CASTIGO | AI14: +56953547488 | AL14: PAULETIGNACIA26@gmail.com | AO14: PASAJE CAPELLAN PABLO VALLIER 2880 | AP14: LA SERENA | AQ14: IV REGION | AR14: C-19064-2024 | AS14: 25º JUZGADO CIVIL DE SANTIAGO | AT14: INGRESADO | AU14: SUSPENDIDO | AZ14: NO | BA14: SUSPENDIDO | BB14: GFCS66 | BC14: HYUNDAI | BD14: PORTER HR CRDI 2.5 | BE14: 2014
A15: 2221834 | B15: 309 | D15: 3892558 | F15: PHOENIX | G15: JUDICIAL | H15: 0-365 | I15: 0-365 | J15: CASTIGO | K15: COBRANZA | L15: 46118 | N15: 26793032 | O15: 5 | P15: CARLOS ALBERTO GIANNOTTY MORENO | R15: 221578 | S15: 45809 | W15: TANNER | Y15: 0 | Z15: 0 | AC15: 3642558 | AE15: PLAN DE PAGO | AF15: PHOENIX | AH15: CASTIGO | AI15: 959766639 | AL15: Carlosagiannotti@gmail.com | AO15: NUEVA LOS LEONES 0253 | AP15: PROVIDENCIA | AQ15: REGION METROPOLITANA | AR15: 24º Juzgado Civil de Santiago | AS15: C-15608-2024 | AT15: INGRESADO | AU15: MANTIENE | AZ15: NO | BA15: ACTIVO | BB15: WHP019 | BC15: YAMAHA | BD15: MT-03A | BE15: 2023
A16: 2316103 | B16: 309 | D16: 8882006 | F16: PHOENIX | G16: JUDICIAL | H16: 0-365 | I16: 0-365 | J16: CASTIGO | K16: COBRANZA | L16: 46118 | N16: 76287256 | O16: 0 | P16: COMERCIALIZADORA ALPES LIMITADA | R16: 234347 | S16: 45809 | W16: TANNER | Y16: 0 | Z16: 0 | AC16: 8882006 | AE16: PUT EN CUOTAS | AF16: PHOENIX | AH16: CASTIGO | AI16: 942283930 | AL16: MPARADA@ALPESLTDA.CL | AO16: NIMES | AR16: C-19082-2024 | AS16: 18º Juzgado Civil de Santiago | AT16: EMBARGADO | AU16: MANTIENE | AZ16: SI | BA16: ACTIVO | BB16: RFXS15 | BC16: CITROEN | BD16: BERLINGO 2 HDI 1.6 | BE16: 2022
A17: 2359330 | B17: 429 | D17: 17079615 | F17: PHOENIX | G17: JUDICIAL | H17: 366-730 | I17: 366-730 | J17: CASTIGO | K17: COBRANZA | L17: 46118 | N17: 14387173 | O17: 8 | P17: SOLEDAD DEL CARMEN ALFARO PINTO | R17: 457241 | S17: 45689 | W17: TANNER | Y17: 0 | Z17: 0 | AC17: 12315615 | AE17: PLAN DE PAGO | AF17: PHOENIX | AH17: CASTIGO | AI17: 971808740 | AL17: soledadalfaro.pinto@gmail.com | AO17: OLEA 3869 CASA E | AP17: ISLA DE MAIPO | AQ17: REGION METROPOLITANA | AR17: 16º Juzgado Civil de Santiago | AS17: C-15702-2024 | AT17: EMBARGADO | AU17: SUSPENDIDO | AZ17: SI | BA17: SUSPENDIDO | BB17: SRFJ82 | BC17: GEELY | BD17: AZKARRA 1.5TD 6AT GL 2WD EXCLUSIVE | BE17: 2023
A18: 2361546 | B18: 187 | D18: 5966279 | F18: PHOENIX | G18: JUDICIAL | H18: 0-365 | I18: 0-365 | J18: CASTIGO | K18: COBRANZA | L18: 46118 | N18: 18845546 | O18: 8 | P18: PAULETTE CRISTINA PEÑA JARA | R18: 234494 | S18: 45931 | W18: TANNER | Y18: 0 | Z18: 0 | AC18: 4966279 | AE18: PLAN DE PAGO | AF18: PHOENIX | AH18: CASTIGO | AI18: 981279138 | AL18: ppena4372@gmail.com | AO18: Calle Salitrera Rica Aventura, El Palomar 542 | AP18: COPIAPO | AQ18: III REGION | AR18: C-22161-2024 | AS18: 7º Juzgado Civil de Santiago | AT18: EMBARGADO | AU18: MANTIENE | AZ18: SI | BA18: ACTIVO | BB18: JDKT88 | BC18: FORD | BD18: ECOSPORT TITANIUM 1.6 | BE18: 2017
A19: 2410360 | B19: 217 | D19: 5047680 | F19: PHOENIX | G19: JUDICIAL | H19: 0-365 | I19: 0-365 | J19: CASTIGO | K19: COBRANZA | L19: 46118 | N19: 13291544 | O19: K | P19: ANDREA DEL PILAR GONZÁLEZ URETA | R19: 274774 | S19: 45901 | W19: TANNER | Y19: 0 | Z19: 0 | AC19: 2960760 | AE19: PLAN DE PAGO | AF19: PHOENIX | AH19: CASTIGO | AI19: 948899401 | AL19: agonzalez1977ureta@gmail.com | AO19: PIELAGO DEL SUR 1866 | AP19: LA FLORIDA | AQ19: REGION METROPOLITANA | AR19: C-685-2025 | AS19: 12º Juzgado Civil de Santiago | AT19: EMBARGADO | AU19: SUSPENDIDO | AZ19: SI | BA19: SUSPENDIDO | BB19: SRSZ86 | BC19: FOTON | BD19: MIDI DOBLE 1.3 | BE19: 2023
A20: 2757617 | B20: 95 | D20: 9115829 | F20: PHOENIX | G20: JUDICIAL | H20: 0-365 | I20: 0-365 | J20: CASTIGO | K20: COBRANZA | L20: 46118 | M20: E | N20: 10908669 | O20: K | P20: OSCAR RICARDO ROMERO GONZÁLEZ | R20: 309130 | S20: 46023 | W20: TANNER | Y20: 0 | Z20: 0 | AC20: 9115829 | AE20: PUT EN CUOTAS | AF20: PHOENIX | AH20: CASTIGO | AI20: 964496387 | AL20: ROMINAROMEROCARRASCO@GMAIL.COM | AO20: LAS BANDURRIAS 10915 VILLA COLOMBIA | AP20: LA PINTANA | AQ20: REGION METROPOLITANA | AR20: C-6724-2025 | AS20: 18º Juzgado Civil de Santiago | AT20: EMBARGADO | AU20: MANTIENE | AZ20: SI | BA20: ACTIVO | BB20: TDZV42 | BC20: DFM | BD20: T5 | BE20: 2024
A21: 2762910 | B21: 340 | D21: 15253118 | F21: PHOENIX | G21: JUDICIAL | H21: 0-365 | I21: 0-365 | J21: CASTIGO | K21: COBRANZA | L21: 46118 | N21: 9369669 | O21: 7 | P21: CARLOS ORLANDO PLAZA COLMAN | R21: 316420 | S21: 45778 | W21: TANNER | Y21: 0 | Z21: 0 | AC21: 15253118 | AE21: PLAN DE PAGO | AF21: PHOENIX | AH21: CASTIGO | AI21: 992941506 | AL21: CARLOSPIEZACOLMAN@GMAIL.COM | AO21: MANUEL MONTT | AP21: TIERRA AMARILLA | AQ21: III REGION | AR21: 11º Juzgado Civil de Santiago | AS21: C-15702-2024 | AT21: EMBARGADO | AU21: MANTIENE | AZ21: SI | BA21: ACTIVO | BB21: SDJY64 | BC21: HAVAL | BD21: JOLION ACTIVE 1.5 | BE21: 2022
A22: 3115557 | B22: 95 | D22: 10316441 | F22: PHOENIX | G22: JUDICIAL | H22: 0-365 | I22: 0-365 | J22: CASTIGO | K22: COBRANZA | L22: 46118 | M22: E | N22: 18488596 | O22: 4 | P22: ELENA ROMANE VIDAL GOMEZ | R22: 280540 | S22: 46023 | W22: TANNER | Y22: 0 | Z22: 0 | AC22: 7816441 | AE22: PLAN DE PAGO | AF22: PHOENIX | AH22: CASTIGO | AI22: 56955195058 | AL22: vidal.gomez.elena.93@gmail.com | AO22: SANTA LAURA 1290 | AP22: MELIPILLA | AQ22: REGION METROPOLITANA | AR22: C-6723-2025 | AS22: 3º Juzgado Civil de Santiago | AT22: NOTIFICADO | AU22: MANTIENE | AZ22: SI | BA22: ACTIVO | BC22: SUZUKI | BD22: SWIFT 1.2 AMT GL SPORT | BE22: 0
A23: 3120521 | B23: 156 | D23: 15352634 | F23: PHOENIX | G23: JUDICIAL | H23: 0-365 | I23: 0-365 | J23: CASTIGO | K23: COBRANZA | L23: 46118 | N23: 6332455 | O23: 8 | P23: ELSA MARCIA DIAZ MORA | R23: 432150 | S23: 45962 | W23: TANNER | Y23: 0 | Z23: 0 | AC23: 15352634 | AE23: PLAN DE PAGO | AF23: PHOENIX | AH23: CASTIGO | AL23: DIAZVEGA82_@HOTMAIL.COM | AO23: PASAJE CORDILLERA CASA | AP23: ÑUBLE | AQ23: XIV REGION | AR23: C-2589-2025 | AS23: 5º Juzgado Civil de Santiago | AT23: INGRESADO | AU23: MANTIENE | AZ23: NO | BA23: ACTIVO | BC23: FOTON | BD23: G7 4x4 | BE23: 2024

Sheet TUBO VIGENTE JULIO
A1: CREDITO | B1: RUT | C1: NOMBRE | D1: TRAMO | E1: TRAMO ACTUAL | F1: TRAMO PEGA | G1: ESTADO_COBRANZA | H1: SOLUCION | I1: N° CUOTAS | J1: DIAS MORA | K1: VALOR CUOTA | L1: CAPITAL | M1: VALOR APROX DE PAGO | N1: FECHA COMPROMISO | O1: ESTADO | P1: FECHA PAGO | Q1: RECUPERADO | R1: OBSERVACIONES | S1: audios | T1: Oficio
A2: 2893403 | B2: =VLOOKUP(A2,Export!A:N,14,0) -> 10357961 | C2: =VLOOKUP(A2,Export!A:P,16,0) -> LUZ MARCELA LOPEZ BEAS | D2: =VLOOKUP(A2,Export!A:H,8,0) -> 91-120 | E2: =VLOOKUP(A2,Export!A:I,9,0) -> 61-90 | F2: 90+ | G2: =VLOOKUP(A2,Export!A:AH,34,0) -> BAJA90 | H2: PAGO CUOTAS | I2: 2 | J2: =VLOOKUP(A2,Export!A:B,2,0) -> 69 | K2: =VLOOKUP(A2,Export!A:R,18,0) -> 314.918 | L2: =VLOOKUP(A2,Export!A:D,4,0) -> 5770645 | M2: =IF(H2="PAGO CUOTAS",I2*K2,L2) -> 629.836 | N2: 46204 | O2: PAGADO | P2: 46204 | Q2: =+SUMIF(O2,"PAGADO",L2) -> 5770645 | R2: tt pago 1 y pagara otrael 15 y a fin de mes, 2do.pago 17/07 | S2: FALSE | T2: =VLOOKUP(A2,'OFICIO '!A:J,10,0) -> 46055
A3: 3251019 | B3: =VLOOKUP(A3,Export!A:N,14,0) -> 25890131 | C3: =VLOOKUP(A3,Export!A:P,16,0) -> JOSE JORGE COLORADO RODRIGUEZ | D3: =VLOOKUP(A3,Export!A:H,8,0) -> 61-90 | E3: =VLOOKUP(A3,Export!A:I,9,0) -> 61-90 | F3: C4 | G3: =VLOOKUP(A3,Export!A:AH,34,0) -> BAJA90 | H3: PAGO CUOTAS | I3: 1 | J3: =VLOOKUP(A3,Export!A:B,2,0) -> 71 | K3: =VLOOKUP(A3,Export!A:R,18,0) -> 373.22 | L3: =VLOOKUP(A3,Export!A:D,4,0) -> 9744091 | M3: =IF(H3="PAGO CUOTAS",I3*K3,L3) -> 373.22 | N3: 46205 | O3: PAGADO | P3: 46209 | Q3: =+SUMIF(O3,"PAGADO",L3) -> 9744091 | S3: FALSE | T3: =VLOOKUP(A3,'OFICIO '!A:J,10,0) -> #N/A
A4: 2914167 | B4: =VLOOKUP(A4,Export!A:N,14,0) -> 10585244 | C4: =VLOOKUP(A4,Export!A:P,16,0) -> CLAUDIA ORIETTA FREDES BARRERA | D4: =VLOOKUP(A4,Export!A:H,8,0) -> 31-60 | E4: =VLOOKUP(A4,Export!A:I,9,0) -> 61-90 | F4: C3 | G4: =VLOOKUP(A4,Export!A:AH,34,0) -> NO RECUPERADO | H4: PAGO CUOTAS | I4: 1 | J4: =VLOOKUP(A4,Export!A:B,2,0) -> 66 | K4: =VLOOKUP(A4,Export!A:R,18,0) -> 173.183 | L4: =VLOOKUP(A4,Export!A:D,4,0) -> 2641698 | M4: =IF(H4="PAGO CUOTAS",I4*K4,L4) -> 173.183 | N4: 46227 | O4: PENDIENTE | Q4: =+SUMIF(O4,"PAGADO",L4) -> 0 | S4: FALSE | T4: =VLOOKUP(A4,'OFICIO '!A:J,10,0) -> #N/A
A5: 2901204 | B5: =VLOOKUP(A5,Export!A:N,14,0) -> 14027161 | C5: =VLOOKUP(A5,Export!A:P,16,0) -> SAMUEL RODRIGO AGUILERA CARTER | D5: =VLOOKUP(A5,Export!A:H,8,0) -> 61-90 | E5: =VLOOKUP(A5,Export!A:I,9,0) -> 31-60 | F5: C4 | G5: =VLOOKUP(A5,Export!A:AH,34,0) -> BAJA90 | H5: PAGO CUOTAS | I5: 2 | J5: =VLOOKUP(A5,Export!A:B,2,0) -> 45 | K5: =VLOOKUP(A5,Export!A:R,18,0) -> 263.534 | L5: =VLOOKUP(A5,Export!A:D,4,0) -> 6922351 | M5: =IF(H5="PAGO CUOTAS",I5*K5,L5) -> 527.068 | N5: 46209 | O5: PAGADO | P5: 46209 | Q5: =+SUMIF(O5,"PAGADO",L5) -> 6922351 | S5: FALSE | T5: =VLOOKUP(A5,'OFICIO '!A:J,10,0) -> #N/A
A6: 2901203 | B6: =VLOOKUP(A6,Export!A:N,14,0) -> 19940769 | C6: =VLOOKUP(A6,Export!A:P,16,0) -> IGNACIO ALEJANDRO NAVARRETE DIAZ | D6: =VLOOKUP(A6,Export!A:H,8,0) -> 31-60 | E6: =VLOOKUP(A6,Export!A:I,9,0) -> 31-60 | F6: C3 | G6: =VLOOKUP(A6,Export!A:AH,34,0) -> CONTENIDO | H6: PAGO CUOTAS | I6: 1 | J6: =VLOOKUP(A6,Export!A:B,2,0) -> 45 | K6: =VLOOKUP(A6,Export!A:R,18,0) -> 325.481 | L6: =VLOOKUP(A6,Export!A:D,4,0) -> 5732485 | M6: =IF(H6="PAGO CUOTAS",I6*K6,L6) -> 325.481 | N6: 46205 | O6: PAGADO | P6: 46205 | Q6: =+SUMIF(O6,"PAGADO",L6) -> 5732485 | S6: FALSE | T6: =VLOOKUP(A6,'OFICIO '!A:J,10,0) -> #N/A
A7: 3334914 | B7: =VLOOKUP(A7,Export!A:N,14,0) -> 9507551 | C7: =VLOOKUP(A7,Export!A:P,16,0) -> JUAN LUIS HERNANDEZ ALMONACID | D7: =VLOOKUP(A7,Export!A:H,8,0) -> 121-150 | E7: =VLOOKUP(A7,Export!A:I,9,0) -> 151-180 | F7: 90+ | G7: =VLOOKUP(A7,Export!A:AH,34,0) -> NO RECUPERADO | H7: PAGO CUOTAS | I7: 5 | J7: =VLOOKUP(A7,Export!A:B,2,0) -> 165 | K7: =VLOOKUP(A7,Export!A:R,18,0) -> 367.186 | L7: =VLOOKUP(A7,Export!A:D,4,0) -> 10255953 | M7: =IF(H7="PAGO CUOTAS",I7*K7,L7) -> 1835.93 | N7: 46223 | O7: PENDIENTE | Q7: =+SUMIF(O7,"PAGADO",L7) -> 0 | S7: FALSE | T7: =VLOOKUP(A7,'OFICIO '!A:J,10,0) -> #N/A
A8: 2965293 | B8: =VLOOKUP(A8,Export!A:N,14,0) -> 9721000 | C8: =VLOOKUP(A8,Export!A:P,16,0) -> ELENA TERCIRA RIVAS JIMÉNEZ | D8: =VLOOKUP(A8,Export!A:H,8,0) -> 31-60 | E8: =VLOOKUP(A8,Export!A:I,9,0) -> 31-60 | F8: C3 | G8: =VLOOKUP(A8,Export!A:AH,34,0) -> CONTENIDO | H8: PAGO CUOTAS | I8: 1 | J8: =VLOOKUP(A8,Export!A:B,2,0) -> 40 | K8: =VLOOKUP(A8,Export!A:R,18,0) -> 359.588 | L8: =VLOOKUP(A8,Export!A:D,4,0) -> 8234831 | M8: =IF(H8="PAGO CUOTAS",I8*K8,L8) -> 359.588 | N8: 46207 | O8: PAGADO | Q8: =+SUMIF(O8,"PAGADO",L8) -> 8234831 | S8: FALSE | T8: =VLOOKUP(A8,'OFICIO '!A:J,10,0) -> #N/A
A9: 3159040 | B9: =VLOOKUP(A9,Export!A:N,14,0) -> 13872350 | C9: =VLOOKUP(A9,Export!A:P,16,0) -> ALEJANDRO PATRICIO NIETO SALFATE | D9: =VLOOKUP(A9,Export!A:H,8,0) -> 31-60 | E9: =VLOOKUP(A9,Export!A:I,9,0) -> 31-60 | F9: C3 | G9: =VLOOKUP(A9,Export!A:AH,34,0) -> CONTENIDO | H9: PAGO CUOTAS | I9: 1 | J9: =VLOOKUP(A9,Export!A:B,2,0) -> 34 | K9: =VLOOKUP(A9,Export!A:R,18,0) -> 510.567 | L9: =VLOOKUP(A9,Export!A:D,4,0) -> 15663717 | M9: =IF(H9="PAGO CUOTAS",I9*K9,L9) -> 510.567 | N9: 46206 | O9: PAGADO | P9: 46210 | Q9: =+SUMIF(O9,"PAGADO",L9) -> 15663717 | S9: FALSE | T9: =VLOOKUP(A9,'OFICIO '!A:J,10,0) -> #N/A
A10: 2926586 | B10: =VLOOKUP(A10,Export!A:N,14,0) -> 26071337 | C10: =VLOOKUP(A10,Export!A:P,16,0) -> WADSON CELESTIN | D10: =VLOOKUP(A10,Export!A:H,8,0) -> 121-150 | E10: =VLOOKUP(A10,Export!A:I,9,0) -> 91-120 | F10: 90+ | G10: =VLOOKUP(A10,Export!A:AH,34,0) -> CONTENIDO | H10: PAGO CUOTAS | I10: 3 | J10: =VLOOKUP(A10,Export!A:B,2,0) -> 106 | K10: =VLOOKUP(A10,Export!A:R,18,0) -> 98.892 | L10: =VLOOKUP(A10,Export!A:D,4,0) -> 1743128 | M10: =IF(H10="PAGO CUOTAS",I10*K10,L10) -> 296.676 | N10: 46206 | O10: PAGADO | Q10: =+SUMIF(O10,"PAGADO",L10) -> 1743128 | R10: trasf. M$250. pago 2 cuotas 15/07 | S10: FALSE | T10: =VLOOKUP(A10,'OFICIO '!A:J,10,0) -> #N/A
A11: 3524299 | B11: =VLOOKUP(A11,Export!A:N,14,0) -> 17174056 | C11: =VLOOKUP(A11,Export!A:P,16,0) -> JORGE JOEL IBÁÑEZ LÓPEZ | D11: =VLOOKUP(A11,Export!A:H,8,0) -> 61-90 | E11: =VLOOKUP(A11,Export!A:I,9,0) -> 46052 | F11: C4 | G11: =VLOOKUP(A11,Export!A:AH,34,0) -> BAJA90 | H11: PAGO CUOTAS | I11: 2 | J11: =VLOOKUP(A11,Export!A:B,2,0) -> 28 | K11: =VLOOKUP(A11,Export!A:R,18,0) -> 222.791 | L11: =VLOOKUP(A11,Export!A:D,4,0) -> 6436678 | M11: =IF(H11="PAGO CUOTAS",I11*K11,L11) -> 445.582 | N11: 46206 | O11: PAGADO | P11: 46210 | Q11: =+SUMIF(O11,"PAGADO",L11) -> 6436678 | S11: FALSE | T11: =VLOOKUP(A11,'OFICIO '!A:J,10,0) -> #N/A
A12: 2456670 | B12: =VLOOKUP(A12,Export!A:N,14,0) -> 26501219 | C12: =VLOOKUP(A12,Export!A:P,16,0) -> YERLAIN MARIA VILLALOBOS CAMACARO | D12: =VLOOKUP(A12,Export!A:H,8,0) -> 31-60 | E12: =VLOOKUP(A12,Export!A:I,9,0) -> 46052 | F12: C3 | G12: =VLOOKUP(A12,Export!A:AH,34,0) -> CONTENIDO | H12: PAGO CUOTAS | I12: 3 | J12: =VLOOKUP(A12,Export!A:B,2,0) -> 10 | K12: =VLOOKUP(A12,Export!A:R,18,0) -> 185.595 | L12: =VLOOKUP(A12,Export!A:D,4,0) -> 6715037 | M12: =IF(H12="PAGO CUOTAS",I12*K12,L12) -> 556.785 | N12: 46204 | O12: PAGADO | P12: 46210 | Q12: =+SUMIF(O12,"PAGADO",L12) -> 6715037 | S12: FALSE | T12: =VLOOKUP(A12,'OFICIO '!A:J,10,0) -> #N/A
A13: 3350049 | B13: =VLOOKUP(A13,Export!A:N,14,0) -> 15221775 | C13: =VLOOKUP(A13,Export!A:P,16,0) -> PAMELA ALEJANDRA GONZALEZ ALVAREZ | D13: =VLOOKUP(A13,Export!A:H,8,0) -> 151-180 | E13: =VLOOKUP(A13,Export!A:I,9,0) -> AL DIA | F13: 90+ | G13: =VLOOKUP(A13,Export!A:AH,34,0) -> BAJA90 | H13: PAGO CUOTAS | I13: 5 | J13: =VLOOKUP(A13,Export!A:B,2,0) -> 0 | K13: =VLOOKUP(A13,Export!A:R,18,0) -> 210.091 | L13: =VLOOKUP(A13,Export!A:D,4,0) -> 5661718 | M13: =IF(H13="PAGO CUOTAS",I13*K13,L13) -> 1050.455 | N13: 46206 | O13: PAGADO | Q13: =+SUMIF(O13,"PAGADO",L13) -> 5661718 | S13: FALSE | T13: =VLOOKUP(A13,'OFICIO '!A:J,10,0) -> #N/A
A14: 3456392 | B14: =VLOOKUP(A14,Export!A:N,14,0) -> 16406426 | C14: =VLOOKUP(A14,Export!A:P,16,0) -> MAURICIO ANDRÉS OLIVOS VILLALOBOS | D14: =VLOOKUP(A14,Export!A:H,8,0) -> 271-300 | E14: =VLOOKUP(A14,Export!A:I,9,0) -> 301-330 | F14: 90+ | G14: =VLOOKUP(A14,Export!A:AH,34,0) -> NO RECUPERADO | H14: PAGO CUOTAS | I14: 1 | J14: =VLOOKUP(A14,Export!A:B,2,0) -> 318 | K14: =VLOOKUP(A14,Export!A:R,18,0) -> 293.944 | L14: =VLOOKUP(A14,Export!A:D,4,0) -> 5914470 | M14: =IF(H14="PAGO CUOTAS",I14*K14,L14) -> 293.944 | N14: 46205 | O14: PENDIENTE | Q14: =+SUMIF(O14,"PAGADO",L14) -> 0 | S14: FALSE | T14: =VLOOKUP(A14,'OFICIO '!A:J,10,0) -> #N/A
A15: 2791803 | B15: =VLOOKUP(A15,Export!A:N,14,0) -> 15029397 | C15: =VLOOKUP(A15,Export!A:P,16,0) -> MARIA PIA ROJAS RAVEST | D15: =VLOOKUP(A15,Export!A:H,8,0) -> 31-60 | E15: =VLOOKUP(A15,Export!A:I,9,0) -> 61-90 | F15: C3 | G15: =VLOOKUP(A15,Export!A:AH,34,0) -> NO RECUPERADO | H15: PAGO CUOTAS | I15: 1 | J15: =VLOOKUP(A15,Export!A:B,2,0) -> 72 | K15: =VLOOKUP(A15,Export!A:R,18,0) -> 267.964 | L15: =VLOOKUP(A15,Export!A:D,4,0) -> 5749965 | M15: =IF(H15="PAGO CUOTAS",I15*K15,L15) -> 267.964 | N15: 46233 | O15: PENDIENTE | Q15: =+SUMIF(O15,"PAGADO",L15) -> 0 | S15: FALSE | T15: =VLOOKUP(A15,'OFICIO '!A:J,10,0) -> #N/A
A16: 3291352 | B16: =VLOOKUP(A16,Export!A:N,14,0) -> 11378450 | C16: =VLOOKUP(A16,Export!A:P,16,0) -> MARCO ANTONIO NATIVIA ESCALERA | D16: =VLOOKUP(A16,Export!A:H,8,0) -> 151-180 | E16: =VLOOKUP(A16,Export!A:I,9,0) -> 31-60 | F16: 90+ | G16: =VLOOKUP(A16,Export!A:AH,34,0) -> BAJA90 | H16: PAGO CUOTAS | I16: 4 | J16: =VLOOKUP(A16,Export!A:B,2,0) -> 53 | K16: =VLOOKUP(A16,Export!A:R,18,0) -> 147.577 | L16: =VLOOKUP(A16,Export!A:D,4,0) -> 4680147 | M16: =IF(H16="PAGO CUOTAS",I16*K16,L16) -> 590.308 | N16: 46205 | O16: PAGADO | Q16: =+SUMIF(O16,"PAGADO",L16) -> 4680147 | S16: FALSE | T16: =VLOOKUP(A16,'OFICIO '!A:J,10,0) -> #N/A
A17: 3089537 | B17: =VLOOKUP(A17,Export!A:N,14,0) -> 14530681 | C17: =VLOOKUP(A17,Export!A:P,16,0) -> INGRID ALEJANDRA SANDOVAL MARDONES | D17: =VLOOKUP(A17,Export!A:H,8,0) -> 61-90 | E17: =VLOOKUP(A17,Export!A:I,9,0) -> 61-90 | F17: C4 | G17: =VLOOKUP(A17,Export!A:AH,34,0) -> BAJA90 | H17: PAGO CUOTAS | I17: 1 | J17: =VLOOKUP(A17,Export!A:B,2,0) -> 66 | K17: =VLOOKUP(A17,Export!A:R,18,0) -> 322.279 | L17: =VLOOKUP(A17,Export!A:D,4,0) -> 7477518 | M17: =IF(H17="PAGO CUOTAS",I17*K17,L17) -> 322.279 | N17: 46204 | O17: PAGADO | P17: 46204 | Q17: =+SUMIF(O17,"PAGADO",L17) -> 7477518 | S17: FALSE | T17: =VLOOKUP(A17,'OFICIO '!A:J,10,0) -> #N/A
A18: 2820080 | B18: =VLOOKUP(A18,Export!A:N,14,0) -> 14570180 | C18: =VLOOKUP(A18,Export!A:P,16,0) -> HIFFYT MARLENE AGUILERA PEREZ | D18: =VLOOKUP(A18,Export!A:H,8,0) -> 61-90 | E18: =VLOOKUP(A18,Export!A:I,9,0) -> 31-60 | F18: C4 | G18: =VLOOKUP(A18,Export!A:AH,34,0) -> BAJA90 | H18: PAGO CUOTAS | I18: 2 | J18: =VLOOKUP(A18,Export!A:B,2,0) -> 45 | K18: =VLOOKUP(A18,Export!A:R,18,0) -> 360.517 | L18: =VLOOKUP(A18,Export!A:D,4,0) -> 3173278 | M18: =IF(H18="PAGO CUOTAS",I18*K18,L18) -> 721.034 | O18: PAGADO | Q18: =+SUMIF(O18,"PAGADO",L18) -> 3173278 | R18: 15/07 y 30/07 paga 1 cuota + | S18: FALSE | T18: =VLOOKUP(A18,'OFICIO '!A:J,10,0) -> #N/A
A19: 2822126 | B19: =VLOOKUP(A19,Export!A:N,14,0) -> 17484621 | C19: =VLOOKUP(A19,Export!A:P,16,0) -> PRISCILLA FERNANDA SALDÍAS BARROS | D19: =VLOOKUP(A19,Export!A:H,8,0) -> 61-90 | E19: =VLOOKUP(A19,Export!A:I,9,0) -> 46052 | F19: C4 | G19: =VLOOKUP(A19,Export!A:AH,34,0) -> BAJA90 | H19: PAGO CUOTAS | I19: 2 | J19: =VLOOKUP(A19,Export!A:B,2,0) -> 30 | K19: =VLOOKUP(A19,Export!A:R,18,0) -> 170.887 | L19: =VLOOKUP(A19,Export!A:D,4,0) -> 2494587 | M19: =IF(H19="PAGO CUOTAS",I19*K19,L19) -> 341.774 | N19: 46205 | O19: PAGADO | P19: 46205 | Q19: =+SUMIF(O19,"PAGADO",L19) -> 2494587 | S19: FALSE | T19: =VLOOKUP(A19,'OFICIO '!A:J,10,0) -> #N/A
A20: 2381394 | B20: =VLOOKUP(A20,Export!A:N,14,0) -> 13875254 | C20: =VLOOKUP(A20,Export!A:P,16,0) -> CARLA ORIANA MUÑOZ MIRANDA | D20: =VLOOKUP(A20,Export!A:H,8,0) -> 61-90 | E20: =VLOOKUP(A20,Export!A:I,9,0) -> 31-60 | F20: C4 | G20: =VLOOKUP(A20,Export!A:AH,34,0) -> BAJA90 | H20: PAGO CUOTAS | I20: 1 | J20: =VLOOKUP(A20,Export!A:B,2,0) -> 58 | K20: =VLOOKUP(A20,Export!A:R,18,0) -> 378.731 | L20: =VLOOKUP(A20,Export!A:D,4,0) -> 3575169 | M20: =IF(H20="PAGO CUOTAS",I20*K20,L20) -> 378.731 | N20: 46204 | O20: PAGADO | P20: 46204 | Q20: =+SUMIF(O20,"PAGADO",L20) -> 3575169 | S20: FALSE | T20: =VLOOKUP(A20,'OFICIO '!A:J,10,0) -> #N/A
A21: 2545904 | B21: =VLOOKUP(A21,Export!A:N,14,0) -> 13011353 | C21: =VLOOKUP(A21,Export!A:P,16,0) -> MAURICIO ALEJANDRO DIAZ CARRIZO | D21: =VLOOKUP(A21,Export!A:H,8,0) -> 31-60 | E21: =VLOOKUP(A21,Export!A:I,9,0) -> 31-60 | F21: C3 | G21: =VLOOKUP(A21,Export!A:AH,34,0) -> CONTENIDO | H21: PAGO CUOTAS | I21: 2 | J21: =VLOOKUP(A21,Export!A:B,2,0) -> 45 | K21: =VLOOKUP(A21,Export!A:R,18,0) -> 189.035 | L21: =VLOOKUP(A21,Export!A:D,4,0) -> 4134127 | M21: =IF(H21="PAGO CUOTAS",I21*K21,L21) -> 378.07 | N21: 46209 | O21: PAGADO | Q21: =+SUMIF(O21,"PAGADO",L21) -> 4134127 | S21: FALSE | T21: =VLOOKUP(A21,'OFICIO '!A:J,10,0) -> #N/A
A22: 2993173 | B22: =VLOOKUP(A22,Export!A:N,14,0) -> 13217975 | C22: =VLOOKUP(A22,Export!A:P,16,0) -> FERNANDO RAÚL FERNÁNDEZ ZAVALA | D22: =VLOOKUP(A22,Export!A:H,8,0) -> 211-240 | E22: =VLOOKUP(A22,Export!A:I,9,0) -> 241-270 | F22: 90+ | G22: =VLOOKUP(A22,Export!A:AH,34,0) -> NO RECUPERADO | H22: PAGO CUOTAS | I22: 6 | J22: =VLOOKUP(A22,Export!A:B,2,0) -> 251 | K22: =VLOOKUP(A22,Export!A:R,18,0) -> 304.433 | L22: =VLOOKUP(A22,Export!A:D,4,0) -> 4482749 | M22: =IF(H22="PAGO CUOTAS",I22*K22,L22) -> 1826.598 | N22: 46234 | O22: PAGADO | Q22: =+SUMIF(O22,"PAGADO",L22) -> 4482749 | R22: transferencia M$2098. | S22: FALSE | T22: =VLOOKUP(A22,'OFICIO '!A:J,10,0) -> #N/A
A23: 2567747 | B23: =VLOOKUP(A23,Export!A:N,14,0) -> 23109537 | C23: =VLOOKUP(A23,Export!A:P,16,0) -> BRAYAN GIAMPIER BAZAN VIGO | D23: =VLOOKUP(A23,Export!A:H,8,0) -> 181-210 | E23: =VLOOKUP(A23,Export!A:I,9,0) -> 211-240 | F23: 90+ | G23: =VLOOKUP(A23,Export!A:AH,34,0) -> NO RECUPERADO | H23: PAGO CUOTAS | I23: 5 | J23: =VLOOKUP(A23,Export!A:B,2,0) -> 222 | K23: =VLOOKUP(A23,Export!A:R,18,0) -> 383.307 | L23: =VLOOKUP(A23,Export!A:D,4,0) -> 9087248 | M23: =IF(H23="PAGO CUOTAS",I23*K23,L23) -> 1916.535 | N23: 46218 | O23: PENDIENTE | Q23: =+SUMIF(O23,"PAGADO",L23) -> 0 | S23: FALSE | T23: =VLOOKUP(A23,'OFICIO '!A:J,10,0) -> #N/A
A24: 2877820 | B24: =VLOOKUP(A24,Export!A:N,14,0) -> 7896030 | C24: =VLOOKUP(A24,Export!A:P,16,0) -> MIGUEL ANGEL CAMPOS CID | D24: =VLOOKUP(A24,Export!A:H,8,0) -> 61-90 | E24: =VLOOKUP(A24,Export!A:I,9,0) -> 61-90 | F24: C4 | G24: =VLOOKUP(A24,Export!A:AH,34,0) -> BAJA90 | H24: PAGO CUOTAS | I24: 1 | J24: =VLOOKUP(A24,Export!A:B,2,0) -> 74 | K24: =VLOOKUP(A24,Export!A:R,18,0) -> 336.651 | L24: =VLOOKUP(A24,Export!A:D,4,0) -> 5841087 | M24: =IF(H24="PAGO CUOTAS",I24*K24,L24) -> 336.651 | N24: 46209 | O24: PAGADO | P24: 46209 | Q24: =+SUMIF(O24,"PAGADO",L24) -> 5841087 | S24: FALSE | T24: =VLOOKUP(A24,'OFICIO '!A:J,10,0) -> #N/A
A25: 2003692 | B25: =VLOOKUP(A25,Export!A:N,14,0) -> 11527231 | C25: =VLOOKUP(A25,Export!A:P,16,0) -> LAURA DEL CARMEN SOTO BARRÍA | D25: =VLOOKUP(A25,Export!A:H,8,0) -> 151-180 | E25: =VLOOKUP(A25,Export!A:I,9,0) -> 61-90 | F25: 90+ | G25: =VLOOKUP(A25,Export!A:AH,34,0) -> CONTENIDO | H25: PAGO CUOTAS | I25: 4 | J25: =VLOOKUP(A25,Export!A:B,2,0) -> 89 | K25: =VLOOKUP(A25,Export!A:R,18,0) -> 399.393 | L25: =VLOOKUP(A25,Export!A:D,4,0) -> 2205064 | M25: =IF(H25="PAGO CUOTAS",I25*K25,L25) -> 1597.572 | N25: 46216 | O25: PAGADO | Q25: =+SUMIF(O25,"PAGADO",L25) -> 2205064 | S25: FALSE | T25: =VLOOKUP(A25,'OFICIO '!A:J,10,0) -> #N/A
A26: 3346863 | B26: =VLOOKUP(A26,Export!A:N,14,0) -> 8331309 | C26: =VLOOKUP(A26,Export!A:P,16,0) -> MÓNICA ELIZABETH LINEROS FUENTES | D26: =VLOOKUP(A26,Export!A:H,8,0) -> 61-90 | E26: =VLOOKUP(A26,Export!A:I,9,0) -> 91-120 | F26: C4 | G26: =VLOOKUP(A26,Export!A:AH,34,0) -> NO RECUPERADO | H26: PAGO CUOTAS | I26: 2 | J26: =VLOOKUP(A26,Export!A:B,2,0) -> 97 | K26: =VLOOKUP(A26,Export!A:R,18,0) -> 344.975 | L26: =VLOOKUP(A26,Export!A:D,4,0) -> 10062772 | M26: =IF(H26="PAGO CUOTAS",I26*K26,L26) -> 689.95 | N26: 46233 | O26: PENDIENTE | Q26: =+SUMIF(O26,"PAGADO",L26) -> 0 | S26: FALSE | T26: =VLOOKUP(A26,'OFICIO '!A:J,10,0) -> #N/A
A27: 1769482 | B27: =VLOOKUP(A27,Export!A:N,14,0) -> 16986051 | C27: =VLOOKUP(A27,Export!A:P,16,0) -> CARLOS ANDRES POLANCO DIAZ | D27: =VLOOKUP(A27,Export!A:H,8,0) -> 211-240 | E27: =VLOOKUP(A27,Export!A:I,9,0) -> 241-270 | F27: 90+ | G27: =VLOOKUP(A27,Export!A:AH,34,0) -> NO RECUPERADO | H27: PREPAGO | J27: =VLOOKUP(A27,Export!A:B,2,0) -> 252 | K27: =VLOOKUP(A27,Export!A:R,18,0) -> 336.303 | L27: =VLOOKUP(A27,Export!A:D,4,0) -> 4635527 | M27: =IF(H27="PAGO CUOTAS",I27*K27,L27) -> 4635527 | N27: 46234 | O27: PENDIENTE | Q27: =+SUMIF(O27,"PAGADO",L27) -> 0 | S27: FALSE | T27: =VLOOKUP(A27,'OFICIO '!A:J,10,0) -> #N/A
A28: 2348879 | B28: =VLOOKUP(A28,Export!A:N,14,0) -> 19398935 | C28: =VLOOKUP(A28,Export!A:P,16,0) -> William Anselmo Morales Toro | D28: =VLOOKUP(A28,Export!A:H,8,0) -> 61-90 | E28: =VLOOKUP(A28,Export!A:I,9,0) -> 46052 | F28: C4 | G28: =VLOOKUP(A28,Export!A:AH,34,0) -> BAJA90 | H28: PAGO CUOTAS | I28: 3 | J28: =VLOOKUP(A28,Export!A:B,2,0) -> 15 | K28: =VLOOKUP(A28,Export!A:R,18,0) -> 226.684 | L28: =VLOOKUP(A28,Export!A:D,4,0) -> 4943344 | M28: =IF(H28="PAGO CUOTAS",I28*K28,L28) -> 680.052 | N28: 46218 | O28: PAGADO | Q28: =+SUMIF(O28,"PAGADO",L28) -> 4943344 | S28: FALSE | T28: =VLOOKUP(A28,'OFICIO '!A:J,10,0) -> #N/A
A29: 3378278 | B29: =VLOOKUP(A29,Export!A:N,14,0) -> 10780067 | C29: =VLOOKUP(A29,Export!A:P,16,0) -> HERMAN ROGELIO VELIZ ITE | D29: =VLOOKUP(A29,Export!A:H,8,0) -> 91-120 | E29: =VLOOKUP(A29,Export!A:I,9,0) -> 121-150 | F29: 90+ | G29: =VLOOKUP(A29,Export!A:AH,34,0) -> NO RECUPERADO | H29: PAGO CUOTAS | I29: 2 | J29: =VLOOKUP(A29,Export!A:B,2,0) -> 137 | K29: =VLOOKUP(A29,Export!A:R,18,0) -> 253.855 | L29: =VLOOKUP(A29,Export!A:D,4,0) -> 7299234 | M29: =IF(H29="PAGO CUOTAS",I29*K29,L29) -> 507.71 | N29: 46223 | O29: PENDIENTE | Q29: =+SUMIF(O29,"PAGADO",L29) -> 0 | S29: FALSE | T29: =VLOOKUP(A29,'OFICIO '!A:J,10,0) -> #N/A
A30: 3217807 | B30: =VLOOKUP(A30,Export!A:N,14,0) -> 13014709 | C30: =VLOOKUP(A30,Export!A:P,16,0) -> CLAUDIO ALBERTO MOLINA CHÁVEZ | D30: =VLOOKUP(A30,Export!A:H,8,0) -> 61-90 | E30: =VLOOKUP(A30,Export!A:I,9,0) -> 91-120 | F30: C4 | G30: =VLOOKUP(A30,Export!A:AH,34,0) -> NO RECUPERADO | H30: PAGO CUOTAS | I30: 1 | J30: =VLOOKUP(A30,Export!A:B,2,0) -> 92 | K30: =VLOOKUP(A30,Export!A:R,18,0) -> 443.361 | L30: =VLOOKUP(A30,Export!A:D,4,0) -> 10181670 | M30: =IF(H30="PAGO CUOTAS",I30*K30,L30) -> 443.361 | N30: 46214 | O30: PENDIENTE | Q30: =+SUMIF(O30,"PAGADO",L30) -> 0 | R30: Tit. espera pagar otra cuota 25/07 | S30: FALSE | T30: =VLOOKUP(A30,'OFICIO '!A:J,10,0) -> #N/A
A31: 2545904 | B31: =VLOOKUP(A31,Export!A:N,14,0) -> 13011353 | C31: =VLOOKUP(A31,Export!A:P,16,0) -> MAURICIO ALEJANDRO DIAZ CARRIZO | D31: =VLOOKUP(A31,Export!A:H,8,0) -> 31-60 | E31: =VLOOKUP(A31,Export!A:I,9,0) -> 31-60 | F31: C3 | G31: =VLOOKUP(A31,Export!A:AH,34,0) -> CONTENIDO | H31: PAGO CUOTAS | J31: =VLOOKUP(A31,Export!A:B,2,0) -> 45 | K31: =VLOOKUP(A31,Export!A:R,18,0) -> 189.035 | L31: =VLOOKUP(A31,Export!A:D,4,0) -> 4134127 | M31: =IF(H31="PAGO CUOTAS",I31*K31,L31) -> 0 | N31: 46209 | O31: PAGADO | Q31: =+SUMIF(O31,"PAGADO",L31) -> 4134127 | S31: FALSE | T31: =VLOOKUP(A31,'OFICIO '!A:J,10,0) -> #N/A
A32: 2578418 | B32: =VLOOKUP(A32,Export!A:N,14,0) -> 15815436 | C32: =VLOOKUP(A32,Export!A:P,16,0) -> MARIA ELENA LEAL REYES | D32: =VLOOKUP(A32,Export!A:H,8,0) -> 211-240 | E32: =VLOOKUP(A32,Export!A:I,9,0) -> 241-270 | F32: 90+ | G32: =VLOOKUP(A32,Export!A:AH,34,0) -> NO RECUPERADO | H32: RENEGOCIACIÓN | J32: =VLOOKUP(A32,Export!A:B,2,0) -> 257 | K32: =VLOOKUP(A32,Export!A:R,18,0) -> 420.387 | L32: =VLOOKUP(A32,Export!A:D,4,0) -> 3374696 | M32: =IF(H32="PAGO CUOTAS",I32*K32,L32) -> 3374696 | O32: PENDIENTE | Q32: =+SUMIF(O32,"PAGADO",L32) -> 0 | R32: VOLVER A LLAMAR VIERNES 10 | S32: FALSE | T32: =VLOOKUP(A32,'OFICIO '!A:J,10,0) -> #N/A
A33: 2949060 | B33: =VLOOKUP(A33,Export!A:N,14,0) -> 6756651 | C33: =VLOOKUP(A33,Export!A:P,16,0) -> LUZVENIA DEL CARMEN FIGUEROA REPOL | D33: =VLOOKUP(A33,Export!A:H,8,0) -> 61-90 | E33: =VLOOKUP(A33,Export!A:I,9,0) -> 61-90 | F33: C4 | G33: =VLOOKUP(A33,Export!A:AH,34,0) -> NO RECUPERADO | H33: PAGO CUOTAS | I33: 2 | J33: =VLOOKUP(A33,Export!A:B,2,0) -> 84 | K33: =VLOOKUP(A33,Export!A:R,18,0) -> 227.731 | L33: =VLOOKUP(A33,Export!A:D,4,0) -> 2648525 | M33: =IF(H33="PAGO CUOTAS",I33*K33,L33) -> 455.462 | N33: 46225 | O33: PENDIENTE | Q33: =+SUMIF(O33,"PAGADO",L33) -> 0 | S33: FALSE | T33: =VLOOKUP(A33,'OFICIO '!A:J,10,0) -> #N/A
A34: 3535778 | B34: =VLOOKUP(A34,Export!A:N,14,0) -> 26530441 | C34: =VLOOKUP(A34,Export!A:P,16,0) -> ANDRES EDUARDO MARTINEZ GUEVARA | D34: =VLOOKUP(A34,Export!A:H,8,0) -> 121-150 | E34: =VLOOKUP(A34,Export!A:I,9,0) -> 151-180 | F34: 90+ | G34: =VLOOKUP(A34,Export!A:AH,34,0) -> NO RECUPERADO | H34: DACIÓN | I34: 2 | J34: =VLOOKUP(A34,Export!A:B,2,0) -> 169 | K34: =VLOOKUP(A34,Export!A:R,18,0) -> 266.729 | L34: =VLOOKUP(A34,Export!A:D,4,0) -> 7568627 | M34: =IF(H34="PAGO CUOTAS",I34*K34,L34) -> 7568627 | N34: 46212 | O34: PENDIENTE | Q34: =+SUMIF(O34,"PAGADO",L34) -> 0 | S34: FALSE | T34: =VLOOKUP(A34,'OFICIO '!A:J,10,0) -> #N/A
A35: 3018067 | B35: =VLOOKUP(A35,Export!A:N,14,0) -> 7806553 | C35: =VLOOKUP(A35,Export!A:P,16,0) -> PILAR ISABEL SEPÚLVEDA OLATE | D35: =VLOOKUP(A35,Export!A:H,8,0) -> 121-150 | E35: =VLOOKUP(A35,Export!A:I,9,0) -> 91-120 | F35: 90+ | G35: =VLOOKUP(A35,Export!A:AH,34,0) -> CONTENIDO | H35: PAGO CUOTAS | I35: 2 | J35: =VLOOKUP(A35,Export!A:B,2,0) -> 110 | K35: =VLOOKUP(A35,Export!A:R,18,0) -> 357.516 | L35: =VLOOKUP(A35,Export!A:D,4,0) -> 7330135 | M35: =IF(H35="PAGO CUOTAS",I35*K35,L35) -> 715.032 | N35: 46234 | O35: PAGADO | Q35: =+SUMIF(O35,"PAGADO",L35) -> 7330135 | R35: Tit. pago 1 cta. 09/07 + 1 cta.31/07 | S35: FALSE | T35: =VLOOKUP(A35,'OFICIO '!A:J,10,0) -> #N/A
A36: 2762576 | B36: =VLOOKUP(A36,Export!A:N,14,0) -> 12829586 | C36: =VLOOKUP(A36,Export!A:P,16,0) -> MARÍA ELENA ARENAS VALDENEGRO | D36: =VLOOKUP(A36,Export!A:H,8,0) -> 91-120 | E36: =VLOOKUP(A36,Export!A:I,9,0) -> 31-60 | F36: 90+ | H36: PAGO CUOTAS | I36: 3 | J36: =VLOOKUP(A36,Export!A:B,2,0) -> 44 | K36: =VLOOKUP(A36,Export!A:R,18,0) -> 335.115 | L36: =VLOOKUP(A36,Export!A:D,4,0) -> 5360106 | M36: =IF(H36="PAGO CUOTAS",I36*K36,L36) -> 1005.345 | N36: 46213 | O36: PAGADO | Q36: =+SUMIF(O36,"PAGADO",L36) -> 5360106 | S36: FALSE | T36: =VLOOKUP(A36,'OFICIO '!A:J,10,0) -> #N/A
A37: 1854377 | B37: =VLOOKUP(A37,Export!A:N,14,0) -> 13422825 | C37: =VLOOKUP(A37,Export!A:P,16,0) -> PAMELA ALEJANDRA MIRANDA GARCIA | D37: =VLOOKUP(A37,Export!A:H,8,0) -> 31-60 | E37: =VLOOKUP(A37,Export!A:I,9,0) -> 46052 | F37: C3 | G37: =VLOOKUP(A37,Export!A:AH,34,0) -> CONTENIDO | H37: PAGO CUOTAS | I37: 1 | J37: =VLOOKUP(A37,Export!A:B,2,0) -> 20 | K37: =VLOOKUP(A37,Export!A:R,18,0) -> 236.313 | L37: =VLOOKUP(A37,Export!A:D,4,0) -> 2473233 | M37: =IF(H37="PAGO CUOTAS",I37*K37,L37) -> 236.313 | N37: 46213 | O37: PAGADO | Q37: =+SUMIF(O37,"PAGADO",L37) -> 2473233 | S37: FALSE | T37: =VLOOKUP(A37,'OFICIO '!A:J,10,0) -> 46107
A38: 2916362 | B38: =VLOOKUP(A38,Export!A:N,14,0) -> 17194972 | C38: =VLOOKUP(A38,Export!A:P,16,0) -> DANISA JOHANNA VILCHES ROJAS | D38: =VLOOKUP(A38,Export!A:H,8,0) -> 31-60 | E38: =VLOOKUP(A38,Export!A:I,9,0) -> 31-60 | F38: C3 | G38: =VLOOKUP(A38,Export!A:AH,34,0) -> CONTENIDO | H38: PAGO CUOTAS | I38: 1 | J38: =VLOOKUP(A38,Export!A:B,2,0) -> 45 | K38: =VLOOKUP(A38,Export!A:R,18,0) -> 137.238 | L38: =VLOOKUP(A38,Export!A:D,4,0) -> 1484865 | M38: =IF(H38="PAGO CUOTAS",I38*K38,L38) -> 137.238 | N38: 46204 | O38: PAGADO | Q38: =+SUMIF(O38,"PAGADO",L38) -> 1484865 | S38: FALSE | T38: =VLOOKUP(A38,'OFICIO '!A:J,10,0) -> #N/A
A39: 3455901 | B39: =VLOOKUP(A39,Export!A:N,14,0) -> 15915568 | C39: =VLOOKUP(A39,Export!A:P,16,0) -> RODRIGO ALEXIS MELLA VARGAS | D39: =VLOOKUP(A39,Export!A:H,8,0) -> 121-150 | E39: =VLOOKUP(A39,Export!A:I,9,0) -> 31-60 | F39: 90+ | G39: =VLOOKUP(A39,Export!A:AH,34,0) -> BAJA90 | H39: PAGO CUOTAS | I39: 4 | J39: =VLOOKUP(A39,Export!A:B,2,0) -> 43 | K39: =VLOOKUP(A39,Export!A:R,18,0) -> 207.155 | L39: =VLOOKUP(A39,Export!A:D,4,0) -> 4758382 | M39: =IF(H39="PAGO CUOTAS",I39*K39,L39) -> 828.62 | N39: 46216 | O39: PAGADO | Q39: =+SUMIF(O39,"PAGADO",L39) -> 4758382 | S39: FALSE | T39: =VLOOKUP(A39,'OFICIO '!A:J,10,0) -> #N/A
A40: 3728601 | B40: =VLOOKUP(A40,Export!A:N,14,0) -> 20782949 | C40: =VLOOKUP(A40,Export!A:P,16,0) -> DAFNE DENISSE REYES LEIVA | D40: =VLOOKUP(A40,Export!A:H,8,0) -> 61-90 | E40: =VLOOKUP(A40,Export!A:I,9,0) -> 61-90 | F40: C4 | G40: =VLOOKUP(A40,Export!A:AH,34,0) -> NO RECUPERADO | H40: PAGO CUOTAS | I40: 3 | J40: =VLOOKUP(A40,Export!A:B,2,0) -> 88 | K40: =VLOOKUP(A40,Export!A:R,18,0) -> 418.15 | L40: =VLOOKUP(A40,Export!A:D,4,0) -> 12538556 | M40: =IF(H40="PAGO CUOTAS",I40*K40,L40) -> 1254.45 | N40: 46227 | O40: PENDIENTE | Q40: =+SUMIF(O40,"PAGADO",L40) -> 0 | S40: FALSE | T40: =VLOOKUP(A40,'OFICIO '!A:J,10,0) -> #N/A
A41: 3468638 | B41: =VLOOKUP(A41,Export!A:N,14,0) -> 21240406 | C41: =VLOOKUP(A41,Export!A:P,16,0) -> MIGUEL ALEJANDRO THOMAS RIVADERA | D41: =VLOOKUP(A41,Export!A:H,8,0) -> 121-150 | E41: =VLOOKUP(A41,Export!A:I,9,0) -> 151-180 | F41: 90+ | G41: =VLOOKUP(A41,Export!A:AH,34,0) -> NO RECUPERADO | H41: PAGO CUOTAS | I41: 1 | J41: =VLOOKUP(A41,Export!A:B,2,0) -> 165 | K41: =VLOOKUP(A41,Export!A:R,18,0) -> 270.198 | L41: =VLOOKUP(A41,Export!A:D,4,0) -> 7376704 | M41: =IF(H41="PAGO CUOTAS",I41*K41,L41) -> 270.198 | N41: 46226 | O41: PENDIENTE | Q41: =+SUMIF(O41,"PAGADO",L41) -> 0 | S41: FALSE | T41: =VLOOKUP(A41,'OFICIO '!A:J,10,0) -> #N/A
A42: 3534190 | B42: =VLOOKUP(A42,Export!A:N,14,0) -> 13478543 | C42: =VLOOKUP(A42,Export!A:P,16,0) -> JUAN LUIS RETAMAL PICHIPIL | D42: =VLOOKUP(A42,Export!A:H,8,0) -> 121-150 | E42: =VLOOKUP(A42,Export!A:I,9,0) -> 61-90 | F42: 90+ | G42: =VLOOKUP(A42,Export!A:AH,34,0) -> CONTENIDO | H42: PAGO CUOTAS | I42: 2 | J42: =VLOOKUP(A42,Export!A:B,2,0) -> 80 | K42: =VLOOKUP(A42,Export!A:R,18,0) -> 257.749 | L42: =VLOOKUP(A42,Export!A:D,4,0) -> 6649242 | M42: =IF(H42="PAGO CUOTAS",I42*K42,L42) -> 515.498 | N42: 46227 | O42: PAGADO | Q42: =+SUMIF(O42,"PAGADO",L42) -> 6649242 | R42: Tit. pago 2 ctas. + 1 cuota 24/07 | S42: FALSE | T42: =VLOOKUP(A42,'OFICIO '!A:J,10,0) -> #N/A
A43: 1793060 | B43: =VLOOKUP(A43,Export!A:N,14,0) -> 14562732 | C43: =VLOOKUP(A43,Export!A:P,16,0) -> ALEJANDRO ANTONIO VARGAS VERGARA | D43: =VLOOKUP(A43,Export!A:H,8,0) -> 121-150 | E43: =VLOOKUP(A43,Export!A:I,9,0) -> 151-180 | F43: 90+ | G43: =VLOOKUP(A43,Export!A:AH,34,0) -> NO RECUPERADO | H43: PAGO CUOTAS | I43: 1 | J43: =VLOOKUP(A43,Export!A:B,2,0) -> 164 | K43: =VLOOKUP(A43,Export!A:R,18,0) -> 320.287 | L43: =VLOOKUP(A43,Export!A:D,4,0) -> 621128 | M43: =IF(H43="PAGO CUOTAS",I43*K43,L43) -> 320.287 | N43: 46224 | O43: PENDIENTE | Q43: =+SUMIF(O43,"PAGADO",L43) -> 0 | R43: paga 1 cuota el 17 y otra la siguiente semana | S43: FALSE | T43: =VLOOKUP(A43,'OFICIO '!A:J,10,0) -> #N/A
A44: 2284509 | B44: =VLOOKUP(A44,Export!A:N,14,0) -> 15465536 | C44: =VLOOKUP(A44,Export!A:P,16,0) -> HERNAN ALEJANDRO PEÑA ESTRADA | D44: =VLOOKUP(A44,Export!A:H,8,0) -> 61-90 | E44: =VLOOKUP(A44,Export!A:I,9,0) -> 61-90 | F44: C4 | G44: =VLOOKUP(A44,Export!A:AH,34,0) -> CONTENIDO | H44: PAGO CUOTAS | I44: 1 | J44: =VLOOKUP(A44,Export!A:B,2,0) -> 80 | K44: =VLOOKUP(A44,Export!A:R,18,0) -> 1.593.299 | L44: =VLOOKUP(A44,Export!A:D,4,0) -> 13837185 | M44: =IF(H44="PAGO CUOTAS",I44*K44,L44) -> #VALUE! | N44: 46216 | O44: PAGADO | Q44: =+SUMIF(O44,"PAGADO",L44) -> 13837185 | S44: FALSE | T44: =VLOOKUP(A44,'OFICIO '!A:J,10,0) -> #N/A
A45: 2142176 | B45: =VLOOKUP(A45,Export!A:N,14,0) -> 17280965 | C45: =VLOOKUP(A45,Export!A:P,16,0) -> CRISTIAN ENRIQUE VILLAGRA YAÑEZ | D45: =VLOOKUP(A45,Export!A:H,8,0) -> 151-180 | E45: =VLOOKUP(A45,Export!A:I,9,0) -> 181-210 | F45: 90+ | G45: =VLOOKUP(A45,Export!A:AH,34,0) -> NO RECUPERADO | H45: PAGO CUOTAS | I45: 3 | J45: =VLOOKUP(A45,Export!A:B,2,0) -> 195 | K45: =VLOOKUP(A45,Export!A:R,18,0) -> 228.678 | L45: =VLOOKUP(A45,Export!A:D,4,0) -> 1576260 | M45: =IF(H45="PAGO CUOTAS",I45*K45,L45) -> 686.034 | N45: 46234 | O45: PENDIENTE | Q45: =+SUMIF(O45,"PAGADO",L45) -> 0 | S45: FALSE | T45: =VLOOKUP(A45,'OFICIO '!A:J,10,0) -> #N/A
A46: 3457201 | B46: =VLOOKUP(A46,Export!A:N,14,0) -> 12034672 | C46: =VLOOKUP(A46,Export!A:P,16,0) -> VIVIANA SOLEDAD AGUSTO AVALOS | D46: =VLOOKUP(A46,Export!A:H,8,0) -> 31-60 | E46: =VLOOKUP(A46,Export!A:I,9,0) -> 61-90 | F46: C3 | G46: =VLOOKUP(A46,Export!A:AH,34,0) -> NO RECUPERADO | H46: PAGO CUOTAS | I46: 3 | J46: =VLOOKUP(A46,Export!A:B,2,0) -> 68 | K46: =VLOOKUP(A46,Export!A:R,18,0) -> 412.019 | L46: =VLOOKUP(A46,Export!A:D,4,0) -> 12409556 | M46: =IF(H46="PAGO CUOTAS",I46*K46,L46) -> 1236.057 | N46: 46227 | O46: PENDIENTE | Q46: =+SUMIF(O46,"PAGADO",L46) -> 0 | S46: FALSE | T46: =VLOOKUP(A46,'OFICIO '!A:J,10,0) -> #N/A
A47: 1307975 | B47: =VLOOKUP(A47,Export!A:N,14,0) -> 8560731 | C47: =VLOOKUP(A47,Export!A:P,16,0) -> ANA PAOLA VEGA RODRÍGUEZ | D47: =VLOOKUP(A47,Export!A:H,8,0) -> 91-120 | E47: =VLOOKUP(A47,Export!A:I,9,0) -> 121-150 | F47: 90+ | G47: =VLOOKUP(A47,Export!A:AH,34,0) -> NO RECUPERADO | H47: PAGO CUOTAS | I47: 3 | J47: =VLOOKUP(A47,Export!A:B,2,0) -> 137 | K47: =VLOOKUP(A47,Export!A:R,18,0) -> 208.169 | L47: =VLOOKUP(A47,Export!A:D,4,0) -> 990073 | M47: =IF(H47="PAGO CUOTAS",I47*K47,L47) -> 624.507 | N47: 46234 | O47: PENDIENTE | Q47: =+SUMIF(O47,"PAGADO",L47) -> 0 | S47: FALSE | T47: =VLOOKUP(A47,'OFICIO '!A:J,10,0) -> #N/A
A48: 3353242 | B48: =VLOOKUP(A48,Export!A:N,14,0) -> 17499289 | C48: =VLOOKUP(A48,Export!A:P,16,0) -> JAIRO ABEL SAEZ NAVARRO | D48: =VLOOKUP(A48,Export!A:H,8,0) -> 181-210 | E48: =VLOOKUP(A48,Export!A:I,9,0) -> 61-90 | F48: 90+ | G48: =VLOOKUP(A48,Export!A:AH,34,0) -> BAJA90 | H48: PAGO CUOTAS | I48: 5 | J48: =VLOOKUP(A48,Export!A:B,2,0) -> 66 | K48: =VLOOKUP(A48,Export!A:R,18,0) -> 118.043 | L48: =VLOOKUP(A48,Export!A:D,4,0) -> 4026591 | M48: =IF(H48="PAGO CUOTAS",I48*K48,L48) -> 590.215 | N48: 46218 | O48: PAGADO | Q48: =+SUMIF(O48,"PAGADO",L48) -> 4026591 | R48: pago 4ctas.c/fecha 14/07, falta 1, pago 1 cuota + 17/07 | S48: FALSE | T48: =VLOOKUP(A48,'OFICIO '!A:J,10,0) -> #N/A
A49: 3253109 | B49: =VLOOKUP(A49,Export!A:N,14,0) -> 14242600 | C49: =VLOOKUP(A49,Export!A:P,16,0) -> JULIETA ADRIANA HENRÍQUEZ CAAMAÑO | D49: =VLOOKUP(A49,Export!A:H,8,0) -> 151-180 | E49: =VLOOKUP(A49,Export!A:I,9,0) -> 181-210 | F49: 90+ | G49: =VLOOKUP(A49,Export!A:AH,34,0) -> NO RECUPERADO | H49: PAGO CUOTAS | I49: 4 | J49: =VLOOKUP(A49,Export!A:B,2,0) -> 196 | K49: =VLOOKUP(A49,Export!A:R,18,0) -> 397.005 | L49: =VLOOKUP(A49,Export!A:D,4,0) -> 10350477 | M49: =IF(H49="PAGO CUOTAS",I49*K49,L49) -> 1588.02 | N49: 46227 | O49: PENDIENTE | Q49: =+SUMIF(O49,"PAGADO",L49) -> 0 | S49: FALSE | T49: =VLOOKUP(A49,'OFICIO '!A:J,10,0) -> #N/A
A50: 3425380 | B50: =VLOOKUP(A50,Export!A:N,14,0) -> 10498341 | C50: =VLOOKUP(A50,Export!A:P,16,0) -> PEDRO EDUARDO RAMIREZ VIDAL | D50: =VLOOKUP(A50,Export!A:H,8,0) -> 151-180 | E50: =VLOOKUP(A50,Export!A:I,9,0) -> 181-210 | F50: 90+ | G50: =VLOOKUP(A50,Export!A:AH,34,0) -> NO RECUPERADO | H50: PAGO CUOTAS | I50: 5 | J50: =VLOOKUP(A50,Export!A:B,2,0) -> 198 | K50: =VLOOKUP(A50,Export!A:R,18,0) -> 335.677 | L50: =VLOOKUP(A50,Export!A:D,4,0) -> 9223296 | M50: =IF(H50="PAGO CUOTAS",I50*K50,L50) -> 1678.385 | N50: 46223 | O50: PAGADO | Q50: =+SUMIF(O50,"PAGADO",L50) -> 9223296 | S50: FALSE | T50: =VLOOKUP(A50,'OFICIO '!A:J,10,0) -> #N/A
A51: 3559382 | B51: =VLOOKUP(A51,Export!A:N,14,0) -> 15437007 | C51: =VLOOKUP(A51,Export!A:P,16,0) -> ADRIANA DE LOURDES VIELMA MACHUCA | D51: =VLOOKUP(A51,Export!A:H,8,0) -> 151-180 | E51: =VLOOKUP(A51,Export!A:I,9,0) -> 181-210 | F51: 90+ | G51: =VLOOKUP(A51,Export!A:AH,34,0) -> NO RECUPERADO | H51: PAGO CUOTAS | I51: 5 | J51: =VLOOKUP(A51,Export!A:B,2,0) -> 198 | K51: =VLOOKUP(A51,Export!A:R,18,0) -> 326.37 | L51: =VLOOKUP(A51,Export!A:D,4,0) -> 9566857 | M51: =IF(H51="PAGO CUOTAS",I51*K51,L51) -> 1631.85 | N51: 46226 | O51: PENDIENTE | Q51: =+SUMIF(O51,"PAGADO",L51) -> 0 | S51: FALSE | T51: =VLOOKUP(A51,'OFICIO '!A:J,10,0) -> #N/A
A52: 3509994 | B52: =VLOOKUP(A52,Export!A:N,14,0) -> 15974000 | C52: =VLOOKUP(A52,Export!A:P,16,0) -> ROMINA ALEJANDRA TENORIO ASTUDILLO | D52: =VLOOKUP(A52,Export!A:H,8,0) -> 121-150 | E52: =VLOOKUP(A52,Export!A:I,9,0) -> 61-90 | F52: 90+ | G52: =VLOOKUP(A52,Export!A:AH,34,0) -> BAJA90 | H52: PAGO CUOTAS | I52: 3 | J52: =VLOOKUP(A52,Export!A:B,2,0) -> 61 | K52: =VLOOKUP(A52,Export!A:R,18,0) -> 231.382 | L52: =VLOOKUP(A52,Export!A:D,4,0) -> 3807891 | M52: =IF(H52="PAGO CUOTAS",I52*K52,L52) -> 694.146 | N52: 46218 | O52: PAGADO | Q52: =+SUMIF(O52,"PAGADO",L52) -> 3807891 | S52: FALSE | T52: =VLOOKUP(A52,'OFICIO '!A:J,10,0) -> #N/A
A53: 2472050 | B53: =VLOOKUP(A53,Export!A:N,14,0) -> 11647024 | C53: =VLOOKUP(A53,Export!A:P,16,0) -> JOHANNA LUISA CERDA ROJAS | D53: =VLOOKUP(A53,Export!A:H,8,0) -> 121-150 | E53: =VLOOKUP(A53,Export!A:I,9,0) -> 151-180 | F53: 90 | G53: =VLOOKUP(A53,Export!A:AH,34,0) -> NO RECUPERADO | H53: PAGO CUOTAS | I53: 3 | J53: =VLOOKUP(A53,Export!A:B,2,0) -> 169 | K53: =VLOOKUP(A53,Export!A:R,18,0) -> 224.93 | L53: =VLOOKUP(A53,Export!A:D,4,0) -> 2840554 | M53: =IF(H53="PAGO CUOTAS",I53*K53,L53) -> 674.79 | N53: 46224 | O53: PENDIENTE | Q53: =+SUMIF(O53,"PAGADO",L53) -> 0 | S53: FALSE | T53: =VLOOKUP(A53,'OFICIO '!A:J,10,0) -> #N/A
A54: 2142176 | B54: =VLOOKUP(A54,Export!A:N,14,0) -> 17280965 | C54: =VLOOKUP(A54,Export!A:P,16,0) -> CRISTIAN ENRIQUE VILLAGRA YAÑEZ | D54: =VLOOKUP(A54,Export!A:H,8,0) -> 151-180 | E54: =VLOOKUP(A54,Export!A:I,9,0) -> 181-210 | F54: 90+ | G54: =VLOOKUP(A54,Export!A:AH,34,0) -> NO RECUPERADO | H54: PAGO CUOTAS | I54: 3 | J54: =VLOOKUP(A54,Export!A:B,2,0) -> 195 | K54: =VLOOKUP(A54,Export!A:R,18,0) -> 228.678 | L54: =VLOOKUP(A54,Export!A:D,4,0) -> 1576260 | M54: =IF(H54="PAGO CUOTAS",I54*K54,L54) -> 686.034 | N54: 46233 | O54: PENDIENTE | Q54: =+SUMIF(O54,"PAGADO",L54) -> 0 | S54: FALSE | T54: =VLOOKUP(A54,'OFICIO '!A:J,10,0) -> #N/A
A55: 3334914 | B55: =VLOOKUP(A55,Export!A:N,14,0) -> 9507551 | C55: =VLOOKUP(A55,Export!A:P,16,0) -> JUAN LUIS HERNANDEZ ALMONACID | D55: =VLOOKUP(A55,Export!A:H,8,0) -> 121-150 | E55: =VLOOKUP(A55,Export!A:I,9,0) -> 151-180 | F55: 90+ | G55: =VLOOKUP(A55,Export!A:AH,34,0) -> NO RECUPERADO | H55: PAGO CUOTAS | I55: 3 | J55: =VLOOKUP(A55,Export!A:B,2,0) -> 165 | K55: =VLOOKUP(A55,Export!A:R,18,0) -> 367.186 | L55: =VLOOKUP(A55,Export!A:D,4,0) -> 10255953 | M55: =IF(H55="PAGO CUOTAS",I55*K55,L55) -> 1101.558 | N55: 46223 | O55: PENDIENTE | Q55: =+SUMIF(O55,"PAGADO",L55) -> 0 | S55: FALSE | T55: =VLOOKUP(A55,'OFICIO '!A:J,10,0) -> #N/A
A56: 1793060 | B56: =VLOOKUP(A56,Export!A:N,14,0) -> 14562732 | C56: =VLOOKUP(A56,Export!A:P,16,0) -> ALEJANDRO ANTONIO VARGAS VERGARA | D56: =VLOOKUP(A56,Export!A:H,8,0) -> 121-150 | E56: =VLOOKUP(A56,Export!A:I,9,0) -> 151-180 | F56: 90+ | G56: =VLOOKUP(A56,Export!A:AH,34,0) -> NO RECUPERADO | H56: PAGO CUOTAS | I56: 2 | J56: =VLOOKUP(A56,Export!A:B,2,0) -> 164 | K56: =VLOOKUP(A56,Export!A:R,18,0) -> 320.287 | L56: =VLOOKUP(A56,Export!A:D,4,0) -> 621128 | M56: =IF(H56="PAGO CUOTAS",I56*K56,L56) -> 640.574 | N56: 46224 | O56: PENDIENTE | Q56: =+SUMIF(O56,"PAGADO",L56) -> 0 | S56: FALSE | T56: =VLOOKUP(A56,'OFICIO '!A:J,10,0) -> #N/A
A57: 3033889 | B57: =VLOOKUP(A57,Export!A:N,14,0) -> 17440023 | C57: =VLOOKUP(A57,Export!A:P,16,0) -> FRANCISCO JAVIER AYULEF LARA | D57: =VLOOKUP(A57,Export!A:H,8,0) -> 181-210 | E57: =VLOOKUP(A57,Export!A:I,9,0) -> 211-240 | F57: 90+ | G57: =VLOOKUP(A57,Export!A:AH,34,0) -> NO RECUPERADO | H57: PAGO CUOTAS | I57: 8 | J57: =VLOOKUP(A57,Export!A:B,2,0) -> 222 | K57: =VLOOKUP(A57,Export!A:R,18,0) -> 116.027 | L57: =VLOOKUP(A57,Export!A:D,4,0) -> 1884519 | M57: =IF(H57="PAGO CUOTAS",I57*K57,L57) -> 928.216 | N57: 46234 | O57: PENDIENTE | Q57: =+SUMIF(O57,"PAGADO",L57) -> 0 | S57: FALSE | T57: =VLOOKUP(A57,'OFICIO '!A:J,10,0) -> #N/A
A58: 2671637 | B58: =VLOOKUP(A58,Export!A:N,14,0) -> 13865701 | C58: =VLOOKUP(A58,Export!A:P,16,0) -> CARLOS ALBERTO MANRIQUEZ GARCIA | D58: =VLOOKUP(A58,Export!A:H,8,0) -> 121-150 | E58: =VLOOKUP(A58,Export!A:I,9,0) -> 151-180 | F58: 90+ | G58: =VLOOKUP(A58,Export!A:AH,34,0) -> NO RECUPERADO | H58: PAGO CUOTAS | I58: 3 | J58: =VLOOKUP(A58,Export!A:B,2,0) -> 160 | K58: =VLOOKUP(A58,Export!A:R,18,0) -> 376.36 | L58: =VLOOKUP(A58,Export!A:D,4,0) -> 5817589 | M58: =IF(H58="PAGO CUOTAS",I58*K58,L58) -> 1129.08 | N58: 46234 | O58: PENDIENTE | Q58: =+SUMIF(O58,"PAGADO",L58) -> 0 | S58: FALSE | T58: =VLOOKUP(A58,'OFICIO '!A:J,10,0) -> #N/A
A59: 2678831 | B59: =VLOOKUP(A59,Export!A:N,14,0) -> 26423358 | C59: =VLOOKUP(A59,Export!A:P,16,0) -> CARLOS EDUARDO GUERRA YAÑEZ | D59: =VLOOKUP(A59,Export!A:H,8,0) -> 31-60 | E59: =VLOOKUP(A59,Export!A:I,9,0) -> 31-60 | F59: C3 | G59: =VLOOKUP(A59,Export!A:AH,34,0) -> CONTENIDO | H59: PAGO CUOTAS | I59: 1 | J59: =VLOOKUP(A59,Export!A:B,2,0) -> 40 | K59: =VLOOKUP(A59,Export!A:R,18,0) -> 203.815 | L59: =VLOOKUP(A59,Export!A:D,4,0) -> 2891119 | M59: =IF(H59="PAGO CUOTAS",I59*K59,L59) -> 203.815 | N59: 46223 | O59: PAGADO | Q59: =+SUMIF(O59,"PAGADO",L59) -> 2891119 | S59: FALSE | T59: =VLOOKUP(A59,'OFICIO '!A:J,10,0) -> 46054
A60: 3102979 | B60: =VLOOKUP(A60,Export!A:N,14,0) -> 25491462 | C60: =VLOOKUP(A60,Export!A:P,16,0) -> MARIANTONIETA ZUBILLAGA CACERES | D60: =VLOOKUP(A60,Export!A:H,8,0) -> 121-150 | E60: =VLOOKUP(A60,Export!A:I,9,0) -> 151-180 | F60: 90+ | G60: =VLOOKUP(A60,Export!A:AH,34,0) -> NO RECUPERADO | H60: PAGO CUOTAS | I60: 3 | J60: =VLOOKUP(A60,Export!A:B,2,0) -> 169 | K60: =VLOOKUP(A60,Export!A:R,18,0) -> 324.755 | L60: =VLOOKUP(A60,Export!A:D,4,0) -> 7415152 | M60: =IF(H60="PAGO CUOTAS",I60*K60,L60) -> 974.265 | N60: 46225 | O60: PENDIENTE | Q60: =+SUMIF(O60,"PAGADO",L60) -> 0 | S60: FALSE | T60: =VLOOKUP(A60,'OFICIO '!A:J,10,0) -> #N/A
A61: 3172499 | B61: =VLOOKUP(A61,Export!A:N,14,0) -> 18017458 | C61: =VLOOKUP(A61,Export!A:P,16,0) -> GERARDO AURELIO ANIÑIR ANTIMÁN | D61: =VLOOKUP(A61,Export!A:H,8,0) -> 31-60 | E61: =VLOOKUP(A61,Export!A:I,9,0) -> 61-90 | F61: C3 | G61: =VLOOKUP(A61,Export!A:AH,34,0) -> NO RECUPERADO | H61: PAGO CUOTAS | I61: 1 | J61: =VLOOKUP(A61,Export!A:B,2,0) -> 61 | K61: =VLOOKUP(A61,Export!A:R,18,0) -> 174.954 | L61: =VLOOKUP(A61,Export!A:D,4,0) -> 3821549 | M61: =IF(H61="PAGO CUOTAS",I61*K61,L61) -> 174.954 | N61: 46223 | O61: PAGADO | Q61: =+SUMIF(O61,"PAGADO",L61) -> 3821549 | S61: FALSE | T61: =VLOOKUP(A61,'OFICIO '!A:J,10,0) -> #N/A
A62: 3378278 | B62: =VLOOKUP(A62,Export!A:N,14,0) -> 10780067 | C62: =VLOOKUP(A62,Export!A:P,16,0) -> HERMAN ROGELIO VELIZ ITE | D62: =VLOOKUP(A62,Export!A:H,8,0) -> 91-120 | E62: =VLOOKUP(A62,Export!A:I,9,0) -> 121-150 | F62: 90+ | G62: =VLOOKUP(A62,Export!A:AH,34,0) -> NO RECUPERADO | H62: PAGO CUOTAS | I62: 2 | J62: =VLOOKUP(A62,Export!A:B,2,0) -> 137 | K62: =VLOOKUP(A62,Export!A:R,18,0) -> 253.855 | L62: =VLOOKUP(A62,Export!A:D,4,0) -> 7299234 | M62: =IF(H62="PAGO CUOTAS",I62*K62,L62) -> 507.71 | N62: 46223 | O62: PENDIENTE | Q62: =+SUMIF(O62,"PAGADO",L62) -> 0 | S62: FALSE | T62: =VLOOKUP(A62,'OFICIO '!A:J,10,0) -> #N/A
A63: 3248956 | B63: =VLOOKUP(A63,Export!A:N,14,0) -> 15744477 | C63: =VLOOKUP(A63,Export!A:P,16,0) -> CARLOS ANDRÉS MATURANA SOTO | D63: =VLOOKUP(A63,Export!A:H,8,0) -> 151-180 | E63: =VLOOKUP(A63,Export!A:I,9,0) -> 181-210 | F63: 90+ | G63: =VLOOKUP(A63,Export!A:AH,34,0) -> NO RECUPERADO | H63: PAGO CUOTAS | I63: 4 | J63: =VLOOKUP(A63,Export!A:B,2,0) -> 196 | K63: =VLOOKUP(A63,Export!A:R,18,0) -> 568.533 | L63: =VLOOKUP(A63,Export!A:D,4,0) -> 6371861 | M63: =IF(H63="PAGO CUOTAS",I63*K63,L63) -> 2274.132 | N63: 46230 | O63: PENDIENTE | Q63: =+SUMIF(O63,"PAGADO",L63) -> 0 | S63: FALSE | T63: =VLOOKUP(A63,'OFICIO '!A:J,10,0) -> #N/A
A64: 3632660 | B64: =VLOOKUP(A64,Export!A:N,14,0) -> 7944304 | C64: =VLOOKUP(A64,Export!A:P,16,0) -> JAIME DEL CARMEN HERRERA DELGADO | D64: =VLOOKUP(A64,Export!A:H,8,0) -> 31-60 | E64: =VLOOKUP(A64,Export!A:I,9,0) -> 61-90 | F64: C3 | G64: =VLOOKUP(A64,Export!A:AH,34,0) -> NO RECUPERADO | H64: PAGO CUOTAS | I64: 3 | J64: =VLOOKUP(A64,Export!A:B,2,0) -> 69 | K64: =VLOOKUP(A64,Export!A:R,18,0) -> 351.237 | L64: =VLOOKUP(A64,Export!A:D,4,0) -> 11368089 | M64: =IF(H64="PAGO CUOTAS",I64*K64,L64) -> 1053.711 | N64: 46227 | O64: PENDIENTE | Q64: =+SUMIF(O64,"PAGADO",L64) -> 0 | S64: FALSE | T64: =VLOOKUP(A64,'OFICIO '!A:J,10,0) -> #N/A
B65: =VLOOKUP(A65,Export!A:N,14,0) -> #N/A | C65: =VLOOKUP(A65,Export!A:P,16,0) -> #N/A | D65: =VLOOKUP(A65,Export!A:H,8,0) -> #N/A | E65: =VLOOKUP(A65,Export!A:I,9,0) -> #N/A | G65: =VLOOKUP(A65,Export!A:AH,34,0) -> #N/A | J65: =VLOOKUP(A65,Export!A:B,2,0) -> #N/A | K65: =VLOOKUP(A65,Export!A:R,18,0) -> #N/A | L65: =VLOOKUP(A65,Export!A:D,4,0) -> #N/A | M65: =IF(H65="PAGO CUOTAS",I65*K65,L65) -> #N/A | O65: PENDIENTE | Q65: =+SUMIF(O65,"PAGADO",L65) -> 0 | S65: FALSE | T65: =VLOOKUP(A65,'OFICIO '!A:J,10,0) -> #N/A
B66: =VLOOKUP(A66,Export!A:N,14,0) -> #N/A | C66: =VLOOKUP(A66,Export!A:P,16,0) -> #N/A | D66: =VLOOKUP(A66,Export!A:H,8,0) -> #N/A | E66: =VLOOKUP(A66,Export!A:I,9,0) -> #N/A | G66: =VLOOKUP(A66,Export!A:AH,34,0) -> #N/A | J66: =VLOOKUP(A66,Export!A:B,2,0) -> #N/A | K66: =VLOOKUP(A66,Export!A:R,18,0) -> #N/A | L66: =VLOOKUP(A66,Export!A:D,4,0) -> #N/A | M66: =IF(H66="PAGO CUOTAS",I66*K66,L66) -> #N/A | O66: PENDIENTE | Q66: =+SUMIF(O66,"PAGADO",L66) -> 0 | S66: FALSE | T66: =VLOOKUP(A66,'OFICIO '!A:J,10,0) -> #N/A
B67: =VLOOKUP(A67,Export!A:N,14,0) -> #N/A | C67: =VLOOKUP(A67,Export!A:P,16,0) -> #N/A | D67: =VLOOKUP(A67,Export!A:H,8,0) -> #N/A | E67: =VLOOKUP(A67,Export!A:I,9,0) -> #N/A | G67: =VLOOKUP(A67,Export!A:AH,34,0) -> #N/A | J67: =VLOOKUP(A67,Export!A:B,2,0) -> #N/A | K67: =VLOOKUP(A67,Export!A:R,18,0) -> #N/A | L67: =VLOOKUP(A67,Export!A:D,4,0) -> #N/A | M67: =IF(H67="PAGO CUOTAS",I67*K67,L67) -> #N/A | O67: PENDIENTE | Q67: =+SUMIF(O67,"PAGADO",L67) -> 0 | S67: FALSE | T67: =VLOOKUP(A67,'OFICIO '!A:J,10,0) -> #N/A
B68: =VLOOKUP(A68,Export!A:N,14,0) -> #N/A | C68: =VLOOKUP(A68,Export!A:P,16,0) -> #N/A | D68: =VLOOKUP(A68,Export!A:H,8,0) -> #N/A | E68: =VLOOKUP(A68,Export!A:I,9,0) -> #N/A | G68: =VLOOKUP(A68,Export!A:AH,34,0) -> #N/A | J68: =VLOOKUP(A68,Export!A:B,2,0) -> #N/A | K68: =VLOOKUP(A68,Export!A:R,18,0) -> #N/A | L68: =VLOOKUP(A68,Export!A:D,4,0) -> #N/A | M68: =IF(H68="PAGO CUOTAS",I68*K68,L68) -> #N/A | O68: PENDIENTE | Q68: =+SUMIF(O68,"PAGADO",L68) -> 0 | S68: FALSE | T68: =VLOOKUP(A68,'OFICIO '!A:J,10,0) -> #N/A
B69: =VLOOKUP(A69,Export!A:N,14,0) -> #N/A | C69: =VLOOKUP(A69,Export!A:P,16,0) -> #N/A | D69: =VLOOKUP(A69,Export!A:H,8,0) -> #N/A | E69: =VLOOKUP(A69,Export!A:I,9,0) -> #N/A | G69: =VLOOKUP(A69,Export!A:AH,34,0) -> #N/A | J69: =VLOOKUP(A69,Export!A:B,2,0) -> #N/A | K69: =VLOOKUP(A69,Export!A:R,18,0) -> #N/A | L69: =VLOOKUP(A69,Export!A:D,4,0) -> #N/A | M69: =IF(H69="PAGO CUOTAS",I69*K69,L69) -> #N/A | O69: PENDIENTE | Q69: =+SUMIF(O69,"PAGADO",L69) -> 0 | S69: FALSE | T69: =VLOOKUP(A69,'OFICIO '!A:J,10,0) -> #N/A
B70: =VLOOKUP(A70,Export!A:N,14,0) -> #N/A | C70: =VLOOKUP(A70,Export!A:P,16,0) -> #N/A | D70: =VLOOKUP(A70,Export!A:H,8,0) -> #N/A | E70: =VLOOKUP(A70,Export!A:I,9,0) -> #N/A | G70: =VLOOKUP(A70,Export!A:AH,34,0) -> #N/A | J70: =VLOOKUP(A70,Export!A:B,2,0) -> #N/A | K70: =VLOOKUP(A70,Export!A:R,18,0) -> #N/A | L70: =VLOOKUP(A70,Export!A:D,4,0) -> #N/A | M70: =IF(H70="PAGO CUOTAS",I70*K70,L70) -> #N/A | O70: PENDIENTE | Q70: =+SUMIF(O70,"PAGADO",L70) -> 0 | S70: FALSE | T70: =VLOOKUP(A70,'OFICIO '!A:J,10,0) -> #N/A
B71: =VLOOKUP(A71,Export!A:N,14,0) -> #N/A | C71: =VLOOKUP(A71,Export!A:P,16,0) -> #N/A | D71: =VLOOKUP(A71,Export!A:H,8,0) -> #N/A | E71: =VLOOKUP(A71,Export!A:I,9,0) -> #N/A | G71: =VLOOKUP(A71,Export!A:AH,34,0) -> #N/A | J71: =VLOOKUP(A71,Export!A:B,2,0) -> #N/A | K71: =VLOOKUP(A71,Export!A:R,18,0) -> #N/A | L71: =VLOOKUP(A71,Export!A:D,4,0) -> #N/A | M71: =IF(H71="PAGO CUOTAS",I71*K71,L71) -> #N/A | O71: PENDIENTE | Q71: =+SUMIF(O71,"PAGADO",L71) -> 0 | S71: FALSE | T71: =VLOOKUP(A71,'OFICIO '!A:J,10,0) -> #N/A
B72: =VLOOKUP(A72,Export!A:N,14,0) -> #N/A | C72: =VLOOKUP(A72,Export!A:P,16,0) -> #N/A | D72: =VLOOKUP(A72,Export!A:H,8,0) -> #N/A | E72: =VLOOKUP(A72,Export!A:I,9,0) -> #N/A | G72: =VLOOKUP(A72,Export!A:AH,34,0) -> #N/A | J72: =VLOOKUP(A72,Export!A:B,2,0) -> #N/A | K72: =VLOOKUP(A72,Export!A:R,18,0) -> #N/A | L72: =VLOOKUP(A72,Export!A:D,4,0) -> #N/A | M72: =IF(H72="PAGO CUOTAS",I72*K72,L72) -> #N/A | O72: PENDIENTE | Q72: =+SUMIF(O72,"PAGADO",L72) -> 0 | S72: FALSE | T72: =VLOOKUP(A72,'OFICIO '!A:J,10,0) -> #N/A
B73: =VLOOKUP(A73,Export!A:N,14,0) -> #N/A | C73: =VLOOKUP(A73,Export!A:P,16,0) -> #N/A | D73: =VLOOKUP(A73,Export!A:H,8,0) -> #N/A | E73: =VLOOKUP(A73,Export!A:I,9,0) -> #N/A | G73: =VLOOKUP(A73,Export!A:AH,34,0) -> #N/A | J73: =VLOOKUP(A73,Export!A:B,2,0) -> #N/A | K73: =VLOOKUP(A73,Export!A:R,18,0) -> #N/A | L73: =VLOOKUP(A73,Export!A:D,4,0) -> #N/A | M73: =IF(H73="PAGO CUOTAS",I73*K73,L73) -> #N/A | O73: PENDIENTE | Q73: =+SUMIF(O73,"PAGADO",L73) -> 0 | S73: FALSE | T73: =VLOOKUP(A73,'OFICIO '!A:J,10,0) -> #N/A
B74: =VLOOKUP(A74,Export!A:N,14,0) -> #N/A | C74: =VLOOKUP(A74,Export!A:P,16,0) -> #N/A | D74: =VLOOKUP(A74,Export!A:H,8,0) -> #N/A | E74: =VLOOKUP(A74,Export!A:I,9,0) -> #N/A | G74: =VLOOKUP(A74,Export!A:AH,34,0) -> #N/A | J74: =VLOOKUP(A74,Export!A:B,2,0) -> #N/A | K74: =VLOOKUP(A74,Export!A:R,18,0) -> #N/A | L74: =VLOOKUP(A74,Export!A:D,4,0) -> #N/A | M74: =IF(H74="PAGO CUOTAS",I74*K74,L74) -> #N/A | O74: PENDIENTE | Q74: =+SUMIF(O74,"PAGADO",L74) -> 0 | S74: FALSE | T74: =VLOOKUP(A74,'OFICIO '!A:J,10,0) -> #N/A
B75: =VLOOKUP(A75,Export!A:N,14,0) -> #N/A | C75: =VLOOKUP(A75,Export!A:P,16,0) -> #N/A | D75: =VLOOKUP(A75,Export!A:H,8,0) -> #N/A | E75: =VLOOKUP(A75,Export!A:I,9,0) -> #N/A | G75: =VLOOKUP(A75,Export!A:AH,34,0) -> #N/A | J75: =VLOOKUP(A75,Export!A:B,2,0) -> #N/A | K75: =VLOOKUP(A75,Export!A:R,18,0) -> #N/A | L75: =VLOOKUP(A75,Export!A:D,4,0) -> #N/A | M75: =IF(H75="PAGO CUOTAS",I75*K75,L75) -> #N/A | O75: PENDIENTE | Q75: =+SUMIF(O75,"PAGADO",L75) -> 0 | S75: FALSE | T75: =VLOOKUP(A75,'OFICIO '!A:J,10,0) -> #N/A
B76: =VLOOKUP(A76,Export!A:N,14,0) -> #N/A | C76: =VLOOKUP(A76,Export!A:P,16,0) -> #N/A | D76: =VLOOKUP(A76,Export!A:H,8,0) -> #N/A | E76: =VLOOKUP(A76,Export!A:I,9,0) -> #N/A | G76: =VLOOKUP(A76,Export!A:AH,34,0) -> #N/A | J76: =VLOOKUP(A76,Export!A:B,2,0) -> #N/A | K76: =VLOOKUP(A76,Export!A:R,18,0) -> #N/A | L76: =VLOOKUP(A76,Export!A:D,4,0) -> #N/A | M76: =IF(H76="PAGO CUOTAS",I76*K76,L76) -> #N/A | O76: PENDIENTE | Q76: =+SUMIF(O76,"PAGADO",L76) -> 0 | S76: FALSE | T76: =VLOOKUP(A76,'OFICIO '!A:J,10,0) -> #N/A
B77: =VLOOKUP(A77,Export!A:N,14,0) -> #N/A | C77: =VLOOKUP(A77,Export!A:P,16,0) -> #N/A | D77: =VLOOKUP(A77,Export!A:H,8,0) -> #N/A | E77: =VLOOKUP(A77,Export!A:I,9,0) -> #N/A | G77: =VLOOKUP(A77,Export!A:AH,34,0) -> #N/A | J77: =VLOOKUP(A77,Export!A:B,2,0) -> #N/A | K77: =VLOOKUP(A77,Export!A:R,18,0) -> #N/A | L77: =VLOOKUP(A77,Export!A:D,4,0) -> #N/A | M77: =IF(H77="PAGO CUOTAS",I77*K77,L77) -> #N/A | O77: PENDIENTE | Q77: =+SUMIF(O77,"PAGADO",L77) -> 0 | S77: FALSE | T77: =VLOOKUP(A77,'OFICIO '!A:J,10,0) -> #N/A
B85: C4 TUBO | C85: =+SUMIF(D:D,"61-90",L:L) -> 99876811 | D85: =+COUNTIF(F:F,"C4")-E88 -> 14
B86: META | C86: 118000000
B87: % TUBO | C87: =C85/C86 -> 0.84641365
B88: C4 PAGADO | C88: =+SUMIFS(L:L,O:O,"PAGADO",D:D,"61-90") -> 64445288 | D88: =+COUNTIFS(F:F,"C4",O:O,"PAGADO") -> 10
B89: % PAGADO | C89: =+C88/C86 -> 0.54614651
B91: 90+ TUBO | C91: =+SUMIF(F:F,"90+",L:L) -> 185558044 | D91: =+COUNTIF(F:F,"90+")-D94 -> 21
B92: META | C92: 188000000
B93: % TUBO | C93: =C91/C92 -> 0.98701087
B94: 90+ PAGADO | C94: =+SUMIFS(L:L,O:O,"PAGADO",F:F,"90+") -> 65699094 | D94: =+COUNTIFS(F:F,"90+",O:O,"PAGADO") -> 13
B95: % PAGADO | C95: =+C94/C92 -> 0.34946327

Sheet CASTIGO JULIO
A1: CREDITO | B1: RUT | C1: NOMBRE | D1: SOLUCION | E1: INSOLUTO | F1: CUOTAS EN EL MES | G1: CUOTA | H1: CUOTA PAGADA | I1: FECHA COMPROMISO | J1: ESTADO | K1: FECHA PAGO | L1: RECUPERADO | M1: AUDIO | N1: OBSERVACIONES
A2: 2359330 | B2: =VLOOKUP(A2,Export!A:N,14,0) -> 14387173 | C2: =VLOOKUP(A2,Export!A:P,16,0) -> SOLEDAD DEL CARMEN ALFARO PINTO | D2: PLAN DE PAGO | E2: =VLOOKUP(A2,Export!A:D,4,0) -> 17079615 | F2: 1 | G2: =+VLOOKUP(A2,'PLAN DE PAGO'!A:D,4,0) -> 294000 | H2: 6/48 | I2: 46203 | J2: PAGADO | K2: 46203 | L2: =+G2*F2 -> 294000 | M2: FALSE | N2: sin subir a flokzu
A3: 1923591 | B3: =VLOOKUP(A3,Export!A:N,14,0) -> 16647012 | C3: =VLOOKUP(A3,Export!A:P,16,0) -> FABRICIO ALEJANDRO VALENZUELA LEIVA | D3: PLAN DE PAGO | E3: =VLOOKUP(A3,Export!A:D,4,0) -> 11082144 | F3: 1 | G3: =+VLOOKUP(A3,'PLAN DE PAGO'!A:D,4,0) -> 170895 | H3: 9 | I3: 46234 | J3: PAGADO | K3: 46206 | L3: =+G3*F3 -> 170895 | M3: FALSE | N3: u pago
A4: 1987553 | B4: =VLOOKUP(A4,Export!A:N,14,0) -> 15242687 | C4: =VLOOKUP(A4,Export!A:P,16,0) -> GIORGIO GENNARO SARTORI TORRES | D4: PLAN DE PAGO | E4: =VLOOKUP(A4,Export!A:D,4,0) -> 10554087 | G4: =+VLOOKUP(A4,'PLAN DE PAGO'!A:D,4,0) -> 348087 | H4: 3/24 | J4: PENDIENTE | L4: =+G4*F4 -> 0 | M4: FALSE
A5: 1769156 | B5: =VLOOKUP(A5,Export!A:N,14,0) -> 7710884 | C5: =VLOOKUP(A5,Export!A:P,16,0) -> MARÍA ANGÉLICA VERGARA SILVA | D5: PLAN DE PAGO | E5: =VLOOKUP(A5,Export!A:D,4,0) -> 7241243 | G5: =+VLOOKUP(A5,'PLAN DE PAGO'!A:D,4,0) -> 197552 | H5: 8 | J5: PENDIENTE | L5: =+G5*F5 -> 0 | M5: FALSE
A6: 1700218 | B6: =VLOOKUP(A6,Export!A:N,14,0) -> 12218160 | C6: =VLOOKUP(A6,Export!A:P,16,0) -> JUAN ALEX OLIVARES ALANO | D6: PLAN DE PAGO | E6: =VLOOKUP(A6,Export!A:D,4,0) -> 6879999 | F6: 2 | G6: =+VLOOKUP(A6,'PLAN DE PAGO'!A:D,4,0) -> 259734 | H6: 46055 | J6: PENDIENTE | L6: =+G6*F6 -> 519468 | M6: FALSE
A7: 2359330 | B7: =VLOOKUP(A7,Export!A:N,14,0) -> 14387173 | C7: =VLOOKUP(A7,Export!A:P,16,0) -> SOLEDAD DEL CARMEN ALFARO PINTO | D7: PLAN DE PAGO | E7: =VLOOKUP(A7,Export!A:D,4,0) -> 17079615 | G7: =+VLOOKUP(A7,'PLAN DE PAGO'!A:D,4,0) -> 294000 | H7: 7/48 | J7: PENDIENTE | L7: =+G7*F7 -> 0 | M7: FALSE
A8: 2410360 | B8: =VLOOKUP(A8,Export!A:N,14,0) -> 13291544 | C8: =VLOOKUP(A8,Export!A:P,16,0) -> ANDREA DEL PILAR GONZÁLEZ URETA | D8: PLAN DE PAGO | E8: =VLOOKUP(A8,Export!A:D,4,0) -> 5047680 | G8: =+VLOOKUP(A8,'PLAN DE PAGO'!A:D,4,0) -> 246730 | H8: 7/16 | J8: PENDIENTE | L8: =+G8*F8 -> 0 | M8: FALSE
A9: 1769156 | B9: =VLOOKUP(A9,Export!A:N,14,0) -> 7710884 | C9: =VLOOKUP(A9,Export!A:P,16,0) -> MARÍA ANGÉLICA VERGARA SILVA | D9: PLAN DE PAGO | E9: =VLOOKUP(A9,Export!A:D,4,0) -> 7241243 | G9: =+VLOOKUP(A9,'PLAN DE PAGO'!A:D,4,0) -> 197552 | H9: 10 | J9: PENDIENTE | L9: =+G9*F9 -> 0 | M9: FALSE
A10: 1638465 | B10: =VLOOKUP(A10,Export!A:N,14,0) -> 27070326 | C10: =VLOOKUP(A10,Export!A:P,16,0) -> LIBIA ROSA VERA TUBIÑEZ | D10: PLAN DE PAGO | E10: =VLOOKUP(A10,Export!A:D,4,0) -> 3871396 | G10: =+VLOOKUP(A10,'PLAN DE PAGO'!A:D,4,0) -> 172022 | H10: 8/18 | J10: PENDIENTE | L10: =+G10*F10 -> 0 | M10: FALSE
A11: 2041907 | B11: =VLOOKUP(A11,Export!A:N,14,0) -> 12446328 | C11: =VLOOKUP(A11,Export!A:P,16,0) -> CLAUDIA LORENA ROJAS ARRIARÁN | D11: PLAN DE PAGO | E11: =VLOOKUP(A11,Export!A:D,4,0) -> 8500246 | F11: 1 | G11: =+VLOOKUP(A11,'PLAN DE PAGO'!A:D,4,0) -> 202800 | H11: 7/36 | I11: 46203 | J11: PAGADO | K11: 46203 | L11: =+G11*F11 -> 202800 | M11: FALSE | N11: sin subir a flokzu
A12: 1791083 | B12: =VLOOKUP(A12,Export!A:N,14,0) -> 15236244 | C12: =VLOOKUP(A12,Export!A:P,16,0) -> RUBÉN ANER CARILAO BARRA | D12: PLAN DE PAGO | E12: =VLOOKUP(A12,Export!A:D,4,0) -> 7569433 | G12: =+VLOOKUP(A12,'PLAN DE PAGO'!A:D,4,0) -> 273726 | H12: nc | J12: PENDIENTE | L12: =+G12*F12 -> 0 | M12: FALSE
A13: 1644932 | B13: =VLOOKUP(A13,Export!A:N,14,0) -> 16002296 | C13: =VLOOKUP(A13,Export!A:P,16,0) -> MIGUEL ANGEL ACEVEDO ARAVENA | D13: PLAN DE PAGO | E13: =VLOOKUP(A13,Export!A:D,4,0) -> 4868802 | G13: =+VLOOKUP(A13,'PLAN DE PAGO'!A:D,4,0) -> 148700 | H13: 2/24 | J13: PENDIENTE | L13: =+G13*F13 -> 0 | M13: FALSE
A14: 2242697 | B14: =VLOOKUP(A14,Export!A:N,14,0) -> 76478759 | C14: =VLOOKUP(A14,Export!A:P,16,0) -> SOLUCIONES DE INGENIERÍA CESAR CESPEDES SPA | D14: PUT EN PARTES | E14: =VLOOKUP(A14,Export!A:D,4,0) -> 14329489 | G14: 2723220 | H14: 2/4 | J14: PENDIENTE | L14: =+G14*F14 -> 0 | M14: FALSE
A15: 2757617 | B15: =VLOOKUP(A15,Export!A:N,14,0) -> 10908669 | C15: =VLOOKUP(A15,Export!A:P,16,0) -> OSCAR RICARDO ROMERO GONZÁLEZ | D15: NUEVO PLAN DE PAGO | E15: =VLOOKUP(A15,Export!A:D,4,0) -> 9115829 | G15: 1500000 | J15: PENDIENTE | L15: =+G15*F15 -> 0 | M15: FALSE | N15: abono 250 + 800
A16: 2056023 | B16: =VLOOKUP(A16,Export!A:N,14,0) -> 76823538 | C16: =VLOOKUP(A16,Export!A:P,16,0) -> COMERCIALIZADORA CORRALES DEL CAMPO CL SPA | D16: NUEVO PLAN DE PAGO | E16: =VLOOKUP(A16,Export!A:D,4,0) -> 13686046 | G16: 3000000 | J16: PENDIENTE | L16: =+G16*F16 -> 0 | M16: FALSE
A17: 1966918 | B17: =VLOOKUP(A17,Export!A:N,14,0) -> 15167058 | C17: =VLOOKUP(A17,Export!A:P,16,0) -> CRISTIAN ALBERTO REYES INZUNZA | D17: PLAN DE PAGO | E17: =VLOOKUP(A17,Export!A:D,4,0) -> 6520106 | F17: 1 | G17: 280877 | H17: 1/18 | J17: PAGADO | L17: =+G17*F17 -> 280877 | M17: FALSE | N17: paga por upago
A18: 3289969 | B18: =VLOOKUP(A18,Export!A:N,14,0) -> 12285582 | C18: =VLOOKUP(A18,Export!A:P,16,0) -> GUILLERMO URBANO NEIRA ROA | D18: EXCEPCION PUT | E18: =VLOOKUP(A18,Export!A:D,4,0) -> 11183501 | G18: 8387626 | I18: 46230 | J18: PENDIENTE | L18: =+G18*F18 -> 0 | M18: FALSE
A19: 1530466 | B19: =VLOOKUP(A19,Export!A:N,14,0) -> 15741073 | C19: =VLOOKUP(A19,Export!A:P,16,0) -> YANIRA ANDREA CHELMES ARAYA | E19: =VLOOKUP(A19,Export!A:D,4,0) -> 4391250 | F19: 1 | G19: 3300000 | I19: 46211 | J19: PAGADO | L19: =+G19*F19 -> 3300000 | M19: FALSE
A20: 3136967 | B20: =VLOOKUP(A20,Export!A:N,14,0) -> 19914674 | C20: =VLOOKUP(A20,Export!A:P,16,0) -> MARIEL ANDREA GARCÍA GONZÁLEZ | D20: DACION | E20: =VLOOKUP(A20,Export!A:D,4,0) -> 4486091 | F20: 1 | G20: =+VLOOKUP(A20,'PLAN DE PAGO'!A:D,4,0) -> #N/A | J20: PENDIENTE | L20: =+G20*F20 -> #N/A | M20: FALSE
A21: 2751867 | B21: =VLOOKUP(A21,Export!A:N,14,0) -> 25588177 | C21: =VLOOKUP(A21,Export!A:P,16,0) -> BIANEY YOSELY RODRIGUEZ DELGADO | D21: INTENCION DE PAGO | E21: =VLOOKUP(A21,Export!A:D,4,0) -> 5982190 | G21: 400000 | J21: PENDIENTE | L21: =+G21*F21 -> 0 | M21: FALSE
B22: =VLOOKUP(A22,Export!A:N,14,0) -> #N/A | C22: =VLOOKUP(A22,Export!A:P,16,0) -> #N/A | E22: =VLOOKUP(A22,Export!A:D,4,0) -> #N/A | G22: =+VLOOKUP(A22,'PLAN DE PAGO'!A:D,4,0) -> #N/A | L22: =+G22*F22 -> #N/A | M22: FALSE
B23: =VLOOKUP(A23,Export!A:N,14,0) -> #N/A | C23: =VLOOKUP(A23,Export!A:P,16,0) -> #N/A | E23: =VLOOKUP(A23,Export!A:D,4,0) -> #N/A | G23: =+VLOOKUP(A23,'PLAN DE PAGO'!A:D,4,0) -> #N/A | L23: =+G23*F23 -> #N/A | M23: FALSE
B24: =VLOOKUP(A24,Export!A:N,14,0) -> #N/A | C24: =VLOOKUP(A24,Export!A:P,16,0) -> #N/A | E24: =VLOOKUP(A24,Export!A:D,4,0) -> #N/A | G24: =+VLOOKUP(A24,'PLAN DE PAGO'!A:D,4,0) -> #N/A | M24: FALSE
L25: =+G24*F24 -> #N/A
G26: =+SUM(G2:G18) -> 18697521
A27: META | B27: 33500000
A28: PAGADO | B28: =+SUMIF(J:J,"PAGADO",L:L) -> 4248572
A29: % | B29: =+B28/B27 -> 0.12682304
A32: 2013176 | B32: leila
A33: 3030656 | B33: volver a llamar
A34: 2184639 | B34: andrea, pidiendo credito para put
A35: 1645952
A36: 2310878
A37: 2361546 | B37: llamar todos los dias
A38: 3142604 | B38: posible pago, en espera de seguro
A39: 1891178 | B39: llamar todos los dias
A40: 2926004
A41: 1996495 | B41: francisco gaica, llamar el lunes 30
A42: 1479919 | B42: llamar el 13-07 contacto de Ely
A43: 1540238 | B43: guillermo andres bahamondes, se le ofrece plan de pago con 1500.000, dice que tiene 1.200.000 insistir
A44: 2926004 | B44: insistir
A45: 2577744 | B45: luis magallanes se envio oferta se envio oferta a tercero, insistir
A46: 1782538 | B46: insistir
A47: 2959119 | B47: cliente trabajado por ariel, volver a llamar el lunes 28
A48: 2246738
A49: 3111100 | B49: se envio oferta a tercero

Sheet TUBO CASTIGO 
A1: CREDITO | B1: RUT | C1: NOMBRE | D1: TRAMO | E1: SOLUCION | F1: CAPITAL | G1: VALOR DE PAGO | H1: CUOTA PAGADA | I1: FECHA COMPROMISO | J1: ESTADO | K1: FECHA PAGO | L1: RECUPERADO | M1: OBSERVACIONES | N1: EJECUTIVA | O1: audios | P1: Oficio | R1: RECUPERO | S1: META PH
A2: 2359330 | B2: =VLOOKUP(A2,Export!A:N,14,0) -> 14387173 | C2: =VLOOKUP(A2,Export!A:P,16,0) -> SOLEDAD DEL CARMEN ALFARO PINTO | D2: =VLOOKUP(A2,Export!A:H,8,0) -> 366-730 | E2: PLAN DE PAGO | F2: =VLOOKUP(A2,'[1]ORIGINAL '!D:M,5,0) -> 17079615 | G2: 294000 | H2: 6/48 | I2: 46147 | J2: PAGADO | L2: =SUMIF(J2,"PAGADO",G2) -> 294000 | M2: ingresado 05-05-2026 | O2: FALSE | P2: =VLOOKUP(A2,'[1]ORIGINAL '!D:I,6,0) -> #N/A
A3: 1923591 | B3: =VLOOKUP(A3,Export!A:N,14,0) -> 16647012 | C3: =VLOOKUP(A3,Export!A:P,16,0) -> FABRICIO ALEJANDRO VALENZUELA LEIVA | D3: =VLOOKUP(A3,Export!A:H,8,0) -> 0-365 | E3: PLAN DE PAGO | F3: =VLOOKUP(A3,'[1]ORIGINAL '!D:M,5,0) -> 11082144 | G3: 170895 | H3: 6 | I3: 46147 | J3: PAGADO | L3: =SUMIF(J3,"PAGADO",G3) -> 170895 | M3: pagado 05-05-2026 | O3: FALSE | P3: =VLOOKUP(A3,'[1]ORIGINAL '!D:I,6,0) -> #N/A
A4: 1987553 | B4: =VLOOKUP(A4,Export!A:N,14,0) -> 15242687 | C4: =VLOOKUP(A4,Export!A:P,16,0) -> GIORGIO GENNARO SARTORI TORRES | D4: =VLOOKUP(A4,Export!A:H,8,0) -> 366-730 | E4: PLAN DE PAGO | F4: =VLOOKUP(A4,'[1]ORIGINAL '!D:M,5,0) -> 10554087 | G4: 348087 | H4: 3/24 | I4: 46142 | J4: PAGADO | L4: =SUMIF(J4,"PAGADO",G4) -> 348087 | M4: paga | O4: FALSE | P4: =VLOOKUP(A4,'[1]ORIGINAL '!D:I,6,0) -> #N/A
A5: 1769156 | B5: =VLOOKUP(A5,Export!A:N,14,0) -> 7710884 | C5: =VLOOKUP(A5,Export!A:P,16,0) -> MARÍA ANGÉLICA VERGARA SILVA | D5: =VLOOKUP(A5,Export!A:H,8,0) -> 366-730 | E5: PLAN DE PAGO | F5: =VLOOKUP(A5,'[1]ORIGINAL '!D:M,5,0) -> 7241243 | G5: 197552 | H5: 8 | I5: 46127 | J5: PAGADO | L5: =SUMIF(J5,"PAGADO",G5) -> 197552 | O5: FALSE | P5: =VLOOKUP(A5,'[1]ORIGINAL '!D:I,6,0) -> #N/A
A6: 1700218 | B6: =VLOOKUP(A6,Export!A:N,14,0) -> 12218160 | C6: =VLOOKUP(A6,Export!A:P,16,0) -> JUAN ALEX OLIVARES ALANO | D6: =VLOOKUP(A6,Export!A:H,8,0) -> 0-365 | E6: NUEVO PLAN DE PAGO | F6: =VLOOKUP(A6,'[1]ORIGINAL '!D:M,5,0) -> 6879999 | G6: 1400000 | I6: 46157 | J6: PAGADO | L6: =SUMIF(J6,"PAGADO",G6) -> 1400000 | M6: pagado 05-05-2026 | O6: FALSE | P6: =VLOOKUP(A6,'[1]ORIGINAL '!D:I,6,0) -> #N/A
A7: 1735638 | B7: =VLOOKUP(A7,Export!A:N,14,0) -> 15656935 | C7: =VLOOKUP(A7,Export!A:P,16,0) -> RAMÓN ALONSO VÁSQUEZ BUSTOS | D7: =VLOOKUP(A7,Export!A:H,8,0) -> 0-365 | E7: NUEVO PLAN DE PAGO | F7: 1000000 | G7: =F7 -> 1000000 | H7: 1/5 | I7: 46149 | J7: Pendiente | L7: 1000000
A8: 2359330 | B8: =VLOOKUP(A8,Export!A:N,14,0) -> 14387173 | C8: =VLOOKUP(A8,Export!A:P,16,0) -> SOLEDAD DEL CARMEN ALFARO PINTO | D8: =VLOOKUP(A8,Export!A:H,8,0) -> 366-730 | E8: PLAN DE PAGO | F8: =VLOOKUP(A8,'[1]ORIGINAL '!D:M,5,0) -> 17079615 | G8: 457241 | H8: 7/48 | I8: 46171 | J8: pagado | K8: 46171 | L8: 457241
A9: 2410360 | B9: =VLOOKUP(A9,Export!A:N,14,0) -> 13291544 | C9: =VLOOKUP(A9,Export!A:P,16,0) -> ANDREA DEL PILAR GONZÁLEZ URETA | D9: =VLOOKUP(A9,Export!A:H,8,0) -> 0-365 | E9: PLAN DE PAGO | F9: =VLOOKUP(A9,'[1]ORIGINAL '!D:M,5,0) -> 5047680 | G9: 274744 | H9: 4/16 | I9: 46167 | J9: Pendiente | L9: 246730
A10: 1858227 | B10: =VLOOKUP(A10,Export!A:N,14,0) -> #N/A | C10: =VLOOKUP(A10,Export!A:P,16,0) -> #N/A | E10: pago total | F10: 6900000 | G10: 6900000 | I10: 46150 | J10: pagado | L10: 6900000
A11: 1769156 | B11: =VLOOKUP(A11,Export!A:N,14,0) -> 7710884 | C11: =VLOOKUP(A11,Export!A:P,16,0) -> MARÍA ANGÉLICA VERGARA SILVA | D11: =VLOOKUP(A11,Export!A:H,8,0) -> 366-730 | E11: PLAN DE PAGO | F11: =VLOOKUP(A11,'[1]ORIGINAL '!D:M,5,0) -> 7241243 | G11: 197552 | H11: 10 | I11: 46157 | J11: PAGADO | L11: =SUMIF(J11,"PAGADO",G11) -> 197552 | O11: FALSE | P11: =VLOOKUP(A11,'[1]ORIGINAL '!D:I,6,0) -> #N/A
A12: 1914398 | B12: =VLOOKUP(A12,Export!A:N,14,0) -> #N/A | C12: =VLOOKUP(A12,Export!A:P,16,0) -> #N/A | D12: =VLOOKUP(A12,Export!A:H,8,0) -> #N/A | E12: pago total | F12: =VLOOKUP(A12,'[1]ORIGINAL '!D:M,5,0) -> 7257716 | G12: 5443287 | H12: no llamar | J12: Pendiente | L12: 457241
A13: 3136967 | B13: =VLOOKUP(A13,Export!A:N,14,0) -> 19914674 | C13: =VLOOKUP(A13,Export!A:P,16,0) -> MARIEL ANDREA GARCÍA GONZÁLEZ | D13: =VLOOKUP(A13,Export!A:H,8,0) -> 0-365 | E13: NUEVO PLAN DE PAGO | F13: 1000000 | G13: =F13 -> 1000000 | H13: mensaje por ws | J13: Pendiente | L13: 457241
A14: 1638465 | B14: =VLOOKUP(A14,Export!A:N,14,0) -> 27070326 | C14: =VLOOKUP(A14,Export!A:P,16,0) -> LIBIA ROSA VERA TUBIÑEZ | D14: =VLOOKUP(A14,Export!A:H,8,0) -> 366-730 | E14: PLAN DE PAGO | F14: =VLOOKUP(A14,'[1]ORIGINAL '!D:M,5,0) -> 3871396 | G14: =F14 -> 3871396 | H14: mensaje por ws | J14: Pendiente | L14: 457241
A15: 2041907 | B15: =VLOOKUP(A15,Export!A:N,14,0) -> 12446328 | C15: =VLOOKUP(A15,Export!A:P,16,0) -> CLAUDIA LORENA ROJAS ARRIARÁN | D15: =VLOOKUP(A15,Export!A:H,8,0) -> 366-730 | E15: PLAN DE PAGO | F15: =VLOOKUP(A15,'[1]ORIGINAL '!D:M,5,0) -> 8500246 | G15: 202800 | H15: 7/36 | I15: 46171 | J15: Pendiente | L15: 457241
A16: 1791083 | B16: =VLOOKUP(A16,Export!A:N,14,0) -> 15236244 | C16: =VLOOKUP(A16,Export!A:P,16,0) -> RUBÉN ANER CARILAO BARRA | D16: =VLOOKUP(A16,Export!A:H,8,0) -> 366-730 | E16: PLAN DE PAGO | F16: =VLOOKUP(A16,'[1]ORIGINAL '!D:M,5,0) -> 7569433 | G16: =F16 -> 7569433 | H16: nc | J16: Pendiente | L16: 457241
A17: 1644932 | B17: =VLOOKUP(A17,Export!A:N,14,0) -> 16002296 | C17: =VLOOKUP(A17,Export!A:P,16,0) -> MIGUEL ANGEL ACEVEDO ARAVENA | D17: =VLOOKUP(A17,Export!A:H,8,0) -> 366-730 | E17: PLAN DE PAGO | F17: =VLOOKUP(A17,'[1]ORIGINAL '!D:M,5,0) -> 4868802 | G17: 148700 | H17: 2/24 | I17: 46171 | J17: Pendiente | K17: falta aplicar | L17: 457241
A18: 1700218 | B18: =VLOOKUP(A18,Export!A:N,14,0) -> 12218160 | C18: =VLOOKUP(A18,Export!A:P,16,0) -> JUAN ALEX OLIVARES ALANO | D18: =VLOOKUP(A18,Export!A:H,8,0) -> 0-365 | E18: PLAN DE PAGO | F18: =VLOOKUP(A18,'[1]ORIGINAL '!D:M,5,0) -> 6879999 | G18: 259734 | H18: 1/12 | I18: 46164 | J18: Pendiente | L18: 457241
A19: 1891178 | B19: =VLOOKUP(A19,Export!A:N,14,0) -> 26313552 | C19: =VLOOKUP(A19,Export!A:P,16,0) -> WILLIAMS JOSE CHACIN MARTINEZ | D19: =VLOOKUP(A19,Export!A:H,8,0) -> 0-365 | E19: PLAN DE PAGO | F19: =VLOOKUP(A19,'[1]ORIGINAL '!D:M,5,0) -> 6382600 | G19: =F19 -> 6382600 | H19: mensaje por ws | J19: Pendiente | L19: 457241
A20: 1923591 | B20: =VLOOKUP(A20,Export!A:N,14,0) -> 16647012 | C20: =VLOOKUP(A20,Export!A:P,16,0) -> FABRICIO ALEJANDRO VALENZUELA LEIVA | D20: =VLOOKUP(A20,Export!A:H,8,0) -> 0-365 | E20: PLAN DE PAGO | F20: =VLOOKUP(A20,'[1]ORIGINAL '!D:M,5,0) -> 11082144 | G20: =F20 -> 11082144 | H20: 8/ | J20: PAGADO | L20: 457241
A21: 2221834 | B21: =VLOOKUP(A21,Export!A:N,14,0) -> 26793032 | C21: =VLOOKUP(A21,Export!A:P,16,0) -> CARLOS ALBERTO GIANNOTTY MORENO | D21: =VLOOKUP(A21,Export!A:H,8,0) -> 366-730 | E21: PLAN DE PAGO | F21: =VLOOKUP(A21,'[1]ORIGINAL '!D:M,5,0) -> 3892558 | G21: =F21 -> 3892558 | H21: mensaje por ws | J21: Pendiente | L21: 457241
A22: 1987553 | B22: =VLOOKUP(A22,Export!A:N,14,0) -> 15242687 | C22: =VLOOKUP(A22,Export!A:P,16,0) -> GIORGIO GENNARO SARTORI TORRES | D22: =VLOOKUP(A22,Export!A:H,8,0) -> 366-730 | E22: PLAN DE PAGO | F22: =VLOOKUP(A22,'[1]ORIGINAL '!D:M,5,0) -> 10554087 | G22: 348087 | H22: 9/24 | I22: 46171 | J22: Pendiente | L22: 457241
A23: 3115557 | B23: =VLOOKUP(A23,Export!A:N,14,0) -> 18488596 | C23: =VLOOKUP(A23,Export!A:P,16,0) -> ELENA ROMANE VIDAL GOMEZ | D23: =VLOOKUP(A23,Export!A:H,8,0) -> 0-365 | E23: PLAN DE PAGO | F23: =VLOOKUP(A23,'[1]ORIGINAL '!D:M,5,0) -> 10316441 | G23: =F23 -> 10316441 | H23: mensaje por ws | J23: Pendiente | L23: 457241
A24: 3120521 | B24: =VLOOKUP(A24,Export!A:N,14,0) -> 6332455 | C24: =VLOOKUP(A24,Export!A:P,16,0) -> ELSA MARCIA DIAZ MORA | D24: =VLOOKUP(A24,Export!A:H,8,0) -> 0-365 | F24: =VLOOKUP(A24,'[1]ORIGINAL '!D:M,5,0) -> 15352634 | G24: =F24 -> 15352634 | H24: nc | J24: Pendiente | L24: 457241
A25: 3142604 | B25: =VLOOKUP(A25,Export!A:N,14,0) -> 18455951 | C25: =VLOOKUP(A25,Export!A:P,16,0) -> BASTIÁN ALEXIS LARA MANRÍQUEZ | D25: =VLOOKUP(A25,Export!A:H,8,0) -> 0-365 | F25: =VLOOKUP(A25,'[1]ORIGINAL '!D:M,5,0) -> 8487006 | G25: =F25 -> 8487006 | H25: no llamar | J25: Pendiente | L25: 457241
A26: 3136967 | B26: =VLOOKUP(A26,Export!A:N,14,0) -> 19914674 | C26: =VLOOKUP(A26,Export!A:P,16,0) -> MARIEL ANDREA GARCÍA GONZÁLEZ | D26: =VLOOKUP(A26,Export!A:H,8,0) -> 0-365 | F26: =VLOOKUP(A26,'[1]ORIGINAL '!D:M,5,0) -> 4486091 | G26: =F26 -> 4486091 | J26: Pendiente | L26: 457241
A27: 2398643 | B27: =VLOOKUP(A27,Export!A:N,14,0) -> #N/A | C27: =VLOOKUP(A27,Export!A:P,16,0) -> #N/A | D27: =VLOOKUP(A27,Export!A:H,8,0) -> #N/A | F27: =VLOOKUP(A27,'[1]ORIGINAL '!D:M,5,0) -> 4285479 | G27: 2785561 | I27: 46171 | J27: Pendiente | L27: 457241
A28: 2959119 | B28: =VLOOKUP(A28,Export!A:N,14,0) -> 19898341 | C28: =VLOOKUP(A28,Export!A:P,16,0) -> CHRISTOPHER ROMMEL SANTOS ANCO | D28: =VLOOKUP(A28,Export!A:H,8,0) -> 0-365 | E28: PUT EN PARTES | F28: =VLOOKUP(A28,'[1]ORIGINAL '!D:M,5,0) -> 6731141 | G28: 2524178 | J28: Pendiente | L28: 457241
A29: 2757617 | B29: =VLOOKUP(A29,Export!A:N,14,0) -> 10908669 | C29: =VLOOKUP(A29,Export!A:P,16,0) -> OSCAR RICARDO ROMERO GONZÁLEZ | D29: =VLOOKUP(A29,Export!A:H,8,0) -> 0-365 | E29: PLAN DE PAGO | F29: =VLOOKUP(A29,'[1]ORIGINAL '!D:M,5,0) -> 9115829 | G29: 1500000 | I29: 46172 | J29: Pendiente | L29: 457241

Sheet PLAN DE PAGO
A1: ID | B1: DEUDA INICIAL | C1: PIE | D1: CUOTA | E1: N° DE CUOTA | F1: CUOTAS PAGADAS A ABRIL
A2: 1769156 | B2: =+VLOOKUP(A2,Export!A:D,4,0) -> 7241243 | C2: 2500000 | D2: 197552 | E2: 23.999975 | F2: 11 | G2: =+VLOOKUP(A2,Export!A:P,16,0) -> MARÍA ANGÉLICA VERGARA SILVA
A3: 1923591 | B3: =+VLOOKUP(A3,Export!A:D,4,0) -> 11082144 | C3: 2000000 | D3: 170895 | E3: 53.144586 | F3: 9 | G3: =+VLOOKUP(A3,Export!A:P,16,0) -> FABRICIO ALEJANDRO VALENZUELA LEIVA
A4: 1638465 | B4: =+VLOOKUP(A4,Export!A:D,4,0) -> 3871396 | C4: 775000 | D4: 172022 | E4: 18 | F4: 8 | G4: =+VLOOKUP(A4,Export!A:P,16,0) -> LIBIA ROSA VERA TUBIÑEZ
A5: 2359330 | B5: =+VLOOKUP(A5,Export!A:D,4,0) -> 17079615 | C5: 3000000 | D5: 294000 | E5: 47.889847 | F5: 9 | G5: =+VLOOKUP(A5,Export!A:P,16,0) -> SOLEDAD DEL CARMEN ALFARO PINTO
A6: 2410360 | B6: =+VLOOKUP(A6,Export!A:D,4,0) -> 5047680 | C6: 1100000 | D6: 246730 | E6: 16 | F6: 6 | G6: =+VLOOKUP(A6,Export!A:P,16,0) -> ANDREA DEL PILAR GONZÁLEZ URETA
A7: 2041907 | B7: =+VLOOKUP(A7,Export!A:D,4,0) -> 8500246 | C7: 1200000 | D7: 202800 | E7: 35.997268 | F7: 6 | G7: =+VLOOKUP(A7,Export!A:P,16,0) -> CLAUDIA LORENA ROJAS ARRIARÁN
A8: 1987553 | B8: =+VLOOKUP(A8,Export!A:D,4,0) -> 10554087 | C8: 2200000 | D8: 348087 | E8: 23.999997 | F8: 6 | G8: =+VLOOKUP(A8,Export!A:P,16,0) -> GIORGIO GENNARO SARTORI TORRES | H8: 30- | I8: upago
A9: 1791083 | B9: =+VLOOKUP(A9,Export!A:D,4,0) -> 7569433 | C9: 1000000 | D9: 273726 | E9: 24.000033 | F9: 3 | G9: =+VLOOKUP(A9,Export!A:P,16,0) -> RUBÉN ANER CARILAO BARRA | H9: 46174
A10: 1644932 | B10: =+VLOOKUP(A10,Export!A:D,4,0) -> 4868802 | C10: 1300000 | D10: 148700 | E10: 24.000013 | F10: 3 | G10: =+VLOOKUP(A10,Export!A:P,16,0) -> MIGUEL ANGEL ACEVEDO ARAVENA | H10: 46203
A11: 2642200 | B11: =+VLOOKUP(A11,Export!A:D,4,0) -> 6213630 | C11: 2000000 | D11: 351136 | E11: 11.999994 | F11: 1 | G11: =+VLOOKUP(A11,Export!A:P,16,0) -> JUAN CLAUDIO SILVA BURDILES | H11: 30 | I11: upago
A12: 1700218 | B12: =+VLOOKUP(A12,Export!A:D,4,0) -> 6879999 | C12: 1400000 | D12: 259734 | E12: 11.999994 | F12: 0 | G12: =+VLOOKUP(A12,Export!A:P,16,0) -> JUAN ALEX OLIVARES ALANO
A13: 1966918 | B13: =+VLOOKUP(A13,Export!A:D,4,0) -> 6520106 | D13: 280877 | E13: 18 | G13: =+VLOOKUP(A13,Export!A:P,16,0) -> CRISTIAN ALBERTO REYES INZUNZA

Sheet TUBO CASTIGO JUNIO MARY
A1: CREDITO | B1: RUT | C1: NOMBRE | D1: TRAMO | E1: SOLUCION | F1: CAPITAL | G1: VALOR DE PAGO | H1: CUOTA PAGADA | I1: FECHA COMPROMISO | J1: ESTADO | K1: FECHA PAGO | L1: RECUPERADO | M1: OBSERVACIONES | N1: EJECUTIVA | O1: audios | P1: Oficio | R1: RECUPERO | S1: META PH
A2: 1638465 | B2: =VLOOKUP(A2,Export!A:N,14,0) -> 27070326 | C2: =VLOOKUP(A2,Export!A:P,16,0) -> LIBIA ROSA VERA TUBIÑEZ | D2: =VLOOKUP(A2,Export!A:H,8,0) -> 366-730 | E2: PLAN DE PAGO | F2: =VLOOKUP(A2,'[1]ORIGINAL '!D:M,5,0) -> 3871396 | G2: 172022 | H2: 8/18 | J2: pagado | L2: 457241
A3: 2041907 | B3: =VLOOKUP(A3,Export!A:N,14,0) -> 12446328 | C3: =VLOOKUP(A3,Export!A:P,16,0) -> CLAUDIA LORENA ROJAS ARRIARÁN | D3: =VLOOKUP(A3,Export!A:H,8,0) -> 366-730 | E3: PLAN DE PAGO | F3: =VLOOKUP(A3,'[1]ORIGINAL '!D:M,5,0) -> 8500246 | G3: 202800 | H3: 6/36 | J3: pagado | L3: 457241
A4: 1791083 | B4: =VLOOKUP(A4,Export!A:N,14,0) -> 15236244 | C4: =VLOOKUP(A4,Export!A:P,16,0) -> RUBÉN ANER CARILAO BARRA | D4: =VLOOKUP(A4,Export!A:H,8,0) -> 366-730 | E4: PLAN DE PAGO | F4: =VLOOKUP(A4,'[1]ORIGINAL '!D:M,5,0) -> 7569433 | G4: 273726 | H4: 3/24 | I4: 46174 | J4: pagado | L4: 457241
A5: 1644932 | B5: =VLOOKUP(A5,Export!A:N,14,0) -> 16002296 | C5: =VLOOKUP(A5,Export!A:P,16,0) -> MIGUEL ANGEL ACEVEDO ARAVENA | D5: =VLOOKUP(A5,Export!A:H,8,0) -> 366-730 | E5: PLAN DE PAGO | F5: =VLOOKUP(A5,'[1]ORIGINAL '!D:M,5,0) -> 4868802 | G5: 148700 | H5: 3/24 | J5: pagado | L5: 457241
A6: 2359330 | B6: =VLOOKUP(A6,Export!A:N,14,0) -> 14387173 | C6: =VLOOKUP(A6,Export!A:P,16,0) -> SOLEDAD DEL CARMEN ALFARO PINTO | D6: =VLOOKUP(A6,Export!A:H,8,0) -> 366-730 | E6: PLAN DE PAGO | F6: =VLOOKUP(A6,'[1]ORIGINAL '!D:M,5,0) -> 17079615 | G6: 294000 | H6: 10/48 | I6: 46202 | J6: pagado | K6: 24-06 | L6: 457241 | M6: p fines de mes
A7: 1923591 | B7: =VLOOKUP(A7,Export!A:N,14,0) -> 16647012 | C7: =VLOOKUP(A7,Export!A:P,16,0) -> FABRICIO ALEJANDRO VALENZUELA LEIVA | D7: =VLOOKUP(A7,Export!A:H,8,0) -> 0-365 | E7: PLAN DE PAGO | F7: =VLOOKUP(A7,'[1]ORIGINAL '!D:M,5,0) -> 11082144 | G7: 170000 | H7: 8/53 | I7: 3/6/2026 PAGAHOY | J7: pagado | L7: 457241 | M7: paga los 5 pr dias
A8: 1987553 | B8: =VLOOKUP(A8,Export!A:N,14,0) -> 15242687 | C8: =VLOOKUP(A8,Export!A:P,16,0) -> GIORGIO GENNARO SARTORI TORRES | D8: =VLOOKUP(A8,Export!A:H,8,0) -> 366-730 | E8: PLAN DE PAGO | F8: =VLOOKUP(A8,'[1]ORIGINAL '!D:M,5,0) -> 10554087 | G8: 348087 | H8: 9/24 | I8: 46203 | J8: pagado | K8: 24-06 | L8: 457241 | M8: p fines de mes
A9: 1769156 | B9: =VLOOKUP(A9,Export!A:N,14,0) -> 7710884 | C9: =VLOOKUP(A9,Export!A:P,16,0) -> MARÍA ANGÉLICA VERGARA SILVA | D9: =VLOOKUP(A9,Export!A:H,8,0) -> 366-730 | E9: PLAN DE PAGO | F9: =VLOOKUP(A9,'[1]ORIGINAL '!D:M,5,0) -> 7241243 | G9: 197552 | H9: 11/24 | I9: 46188 | J9: pagado | L9: 457241 | M9: rut de quien transfier 13334301-6
A10: 2410360 | B10: =VLOOKUP(A10,Export!A:N,14,0) -> 13291544 | C10: =VLOOKUP(A10,Export!A:P,16,0) -> ANDREA DEL PILAR GONZÁLEZ URETA | D10: =VLOOKUP(A10,Export!A:H,8,0) -> 0-365 | E10: PLAN DE PAGO | F10: =VLOOKUP(A10,'[1]ORIGINAL '!D:M,5,0) -> 5047680 | G10: 246730 | H10: 4/16 | I10: 46028 | J10: pagado | L10: 457241 | M10: subido
A11: 2041907 | B11: =VLOOKUP(A11,Export!A:N,14,0) -> 12446328 | C11: =VLOOKUP(A11,Export!A:P,16,0) -> CLAUDIA LORENA ROJAS ARRIARÁN | D11: =VLOOKUP(A11,Export!A:H,8,0) -> 366-730 | E11: PLAN DE PAGO | F11: =VLOOKUP(A11,'[1]ORIGINAL '!D:M,5,0) -> 8500246 | G11: 202800 | H11: 7/36 | I11: 46203 | J11: Pendiente | K11: 24-06 | L11: 457241 | M11: p fines de mes
A12: 1700218 | B12: =VLOOKUP(A12,Export!A:N,14,0) -> 12218160 | C12: =VLOOKUP(A12,Export!A:P,16,0) -> JUAN ALEX OLIVARES ALANO | D12: =VLOOKUP(A12,Export!A:H,8,0) -> 0-365 | E12: PLAN DE PAGO | F12: =VLOOKUP(A12,'[1]ORIGINAL '!D:M,5,0) -> 6879999 | G12: 259734 | H12: 1/12 | I12: 46195 | J12: Pendiente | L12: 457241
A13: 1966918 | B13: =VLOOKUP(A13,Export!A:N,14,0) -> 15167058 | C13: =VLOOKUP(A13,Export!A:P,16,0) -> CRISTIAN ALBERTO REYES INZUNZA | D13: =VLOOKUP(A13,Export!A:H,8,0) -> 0-365 | E13: nuevo plan de pago | F13: =VLOOKUP(A13,'[1]ORIGINAL '!D:M,5,0) -> 5463159 | G13: 1500000 | H13: 0/18 | I13: 46192 | J13: pagado | K13: 46180 | L13: 457241
A14: 2642200 | B14: =VLOOKUP(A14,Export!A:N,14,0) -> 19972407 | C14: =VLOOKUP(A14,Export!A:P,16,0) -> JUAN CLAUDIO SILVA BURDILES | D14: =VLOOKUP(A14,Export!A:H,8,0) -> 0-365 | E14: PLAN DE PAGO | F14: =VLOOKUP(A14,'[1]ORIGINAL '!D:M,5,0) -> 6213630 | G14: 351136 | H14: 1/13 | I14: 30-05-2026 | J14: pagado | L14: 457241
A15: 2642200 | B15: =VLOOKUP(A15,Export!A:N,14,0) -> 19972407 | C15: =VLOOKUP(A15,Export!A:P,16,0) -> JUAN CLAUDIO SILVA BURDILES | D15: =VLOOKUP(A15,Export!A:H,8,0) -> 0-365 | E15: PLAN DE PAGO | F15: =VLOOKUP(A15,'[1]ORIGINAL '!D:M,5,0) -> 6213630 | G15: 351136 | H15: 2/13 | I15: 46202 | J15: Pendiente | L15: 457241 | M15: fines de mes
A16: 1874171 | B16: =VLOOKUP(A16,Export!A:N,14,0) -> #N/A | C16: =VLOOKUP(A16,Export!A:P,16,0) -> #N/A | D16: =VLOOKUP(A16,Export!A:H,8,0) -> #N/A | E16: put pendiente viendo un seguro llamar la proxima semana | F16: =VLOOKUP(A16,'[1]ORIGINAL '!D:M,5,0) -> 4865566 | G16: 3732000 | I16: 8/062026 | J16: pagado | K16: abonado dos millones | L16: 457241 | M16: abonos realizados 2.000000
A17: 1867567 | B17: =VLOOKUP(A17,Export!A:N,14,0) -> #N/A | C17: =VLOOKUP(A17,Export!A:P,16,0) -> #N/A | D17: =VLOOKUP(A17,Export!A:H,8,0) -> #N/A | E17: put | F17: =VLOOKUP(A17,'[1]ORIGINAL '!D:M,5,0) -> 4685635 | G17: 4500000 | J17: pagado | L17: 457241
A18: 2984397 | B18: =VLOOKUP(A18,Export!A:N,14,0) -> #N/A | C18: =VLOOKUP(A18,Export!A:P,16,0) -> #N/A | D18: =VLOOKUP(A18,Export!A:H,8,0) -> #N/A | E18: DACION POST INCAUTACION | F18: =VLOOKUP(A18,'[1]ORIGINAL '!D:M,5,0) -> 7543017 | G18: 7543017 | J18: PAGADO | L18: 457241
A19: 1873778 | B19: =VLOOKUP(A19,Export!A:N,14,0) -> #N/A | C19: =VLOOKUP(A19,Export!A:P,16,0) -> #N/A | D19: =VLOOKUP(A19,Export!A:H,8,0) -> #N/A | E19: dacion pura | F19: 4070817 | G19: 4070817 | H19: 4 | J19: PAGADO | L19: 457241
A20: 2242697 | B20: =VLOOKUP(A20,Export!A:N,14,0) -> 76478759 | C20: =VLOOKUP(A20,Export!A:P,16,0) -> SOLUCIONES DE INGENIERÍA CESAR CESPEDES SPA | D20: =VLOOKUP(A20,Export!A:H,8,0) -> 0-365 | E20: pun en 4 partes | F20: =VLOOKUP(A20,'[1]ORIGINAL '!D:M,5,0) -> 12103197 | G20: 2.723.220 | I20: 46192 | J20: pagado | L20: 457241
A21: 1638465 | B21: =VLOOKUP(A21,Export!A:N,14,0) -> 27070326 | C21: =VLOOKUP(A21,Export!A:P,16,0) -> LIBIA ROSA VERA TUBIÑEZ | D21: =VLOOKUP(A21,Export!A:H,8,0) -> 366-730 | E21: PLAN DE PAGO | F21: =VLOOKUP(A21,'[1]ORIGINAL '!D:M,5,0) -> 3871396 | G21: 177022 | H21: 9/18 | I21: 46203 | J21: Pendiente | L21: 457241
A22: 1644932 | B22: =VLOOKUP(A22,Export!A:N,14,0) -> 16002296 | C22: =VLOOKUP(A22,Export!A:P,16,0) -> MIGUEL ANGEL ACEVEDO ARAVENA | D22: =VLOOKUP(A22,Export!A:H,8,0) -> 366-730 | E22: PLAN DE PAGO | F22: =VLOOKUP(A22,'[1]ORIGINAL '!D:M,5,0) -> 4868802 | G22: 148700 | H22: 4/24 | I22: 46199 | J22: pagado | L22: 457241
A23: 3115557 | B23: =VLOOKUP(A23,Export!A:N,14,0) -> 18488596 | C23: =VLOOKUP(A23,Export!A:P,16,0) -> ELENA ROMANE VIDAL GOMEZ | D23: =VLOOKUP(A23,Export!A:H,8,0) -> 0-365 | E23: plan de pago | F23: =VLOOKUP(A23,'[1]ORIGINAL '!D:M,5,0) -> 10316441 | G23: 260548 | H23: 1/30 | J23: Pendiente | L23: 457241
A24: 1791083 | B24: =VLOOKUP(A24,Export!A:N,14,0) -> 15236244 | C24: =VLOOKUP(A24,Export!A:P,16,0) -> RUBÉN ANER CARILAO BARRA | D24: =VLOOKUP(A24,Export!A:H,8,0) -> 366-730 | F24: =VLOOKUP(A24,'[1]ORIGINAL '!D:M,5,0) -> 7569433 | G24: 273726 | H24: 4/24 | J24: pagado | L24: 457241
B25: =VLOOKUP(A25,Export!A:N,14,0) -> #N/A | C25: =VLOOKUP(A25,Export!A:P,16,0) -> #N/A | D25: =VLOOKUP(A25,Export!A:H,8,0) -> #N/A | F25: =VLOOKUP(A25,'[1]ORIGINAL '!D:M,5,0) -> #N/A | J25: Pendiente | L25: 457241
E30: |
A31: posibles pagos
A32: 1645952 | B32: =VLOOKUP(A32,Export!A:N,14,0) -> 15189992 | C32: =VLOOKUP(A32,Export!A:P,16,0) -> ERIK MARCELO ABURTO MORAGA | D32: =VLOOKUP(A32,Export!A:H,8,0) -> 0-365 | E32: plan de pago | F32: =VLOOKUP(A32,'[1]ORIGINAL '!D:M,5,0) -> 7872938 | H32: 172022 | J32: Pendiente | L32: 457241
A33: 2310878 | B33: =VLOOKUP(A33,Export!A:N,14,0) -> 16782801 | C33: =VLOOKUP(A33,Export!A:P,16,0) -> PATRICIO ESTEBAN GUTIÉRREZ VALENZUELA | D33: =VLOOKUP(A33,Export!A:H,8,0) -> 0-365 | F33: =VLOOKUP(A33,'[1]ORIGINAL '!D:M,5,0) -> 10088187 | H33: 202800 | J33: Pendiente | L33: 457241
A34: 2361546 | B34: =VLOOKUP(A34,Export!A:N,14,0) -> 18845546 | C34: =VLOOKUP(A34,Export!A:P,16,0) -> PAULETTE CRISTINA PEÑA JARA | D34: =VLOOKUP(A34,Export!A:H,8,0) -> 0-365 | F34: =VLOOKUP(A34,'[1]ORIGINAL '!D:M,5,0) -> 5966279 | H34: 148700 | J34: Pendiente | L34: 457241
A35: 3142604 | B35: =VLOOKUP(A35,Export!A:N,14,0) -> 18455951 | C35: =VLOOKUP(A35,Export!A:P,16,0) -> BASTIÁN ALEXIS LARA MANRÍQUEZ | D35: =VLOOKUP(A35,Export!A:H,8,0) -> 0-365 | F35: =VLOOKUP(A35,'[1]ORIGINAL '!D:M,5,0) -> 8487006 | H35: 170000 | J35: Pendiente | L35: 457241
A36: 1891178 | B36: =VLOOKUP(A36,Export!A:N,14,0) -> 26313552 | C36: =VLOOKUP(A36,Export!A:P,16,0) -> WILLIAMS JOSE CHACIN MARTINEZ | D36: =VLOOKUP(A36,Export!A:H,8,0) -> 0-365 | F36: =VLOOKUP(A36,'[1]ORIGINAL '!D:M,5,0) -> 6382600 | H36: 197552 | J36: Pendiente | L36: 457241
B37: =VLOOKUP(A37,Export!A:N,14,0) -> #N/A | C37: =VLOOKUP(A37,Export!A:P,16,0) -> #N/A | D37: =VLOOKUP(A37,Export!A:H,8,0) -> #N/A | F37: =VLOOKUP(A37,'[1]ORIGINAL '!D:M,5,0) -> #N/A | H37: 246730 | J37: Pendiente | L37: 457241
B38: =VLOOKUP(A38,Export!A:N,14,0) -> #N/A | C38: =VLOOKUP(A38,Export!A:P,16,0) -> #N/A | D38: =VLOOKUP(A38,Export!A:H,8,0) -> #N/A | F38: =VLOOKUP(A38,'[1]ORIGINAL '!D:M,5,0) -> #N/A | H38: 1500000 | J38: Pendiente | L38: 457241
B39: =VLOOKUP(A39,Export!A:N,14,0) -> #N/A | C39: =VLOOKUP(A39,Export!A:P,16,0) -> #N/A | D39: =VLOOKUP(A39,Export!A:H,8,0) -> #N/A | F39: =VLOOKUP(A39,'[1]ORIGINAL '!D:M,5,0) -> #N/A | H39: 351136 | J39: Pendiente | L39: 457241
B40: =VLOOKUP(A40,Export!A:N,14,0) -> #N/A | C40: =VLOOKUP(A40,Export!A:P,16,0) -> #N/A | D40: =VLOOKUP(A40,Export!A:H,8,0) -> #N/A | F40: =VLOOKUP(A40,'[1]ORIGINAL '!D:M,5,0) -> #N/A | H40: 3732000 | J40: Pendiente | L40: 457241
B41: =VLOOKUP(A41,Export!A:N,14,0) -> #N/A | C41: =VLOOKUP(A41,Export!A:P,16,0) -> #N/A | D41: =VLOOKUP(A41,Export!A:H,8,0) -> #N/A | F41: =VLOOKUP(A41,'[1]ORIGINAL '!D:M,5,0) -> #N/A | H41: 4500000 | J41: Pendiente | L41: 457241
B42: =VLOOKUP(A42,Export!A:N,14,0) -> #N/A | C42: =VLOOKUP(A42,Export!A:P,16,0) -> #N/A | D42: =VLOOKUP(A42,Export!A:H,8,0) -> #N/A | F42: =VLOOKUP(A42,'[1]ORIGINAL '!D:M,5,0) -> #N/A | H42: 7543017 | J42: Pendiente | L42: 457241
B43: =VLOOKUP(A43,Export!A:N,14,0) -> #N/A | C43: =VLOOKUP(A43,Export!A:P,16,0) -> #N/A | D43: =VLOOKUP(A43,Export!A:H,8,0) -> #N/A | F43: =VLOOKUP(A43,'[1]ORIGINAL '!D:M,5,0) -> #N/A | H43: 4070817 | J43: Pendiente | L43: 457241
H44: 2.723.220
H45: 148700
H46: 4151673
H47: 348087
H48: 294000
H49: 177022
H50: 202800
H51: 259734
H53: 177022
H54: 260548
H56: =SUM(H32:H55) -> 28854360

Sheet OFICIO 
A1: OP | B1: RUT | C1: NOMBRE | D1: ROL | E1: JUZGADO | F1: MANDAMIENTO | G1: PATENTE | H1: DIRECCION | I1: COMUNA | J1: fecha oficio | K1: resultado | L1: TRAMO
A2: 1791083 | B2: 15236244-7 | C2: RUBÉN ANER CARILAO BARRA | D2: 16644-2024 | E2: 16º Juzgado Civil de Santiago | F2: 6234785 | G2: RTFH.40-5 | H2: LA HUASCA N°10834 | I2: LA FLORIDA | J2: 45667 | L2: =+VLOOKUP(A2,'[1]ORIGINAL '!D:N,11,0) -> CASTIGO
A3: 2960003 | B3: 13492280-K | C3: CLAUDIO ANDRÉS TAPIA QUEZADA | D3: 16655-2024 | E3: 3 JZDO CIVIL STGO | F3: 19119523 | G3: TKDC.78-7 | H3: Los Comandos 5040, comuna de PEDRO AGUIRRE CERDA | I3: PEDRO AGUIRRE CERDA | J3: 45742 | L3: =+VLOOKUP(A3,'[1]ORIGINAL '!D:N,11,0) -> CASTIGO
A4: 2501797 | B4: 10709514-4 | C4: MANUEL JESÚS VERGARA IBACACHE | D4: C-19075-2024 | E4: 15º Juzgado Civil de Santiago | F4: 5491364 | G4: SFPH.48-2 | H4: EL PARRON 1751 DPTO 2, comuna de SAN RAMON | I4: SAN RAMON | J4: 45743 | L4: =+VLOOKUP(A4,'[1]ORIGINAL '!D:N,11,0) -> CASTIGO
A5: 2297687 | B5: 15929792-6 | C5: XAVIER ALEJANDRO LAVÍN VÁSQUEZ | D5: C-19071-2024 | E5: 22º Juzgado Civil de Santiago | F5: 8822876 | G5: KKWD.17-2 | H5: LOS TALLADORES 10407, comuna de La Florida | I5: LA FLORIDA | J5: 45744 | L5: =+VLOOKUP(A5,'[1]ORIGINAL '!D:N,11,0) -> CASTIGO
A6: 1609884 | B6: 26440312-K | C6: Leonardo Javier Vallera Reyes | D6: C-19071-2024 | E6: 8º Juzgado Civil de Santiago | F6: 6217251 | G6: RLGC.76-9 | H6: HIPODROMO 1310 DEPTO 608, comuna de Independencia | I6: INDEPENDENCIA | J6: 45749 | K6: SUSPENDIDO | L6: =+VLOOKUP(A6,'[1]ORIGINAL '!D:N,11,0) -> #N/A
A7: 1344919 | B7: 16746764-4 | C7: GERALDINE KAROL VIVAR ARGOMEDO | D7: C-19084-2024 | E7: 19º Juzgado Civil de Santiago | F7: 6704919 | G7: PTSS.82-9 | H7: DECIMA AVENIDA 1430, comuna de SAN MIGUEL | I7: SAN MIGUEL | J7: 45758 | L7: =+VLOOKUP(A7,'[1]ORIGINAL '!D:N,11,0) -> CASTIGO
A8: 2554756 | B8: 10709514-4 | C8: MANUEL JESUS VERGARA IBACACHE | D8: C-19073-2024 | E8: 8º Juzgado Civil de Santiago | F8: 16075166 | G8: FHZP.90-7 | H8: LO OVALLE N°240, comuna de Quilicura | I8: QUILICURA | J8: 45769 | L8: =+VLOOKUP(A8,'[1]ORIGINAL '!D:N,11,0) -> CASTIGO
A9: 1477948 | B9: 13910860-4 | C9: SUSANA VALESKA ARIAS GAETE | D9: C-19076-2024 | E9: 20º Juzgado Civil de Santiago | F9: 6211566 | G9: RBCR.34-0 | H9: PAMPA N° 6234, comuna de Renca | I9: RENCA | J9: 45779 | L9: =+VLOOKUP(A9,'[1]ORIGINAL '!D:N,11,0) -> VIGENTE
A10: 2501085 | B10: 14249393-4 | C10: INGRID MERCEDES GALAZ GUTIÉRREZ | D10: C-20316-2024 | E10: 11º Juzgado Civil de Santiago | F10: 7769536 | G10: SWSF.83-3 | H10: GRAJALES 2154, comuna de Santiago | I10: SANTIAGO | J10: 45782 | L10: =+VLOOKUP(A10,'[1]ORIGINAL '!D:N,11,0) -> VIGENTE
A11: 1811663 | B11: 26030033-4 | C11: ANDRE TERTULIEN | D11: C-22134-2024 | E11: 1º Juzgado Civil de Santiago | F11: 6976272 | G11: RVDH.69-2 | H11: CALLE TRES MONTE 714 DPTO 306, comuna de Quilicura | I11: QUILICURA | J11: 45810 | L11: =+VLOOKUP(A11,'[1]ORIGINAL '!D:N,11,0) -> CASTIGO
A12: 2012591 | B12: 18046771-8 | C12: JONATHAN EDUARDO ARAVENA SÁNCHEZ | D12: C-20318-2024 | E12: 13º Juzgado Civil de Santiago | F12: 8668490 | G12: RZSP.98-6 | H12: LUIS MATTE LARRAIN 1485, comuna de PUENTE ALTO | I12: PUENTE ALTO | J12: 45812 | K12: INCAUTADO | L12: =+VLOOKUP(A12,'[1]ORIGINAL '!D:N,11,0) -> #N/A
A13: 2329701 | B13: 77259568-9 | C13: PIEDRA AZUL SPA | D13: C-15705-2024 | E13: 5º Juzgado Civil de Santiago | F13: 5931892 | G13: GXTK.70-4 | H13: Santa Aída N° 21, comuna de COLINA | I13: COLINA | J13: 45812 | K13: PAGO | L13: =+VLOOKUP(A13,'[1]ORIGINAL '!D:N,11,0) -> #N/A
A14: 3001478 | B14: 17307356-9 | C14: JONATHAN GERSON CORTES BURGOS | D14: c-20317-2024 | E14: 5° Juzgado Civil de Santiago | F14: 4774537 | G14: PPTY.75-5 | H14: Pasaje Los Yales 508, comuna de Pudahuel | I14: PUDAHUEL | J14: 45776 | K14: INCAUTADO | L14: =+VLOOKUP(A14,'[1]ORIGINAL '!D:N,11,0) -> #N/A
A15: 3111100 | B15: 17069258-6 | C15: Tamara Scarlet Soto Vallejos | D15: C-778-2025 | E15: 3º Juzgado Civil de Santiago | F15: 13162113 | G15: TRYG.76-K | H15: AVENIDA JOSE MANUEL BALMACEDA N° 5169, renca | I15: RENCA | J15: 45818 | L15: =+VLOOKUP(A15,'[1]ORIGINAL '!D:N,11,0) -> CASTIGO
A16: 2126564 | B16: 13489611-6 | C16: ELIZABETH DEL CARMEN ARENAS ORELLANA | D16: C-683-2025 | E16: 10º Juzgado Civil de Santiago | F16: 7403628 | G16: KXTC.55-3 | H16: ALMIRANTE LATORRE 0367, comuna de PUENTE ALTO | I16: PUENTE ALTO | J16: 45831 | L16: =+VLOOKUP(A16,'[1]ORIGINAL '!D:N,11,0) -> CASTIGO
A17: 1721051 | B17: 16409957-1 | C17: ROBERTO CARLOS NEER CERDA | D17: C-22132-2024 | E17: 25º Juzgado Civil de Santiago | F17: 8170959 | G17: RRRF.12-7 | H17: PASAJE LOS ARAUCANOS 01351, comuna de PUENTE ALTO | I17: PUENTE ALTO | J17: 45827 | K17: ROBADO | L17: =+VLOOKUP(A17,'[1]ORIGINAL '!D:N,11,0) -> CASTIGO
A18: 2535757 | B18: 26517020-K | C18: PEDRO HUGO ALVARADO PIÑEDO | D18: C-16647-2024 | E18: 26º Juzgado Civil de Santiago | F18: 9224592 | G18: SWWC.84-5 | H18: COQUIMBO 1189 DEPTO 1136, comuna de Santiago | I18: SANTIAGO | L18: =+VLOOKUP(A18,'[1]ORIGINAL '!D:N,11,0) -> CASTIGO
A19: 2895886 | B19: 25456204-1 | C19: ARMANDO JOSE VELASQUEZ ORSINI | D19: C-683-2025 | E19: 23º Juzgado Civil de Santiago | F19: 8074937 | G19: RKYV.85-9 | H19: PASAJE SANTA CARMEN N°02742, comuna de PUENTE ALTO | I19: PUENTE ALTO | J19: 45855 | L19: =+VLOOKUP(A19,'[1]ORIGINAL '!D:N,11,0) -> CASTIGO
A20: 2942690 | B20: 12408989-1 | C20: Mauricio Luciano Moran Mujica | D20: C-15703-2024 | E20: 16º Juzgado Civil de Santiago | F20: 10747281 | G20: JCVV.73-K | H20: Las Golondrinas Poniente 4081, comuna de Maipú | I20: MAIPU | J20: 45853 | L20: =+VLOOKUP(A20,'[1]ORIGINAL '!D:N,11,0) -> CASTIGO
A21: 1585963 | B21: 18051143-1 | C21: ANGELA ALEJANDRA REBECO PÉREZ | D21: C-20323-2024 | E21: 26º Juzgado Civil de Santiago | F21: 5825493 | G21: RHJR.26-K | H21: Pasaje. Antofagasta 2161 Departamento. 306, comuna de Maipú | I21: MAIPU | J21: 45859 | L21: =+VLOOKUP(A21,'[1]ORIGINAL '!D:N,11,0) -> CASTIGO
A22: 1642440 | B22: 16121390-K | C22: NICOLÁS PATRICIO ARRAU SOTO | D22: C-21660-2024 | E22: 24º Juzgado Civil de Santiago | F22: 12008304 | G22: RKXF.13-K | H22: MANQUEHUE NORTE 1635 DPTO 104, comuna de Vitacura | I22: VITACURA | J22: 45875 | L22: =+VLOOKUP(A22,'[1]ORIGINAL '!D:N,11,0) -> CASTIGO
A23: 1642440 | B23: 15035046-8 | C23: YUYUNIS ELIZABETH LOPEHANDÍA GAJARDO | D23: C-21660-2024 | E23: 24º Juzgado Civil de Santiago | F23: 12008304 | G23: RKXF.13-K | H23: MANQUEHUE NORTE 1635 DPTO 104, comuna de Vitacura | I23: VITACURA | J23: 45875 | L23: =+VLOOKUP(A23,'[1]ORIGINAL '!D:N,11,0) -> CASTIGO
A24: 2032522 | B24: 18690010-3 | C24: Brian Abdon Romero Saavedra | D24: E-1974-2025 | E24: 1º Juzgado de Letras de la Serena | F24: 3128101 | G24: PFRL.77-5 | H24: MARIO VANNI SANDOVAL N° 1737, COMUNA DE LA SERENA | I24: LA SERENA | J24: 45883 | L24: =+VLOOKUP(A24,'[1]ORIGINAL '!D:N,11,0) -> #N/A
A25: 1540238 | B25: 16552562-0 | C25: GUILLERMO ANDRÉS BAHAMONDES LORCA | D25: C-20327-2024 | E25: 23º Juzgado Civil de Santiago | F25: 5822119 | G25: RFYY.61-2 | H25: LOS ATACAMEÑOS 2577, comuna de RENCA | I25: RENCA | J25: 45897 | L25: =+VLOOKUP(A25,'[1]ORIGINAL '!D:N,11,0) -> VIGENTE
A26: 3052601 | B26: 26929191-5 | C26: NOELIA MARGARITA CHALO | D26: C-20321-2024 | E26: 13º Juzgado Civil de Santiago | F26: 22115384 | G26: RKJL.71-9 | H26: AVENIDA PUNTA NOGALES 1384, comuna de Huechuraba | I26: HUECHURABA | J26: 45912 | L26: =+VLOOKUP(A26,'[1]ORIGINAL '!D:N,11,0) -> CASTIGO
A27: 2790280 | B27: 15943535-0 | C27: LUIS CAMILO ITURRA EICHIN | D27: C-3907-2025 | E27: 16º JUZGADO CIVIL DE SANTIAGO | F27: 7649079 | G27: TCWJ.59-1 | H27: CALLE EL MAICILLO 4334 ISLA DE MAIPO | I27: ISLA DE MAIPO | J27: 45911 | L27: =+VLOOKUP(A27,'[1]ORIGINAL '!D:N,11,0) -> #N/A
A28: 2959119 | B28: 19898341-1 | C28: CHRISTOPHER ROMMEL SANTOS ÑANCO | D28: C-2592-2025 | E28: 15º JUZGADO CIVIL DE SANTIAGO | F28: 5647062 | G28: RRGV.44-8 | H28: PASAJE DIEZ N°5836, comuna de La Florida | I28: LA FLORIDA | J28: 45916 | L28: =+VLOOKUP(A28,'[1]ORIGINAL '!D:N,11,0) -> CASTIGO
A29: 2307739 | B29: 12885296-4 | C29: CLAUDIO ALEJANDRO VARGAS PÉREZ | D29: C-19085-2024 | E29: 18º Juzgado Civil de Santiago | F29: 4035116 | G29: SKBG.51-K | H29: Espinalillo S/N Lote 1, comuna de San Fernando | I29: SAN FERNANDO | L29: =+VLOOKUP(A29,'[1]ORIGINAL '!D:N,11,0) -> VIGENTE
A30: 2645056 | B30: 13038018-2 | C30: ANA LIDIA BASTÍAS ARAYA | D30: C-5503-2025 | E30: 4º Juzgado Civil de Santiago | F30: 13761870 | G30: KDBV.46-9, | H30: AV CHESTERTON N°7172 Dpt 142, comuna de Las Condes | I30: LAS CONDES | J30: 45925 | L30: =+VLOOKUP(A30,'[1]ORIGINAL '!D:N,11,0) -> CASTIGO
A31: 1782538 | B31: 16174268-6 | C31: JACQUELINE ANDREA GONZÁLEZ CALDERON | D31: C-22302-2024 | E31: 22º Juzgado Civil de Santiago | F31: 4225977 | G31: LPFT.73-6 | H31: Pasaje El Estrecho 1951, comuna de Peñalolén | I31: PEÑALOLEN | J31: 45931 | L31: =+VLOOKUP(A31,'[1]ORIGINAL '!D:N,11,0) -> CASTIGO
A32: 2678909 | B32: 77081782-K | C32: COMERCIALIZADORA Y DISTRIBUIDORA SAN PABLO SPA | D32: C-20329-2024 | E32: 1º Juzgado Civil de Santiago | F32: 3998986 | G32: SRTD.89-3 | H32: ANTILLANCA N°9087 DPT 901, comuna de Vitacura | I32: VITACURA | J32: 45953 | K32: INCAUTADO | L32: =+VLOOKUP(A32,'[1]ORIGINAL '!D:N,11,0) -> CASTIGO
A33: 2768727 | B33: 18151055-2 | C33: Carlos Andres Silva Lopez | D33: C-20318-2024 | E33: 6º Juzgado Civil de Santiago | F33: 7167235 | G33: HRGF.52-7 | H33: Libertad N°1273, comuna de LAMPA | I33: LAMPA | J33: 45957 | K33: INCAUTADO | L33: =+VLOOKUP(A33,'[1]ORIGINAL '!D:N,11,0) -> CASTIGO
A34: 2206128 | B34: 16075823-6 | C34: ALEJANDRO ESTEBAN BEYTÍA OJEDA | D34: C-9896-2025 | E34: 29º Juzgado Civil de Santiago | F34: 7563478 | G34: SFKW.72-9 | H34: MAR EGO N°1772, comuna de EL BOSQUE | I34: EL BOSQUE | J34: 45595 | L34: =+VLOOKUP(A34,'[1]ORIGINAL '!D:N,11,0) -> CASTIGO
A35: 3279513 | B35: 17.633.955-1 | C35: NATALIA JACQUELINE VILCHES RUBILLANCA | D35: C-8328-2025 | E35: 15º Juzgado Civil de Santiago | F35: 17328930 | G35: TYZB.63-5 | H35: EL ALCAZAR ORIENTE 305, comuna de Maipú | I35: MAIPU | J35: 45993 | L35: =+VLOOKUP(A35,'[1]ORIGINAL '!D:N,11,0) -> CASTIGO
A36: 2943458 | B36: 17.696.201-1 | C36: LEONARDO ANTONIO ROA GUZMÃN | D36: C-3910-2025 | E36: 15º Juzgado Civil de Santiago | F36: 2668370 | G36: PDPT.52-2 | H36: Apóstol Santiago N°2347 Dpto 24 Block 8 | I36: RENCA | J36: 45995 | L36: =+VLOOKUP(A36,'[1]ORIGINAL '!D:N,11,0) -> #N/A
A37: 2974045 | B37: 77.436.846-9 | C37: Sociedad De Servicios Dedes Sepulveda Spa | D37: E-793-2025 | E37: Juzgado de Letras de San Javier | F37: 10887731 | G37: HLYR.49-2 | H37: Soldado Guerra del Pacífico N°451, comuna San Javier | I37: SAN JAVIER | J37: 46000 | L37: =+VLOOKUP(A37,'[1]ORIGINAL '!D:N,11,0) -> CASTIGO
A38: 3191186 | B38: 8.167.513-9 | C38: ESTELA ROSA NÚÑEZ QUINTANA | D38: C-6720-2025 | E38: 21º Juzgado Civil de Santiago | F38: 3362898 | G38: LWWP.62-3 | H38: Nonato Coo N°3298, comuna de PUENTE ALTO | I38: PUENTE ALTO | J38: 46000 | K38: INCAUTADO | L38: =+VLOOKUP(A38,'[1]ORIGINAL '!D:N,11,0) -> #N/A
A39: 3170179 | B39: 19.056.039-2 | C39: CARLOS IVAN VILLABLANCA JAQUE | D39: C-3917-2025 | E39: 14º Juzgado Civil de Santiago | F39: 16568260 | G39: LRWP.41-2 | H39: PSJE. BENJAMIN QUEZADA N°1238, comuna de Conchalí | I39: CONCHALI | J39: 46014 | L39: =+VLOOKUP(A39,'[1]ORIGINAL '!D:N,11,0) -> CASTIGO
A40: 3159188 | B40: 17.904.802-7 | C40: RUBÉN ARNALDO PARRA QUINTRICON | D40: C-2592-2025 | E40: 11º Juzgado Civil de Santiago | F40: 8655007 | G40: TSLH.96-0 | H40: San Jose 2538 Departamento 306, comuna de Maipú | I40: MAIPU | J40: 46015 | L40: =+VLOOKUP(A40,'[1]ORIGINAL '!D:N,11,0) -> CASTIGO
A41: 2749966 | B41: 12.401.950-8 | C41: NORBERTO ENRIQUE COLLAO MARIN | D41: C-3912-2025 | E41: 11º Juzgado Civil de Santiago | F41: 8838078 | G41: TCRY.73-1 | H41: SANTA BERTA N°2680, comuna de Maipú | I41: MAIPU | J41: 46017 | K41: INCAUTADO | L41: =+VLOOKUP(A41,'[1]ORIGINAL '!D:N,11,0) -> CASTIGO
A42: 2764515 | B42: 24.025.013-6 | C42: NATHALIE URIBE ZUÑIGA | D42: E-720-2026 | E42: 1º Juzgado Civil de Puente Alto | F42: 5442040 | G42: KXGK.80-8 | H42: BALMACEDA N° 371 DPT 411, comuna de PUENTE ALTO | I42: PUENTE ALTO | J42: 46384 | L42: =+VLOOKUP(A42,'[1]ORIGINAL '!D:N,11,0) -> CASTIGO
A43: 1603752 | B43: 26.445.123-K | C43: EDDY SIMON | D43: E-140-2026 | E43: Juzgado de Letras de Colina | F43: 3882712 | G43: RLCK.51-5 | H43: LOS INGLESES N°166 | I43: COLINA | J43: 46049 | L43: =+VLOOKUP(A43,'[1]ORIGINAL '!D:N,11,0) -> CASTIGO
A44: 1335938 | B44: 12.886.726-0 | C44: GUILLERMO ENRIQUE MIRANDA FLORES | D44: C-22135-2024 | E44: 11º Juzgado Civil de Santiago | F44: 3344828 | G44: PSZB.25-5 | H44: San Pedro Departamento 37 Block 3611, comuna de PUENTE ALTO | I44: PUENTE ALTO | J44: 46042 | K44: PENSION | L44: =+VLOOKUP(A44,'[1]ORIGINAL '!D:N,11,0) -> #N/A
A45: 2392109 | B45: 16.636.916-9 | C45: JOSÉ DOMINGO OSORIO ROMERO | D45: C-20328-2024 | E45: 23º Juzgado Civil de Santiago | F45: 4524773 | G45: JCDG.38-0 | H45: GREGORIO DE LA FUENTE 3268 DEPTO 1704 A, comuna de Macul | I45: MACUL | J45: 46041 | L45: =+VLOOKUP(A45,'[1]ORIGINAL '!D:N,11,0) -> #N/A
A46: 1871157 | B46: 19.061.423-9 | C46: LAURA SOFIA CUBILLOS REYES | D46: C-11270-2025 | E46: 17º Juzgado Civil de Santiago | F46: 4750290 | G46: RVZR.39-8 | H46: PEDRO MIRA N°431, comuna de SAN JOAQUIN | I46: SAN JOAQUIN | J46: 46041 | L46: =+VLOOKUP(A46,'[1]ORIGINAL '!D:N,11,0) -> #N/A
A47: 2764515 | B47: 24.025.013-6 | C47: NATHALIE URIBE ZUÑIGA | D47: E-720-2026 | E47: 1º Juzgado Civil de Puente Alto | F47: 5442040 | G47: KXGK.80-8 | H47: BALMACEDA N° 371 DPT 411, comuna de PUENTE ALTO | I47: PUENTE ALTO | J47: 46054 | L47: =+VLOOKUP(A47,'[1]ORIGINAL '!D:N,11,0) -> CASTIGO
A48: 2514373 | B48: 15.618.940-5 | C48: LORENS GRACE SEPULVEDA RIQUELME | D48: C-2589-2025 | E48: 19º Juzgado Civil de Santiago | F48: 16355846 | G48: SVHP.70-8 | H48: 19 Norte 1004, comuna de Independencia | I48: INDEPENDENCIA | J48: 46054 | L48: =+VLOOKUP(A48,'[1]ORIGINAL '!D:N,11,0) -> CASTIGO
A49: 1846277 | B49: 77.069.582-1 | C49: CONSTRUCCIONES PTS LIMITADA | D49: C-5504-2025 | E49: 4º Juzgado Civil de Santiago | F49: 1171902 | G49: PBFW.24-2 | H49: CHOSHUENCO N° 1399, comuna de La Florida | I49: LA FLORIDA | J49: 46054 | L49: =+VLOOKUP(A49,'[1]ORIGINAL '!D:N,11,0) -> VIGENTE
A50: 3365202 | B50: 26.300.999-1 | C50: LUISA JOSEFA MORALES BARRERO | D50: C-11288-2025 | E50: 7º Juzgado Civil de Santiago | F50: 8073242 | G50: VCPR.85-K | H50: SAN NICOLAS 1380 EDIFICIO A DPTO 406, comuna de SAN MIGUEL | I50: SAN MIGUEL | J50: 46054 | L50: =+VLOOKUP(A50,'[1]ORIGINAL '!D:N,11,0) -> VIGENTE
A51: 2678831 | B51: 26.423.358-5 | C51: CARLOS EDUARDO GUERRA YAÑEZ | D51: C-9873-2025 | E51: 26º Juzgado Civil de Santiago | F51: 3565223 | G51: SWKW.26-4 | H51: SAN ISIDRO 250 DEPTO 2217, comuna de SANTIAGO | I51: SANTIAGO | J51: 46054 | L51: =+VLOOKUP(A51,'[1]ORIGINAL '!D:N,11,0) -> VIGENTE
A52: 3300923 | B52: 14.190.835-9 | C52: RONNY ALBERTO MERIÑO UBAL | D52: C-8483-2025 | E52: 17º Juzgado Civil de Santiago | F52: 4442016 | G52: FBRX.10-2 | H52: TURQUESTAN N°795, comuna de MAIPU | I52: MAIPU | J52: 46054 | L52: =+VLOOKUP(A52,'[1]ORIGINAL '!D:N,11,0) -> VIGENTE
A53: 1670767 | B53: 17.484.899-8 | C53: ANGÉLICA ESTER NARVÁEZ CASTRO | D53: C-8323-2025 | E53: 28º Juzgado Civil de Santiago | F53: 6262558 | G53: RRJV.47-3 | H53: VIOLETA PARRA 1954 DPTO TORRE I DEPTO 212, comuna de LA PINTANA | I53: LA PINTANA | J53: 46054 | K53: INCAUTADO | L53: =+VLOOKUP(A53,'[1]ORIGINAL '!D:N,11,0) -> CASTIGO
A54: 2663330 | B54: 7.044.994-3 | C54: CARMEN LUZ VENEGAS MALUENDA | D54: C-15733-2024 | E54: 23º Juzgado Civil de Santiago | F54: 10787481 | G54: JJXL.31-3 | H54: Huérfanos Nº 714, Of. 116, comuna de Santiago | I54: SANTIAGO | J54: 46054 | L54: =+VLOOKUP(A54,'[1]ORIGINAL '!D:N,11,0) -> CASTIGO
A55: 2550653 | B55: 20.138.902-K | C55: MARÍA JOSÉ RIVERA RÍOS | D55: C-683-2025 | E55: 30º Juzgado Civil de Santiago | F55: 5286982 | G55: LKXR.77-9 | H55: DIAGONAL TRAVESIA N° 8721 Depto 204 Torre Florencia, comuna de Pudahuel | I55: PUDAHUEL | J55: 46054 | L55: =+VLOOKUP(A55,'[1]ORIGINAL '!D:N,11,0) -> VIGENTE
A56: 2869439 | B56: 17.250.462-0 | C56: PABLO CÉSAR LÓPEZ RIQUELME | D56: C-19066-2024 | E56: 4º Juzgado Civil de Santiago | F56: 11436130 | G56: RSTX.44 | H56: ÑUBLE N°985, comuna de Santiago | I56: SANTIAGO | J56: 46079 | K56: INCAUTADO | L56: =+VLOOKUP(A56,'[1]ORIGINAL '!D:N,11,0) -> VIGENTE
A57: 3253290 | B57: 26.312.380-8 | C57: JERALDINE NAZARETH DEL CARMEN SERRANO HERRERA | D57: C-5506-2025 | E57: 18º Juzgado Civil de Santiago | F57: 8932012 | G57: JYZK.93-2 | H57: Aragonés 5 Poniente Casa 1065, comuna de PUENTE ALTO | I57: PUENTE ALTO | J57: 45978 | L57: =+VLOOKUP(A57,'[1]ORIGINAL '!D:N,11,0) -> CASTIGO
A58: 2794654 | B58: 10.101.870-9 | C58: VICTOR MANUEL SEPULVEDA SCHAAF | D58: E-232-2026 | E58: Juzgado de Letras de La Ligua | F58: 3203244 | G58: KLJY.76-K | H58: EL BELLOTO 70 COMUNA DE PAPUDO | I58: PAPUDO | J58: 46086 | L58: =+VLOOKUP(A58,'[1]ORIGINAL '!D:N,11,0) -> VIGENTE
A59: 3246183 | B59: 12.325.963-7 | C59: ESTEBAN ALFREDO NEIRA PEREZ | D59: E-294-2026 | E59: 1º Juzgado de Letras de Los Angeles | F59: 7526544 | G59: TWKK.13-9 | H59: LOS OMAGUACAS N°1720 VILLA LAS AMERICAS, LOS ANGELES | I59: LOS ANGELES | J59: 46087 | L59: =+VLOOKUP(A59,'[1]ORIGINAL '!D:N,11,0) -> CASTIGO
A60: 2206586 | B60: 17.395.256-2 | C60: JULIO CESAR COÑOPAN ESPINOZA | D60: E-6359-2025 | E60: 3º Juzgado Civil de Concepción | F60: 5914449 | G60: SHYD.64-8 | H60: Calle Almirante Rivero Norte Nº1875 Block B Departamento 203, Concepcion | I60: CONCEPACION | J60: 46087 | L60: =+VLOOKUP(A60,'[1]ORIGINAL '!D:N,11,0) -> VIGENTE
A61: 3052978 | B61: 14.398.506-7 | C61: JORGE ANSELMO SANCHEZ VILLARROEL | D61: E-1955-2025 | E61: 2º Juzgado de Letras Civil de Antofagasta | F61: 11339711 | G61: TPCJ.93-0 | H61: Oscar Bonilla N° 9211 comuna Antofagasta | I61: ANTOGASTA | J61: 45904 | L61: =+VLOOKUP(A61,'[1]ORIGINAL '!D:N,11,0) -> CASTIGO
A62: 2984397 | B62: 26.178.249-9 | C62: EDWIN ALBERTO SALINAS LEON | D62: C-22134-2024 | E62: 4º Juzgado Civil de Santiago | F62: 6261294 | G62: RPXP.90-1 | H62: Avda. Espa a #62, casa 10, comuna de Santiago | I62: SANTIAGO | J62: 45728 | L62: =+VLOOKUP(A62,'[1]ORIGINAL '!D:N,11,0) -> CASTIGO
A63: 3127421 | B63: 26.496.146-7 | C63: KARLA DIANNETT COLMENARES MORA | D63: C-11271-2025 | E63: 20º Juzgado Civil de Santiago | F63: 4547513 | G63: RHVS.58-3 | H63: VILLASANA 2045 DP 43 TORRE D, comuna de Quinta Normal | I63: QUINTA NORMAL | J63: 46094 | K63: INCAUTADO | L63: =+VLOOKUP(A63,'[1]ORIGINAL '!D:N,11,0) -> #N/A
A64: 2893403 | B64: 10.357.961-9 | C64: LUZ MARCELA LOPEZ BEAS | D64: E-5182-2025 | E64: 2º Juzgado Civil de Rancagua | F64: 6408585 | G64: RVRB.23-7 | H64: CALLE CENTRAL N° 27 B, POBLACION EL ÁLAMO, COYA, comuna de MACHALI | I64: MACHALI | J64: 46055 | L64: =+VLOOKUP(A64,'[1]ORIGINAL '!D:N,11,0) -> VIGENTE
A65: 2470930 | B65: 15.018.806-7 | C65: JORGE MARCELO TRIGO VEGA | D65: E-2812-2025 | E65: 2º Juzgado de Letras Civil de Antofagasta | F65: 3948079 | G65: PGRC.55-4 | H65: Río Maule N°9575, Antofagasta | I65: ANTOGASTA | J65: 46048 | L65: =+VLOOKUP(A65,'[1]ORIGINAL '!D:N,11,0) -> VIGENTE
A66: 2134165 | B66: 12.178.968-K | C66: CÉSAR ANDRÉS MUÑOZ HERRERA | D66: C-8314-2025 | E66: 2º Juzgado Civil de Santiago | F66: 3005804 | G66: RPWP.65-5 | H66: Santa Filomena 172 Casa 62, comuna de Recoleta | I66: RECOLETA | J66: 46091 | L66: =+VLOOKUP(A66,'[1]ORIGINAL '!D:N,11,0) -> CASTIGO
A67: 2740588 | B67: 10.639.738-4 | C67: CRISTIAN ALEJANDRO ANTONIO RIQUELME VILLAGRA | D67: C-20330-2024 | E67: 18º Juzgado Civil de Santiago | F67: 7970131 | G67: RGXJ.94-1 | H67: Pudeto 6579 Departamento 1706, comuna de La Florida | I67: LA FLORIDA | J67: 46097 | L67: =+VLOOKUP(A67,'[1]ORIGINAL '!D:N,11,0) -> CASTIGO
A68: 2751867 | B68: 25.588.177-9 | C68: BIANEY YOSELY RODRIGUEZ DELGADO | D68: C-6724-2025 | E68: 23º Juzgado Civil de Santiago | F68: 4996835 | G68: RDKT.58-2 | H68: AV ZAÑARTU N°1315 DEPARTAMENTO N°1319, comuna de Ñuñoa | I68: ÑUÑOA | J68: 46105 | L68: =+VLOOKUP(A68,'[1]ORIGINAL '!D:N,11,0) -> CASTIGO | M68: catalpa 1461 | N68: san bernardo
A69: 2942651 | B69: 16.392.150-2 | C69: PATRICIA ALEJANDRA ZEPEDA RIVEROS | D69: C-8354-2025 | E69: 7º Juzgado Civil de Santiago | F69: 6851294 | G69: RCCK.77-7 | H69: GENERAL BUENDIA #431 BLOCK 109 DEPARTAMENTO 11 VILLA VILLA ARTURO PRAT, comuna de Lo Prado | I69: Lo Prado | J69: 46105 | K69: INCAUTADO | L69: =+VLOOKUP(A69,'[1]ORIGINAL '!D:N,11,0) -> #N/A
A70: 1752476 | B70: 18.957.719-2 | C70: PEDRO GERMAN ESPINOZA MUÑOZ | D70: E-514-2026 | E70: 2º Juzgado Civil de Concepción | F70: 4993261 | G70: RTRZ.90-K | H70: Calle 2, casa 749, Boca Sur, San Pedro de la Paz | I70: San Pedro de La Paz | J70: 46100 | L70: =+VLOOKUP(A70,'[1]ORIGINAL '!D:N,11,0) -> CASTIGO
A71: 3307443 | B71: 16.922.010-7 | C71: FELIPE ANDRES ARAVENA CALFUNAO | D71: E-458-2026 | E71: 1º Juzgado Civil de Valdivia | F71: 6585362 | G71: RLRZ.31-7 | H71: PEDRO AGUIRRE CERDA 206 AUTOMOTORA BERRIOS, VALDIVIA | I71: VALDIVIA | J71: 46106 | L71: =+VLOOKUP(A71,'[1]ORIGINAL '!D:N,11,0) -> VIGENTE
A72: 2184893 | B72: 15.396.541-2 | C72: LUIS DAVID CORTES RAMIREZ | D72: E-101-2026 | E72: 1º Juzgado Civil de San Miguel | F72: 7148399 | G72: SHBP.19-5 | H72: Paicavi N 0820, comuna de La Pintana | I72: LA PINTANA | J72: 46107 | L72: =+VLOOKUP(A72,'[1]ORIGINAL '!D:N,11,0) -> CASTIGO
A73: 1854377 | B73: 13.422.825-3 | C73: PAMELA ALEJANDRA MIRANDA GARCIA | D73: E-87-2026 | E73: 2º Juzgado de Letras de Copiapó | F73: 3801438 | G73: RVRF.34-1 | H73: CARLOS VAN BUREN 823, COPIAPO | I73: COPIAPO | J73: 46107 | L73: =+VLOOKUP(A73,'[1]ORIGINAL '!D:N,11,0) -> #N/A
A74: 1865019 | B74: 25.013.996-9 | C74: DANIEL LOPEZ GARCIA | D74: E-2293-2025 | E74: 2º Juzgado de Letras Civil de Antofagasta | F74: 5619946 | G74: RVRH.84-0 | H74: calle Diagonal Norte N°5706, comuna de Antofagasta | I74: ANTOGASTA | J74: 45971 | L74: =+VLOOKUP(A74,'[1]ORIGINAL '!D:N,11,0) -> CASTIGO
A75: 1493544 | B75: 15.621.497-3 | C75: PAULINA ANDREA HENRIQUEZ TELLO | D75: E-1967-2025 | E75: Juzgado de Letras de La Ligua | F75: 8497163 | G75: KVJW.91-2 | H75: LOMAS DE CATAPILCO SITIO N°58, COMUNA DE ZAPALLAR | J75: 45960 | L75: =+VLOOKUP(A75,'[1]ORIGINAL '!D:N,11,0) -> CASTIGO
A76: 2056023 | B76: 76.823.538-4 | C76: COMERCIALIZADORA CORRALES DEL CAMPO CL SPA | D76: E-2352-2025 | E76: 3º Juzgado de Letras de Talca | F76: 10686633 | G76: SCXD.60-1 | H76: LOS MAITENES 1974 LA FORESTA III, TALCA | I76: TALCA | J76: 46052 | L76: =+VLOOKUP(A76,'[1]ORIGINAL '!D:N,11,0) -> VIGENTE
A77: 3321265 | B77: 77.290.431-2 | C77: SERVICIOS PUBLICITARIOS Y TEXTILES MATEXSA SPA | D77: C-14451-2025 | E77: 30º Juzgado Civil de Santiago | F77: 8424283 | G77: PSXX.27-9 | H77: Av Cuadro Verde 160, Torre1 Departamento24, comuna de Estación Central | I77: ESTACION CENTRAL | J77: 46125 | L77: =+VLOOKUP(A77,'[1]ORIGINAL '!D:N,11,0) -> VIGENTE

Sheet TUBO VIGENTE 
A1: CREDITO | B1: RUT | C1: NOMBRE | D1: TRAMO | E1: TRAMO ACTUAL | F1: ESTADO_COBRANZA | G1: SOLUCION | H1: N° CUOTAS | I1: DIAS MORA | J1: VALOR CUOTA | K1: CAPITAL | L1: VALOR APROX DE PAGO | M1: FECHA COMPROMISO | N1: ESTADO | O1: FECHA PAGO | P1: RECUPERADO | Q1: OBSERVACIONES | R1: EJECUTIVA | S1: audios | T1: Oficio
A2: 3379591 | B2: =VLOOKUP(A2,Export!A:N,14,0) -> 12303126 | C2: =VLOOKUP(A2,Export!A:P,16,0) -> EDMUNDO JAVIER FUENTES RODRÍGUEZ | D2: =VLOOKUP(A2,Export!A:H,8,0) -> 121-150 | E2: =VLOOKUP(A2,Export!A:I,9,0) -> 151-180 | F2: =VLOOKUP(A2,Export!A:AH,34,0) -> NO RECUPERADO | G2: PAGO CUOTAS | H2: 4 | I2: =VLOOKUP(A2,Export!A:B,2,0) -> 155 | J2: =VLOOKUP(A2,Export!A:R,18,0) -> 329.902 | K2: =VLOOKUP(A2,Export!A:D,4,0) -> 10431044 | L2: =IF(G2="PAGO CUOTAS",H2*J2,K2) -> 1319.608 | M2: 46171 | N2: PAGADO | P2: =+SUMIF(N2,"PAGADO",K2) -> 10431044 | R2: =+VLOOKUP(A2,'[1]ORIGINAL '!D:E,2,0) -> 0 | S2: FALSE | T2: =VLOOKUP(A2,'OFICIO '!A:J,10,0) -> #N/A
A3: 2796242 | B3: =VLOOKUP(A3,Export!A:N,14,0) -> #N/A | C3: =VLOOKUP(A3,Export!A:P,16,0) -> #N/A | D3: =VLOOKUP(A3,Export!A:H,8,0) -> #N/A | E3: =VLOOKUP(A3,Export!A:I,9,0) -> #N/A | F3: =VLOOKUP(A3,Export!A:AH,34,0) -> #N/A | G3: PAGO CUOTAS | H3: =VLOOKUP(A3,Export!A:C,3,0) -> #N/A | I3: =VLOOKUP(A3,Export!A:B,2,0) -> #N/A | J3: =VLOOKUP(A3,Export!A:R,18,0) -> #N/A | K3: =VLOOKUP(A3,Export!A:D,4,0) -> #N/A | L3: =IF(G3="PAGO CUOTAS",H3*J3,K3) -> #N/A | M3: 46117 | N3: PAGADO | O3: 46117 | P3: =+SUMIF(N3,"PAGADO",K3) -> #N/A | R3: =+VLOOKUP(A3,'[1]ORIGINAL '!D:E,2,0) -> 0 | S3: FALSE | T3: =VLOOKUP(A3,'OFICIO '!A:J,10,0) -> #N/A
A4: 3288242 | B4: =VLOOKUP(A4,Export!A:N,14,0) -> 76839537 | C4: =VLOOKUP(A4,Export!A:P,16,0) -> PROSMART SERVICIOS SPA SPA | D4: =VLOOKUP(A4,Export!A:H,8,0) -> 31-60 | E4: =VLOOKUP(A4,Export!A:I,9,0) -> 31-60 | F4: =VLOOKUP(A4,Export!A:AH,34,0) -> NO RECUPERADO | G4: PAGO CUOTAS | H4: 2 | I4: =VLOOKUP(A4,Export!A:B,2,0) -> 53 | J4: =VLOOKUP(A4,Export!A:R,18,0) -> 481.757 | K4: =VLOOKUP(A4,Export!A:D,4,0) -> 13963215 | L4: =IF(G4="PAGO CUOTAS",H4*J4,K4) -> 963.514 | M4: 29-05-2026 | N4: PAGADO | P4: =+SUMIF(N4,"PAGADO",K4) -> 13963215 | R4: =+VLOOKUP(A4,'[1]ORIGINAL '!D:E,2,0) -> 0 | S4: FALSE | T4: =VLOOKUP(A4,'OFICIO '!A:J,10,0) -> #N/A
A5: 1910675 | B5: =VLOOKUP(A5,Export!A:N,14,0) -> 6461783 | C5: =VLOOKUP(A5,Export!A:P,16,0) -> RAÚL EUGENIO VILLAR MESÍAS | D5: =VLOOKUP(A5,Export!A:H,8,0) -> 31-60 | E5: =VLOOKUP(A5,Export!A:I,9,0) -> 61-90 | F5: =VLOOKUP(A5,Export!A:AH,34,0) -> NO RECUPERADO | G5: PAGO CUOTAS | H5: =VLOOKUP(A5,Export!A:C,3,0) -> 1 | I5: =VLOOKUP(A5,Export!A:B,2,0) -> 71 | J5: =VLOOKUP(A5,Export!A:R,18,0) -> 449.264 | K5: =VLOOKUP(A5,Export!A:D,4,0) -> 439292 | L5: =IF(G5="PAGO CUOTAS",H5*J5,K5) -> 449.264 | M5: 46154 | N5: PAGADO | P5: =+SUMIF(N5,"PAGADO",K5) -> 439292 | R5: =+VLOOKUP(A5,'[1]ORIGINAL '!D:E,2,0) -> 0 | S5: FALSE | T5: =VLOOKUP(A5,'OFICIO '!A:J,10,0) -> #N/A
A6: 2098963 | B6: =VLOOKUP(A6,Export!A:N,14,0) -> 11343555 | C6: =VLOOKUP(A6,Export!A:P,16,0) -> CLAUDIA ALEJANDRA CASTILLO ZAPATA | D6: =VLOOKUP(A6,Export!A:H,8,0) -> 31-60 | E6: =VLOOKUP(A6,Export!A:I,9,0) -> 61-90 | F6: =VLOOKUP(A6,Export!A:AH,34,0) -> NO RECUPERADO | G6: PAGO CUOTAS | H6: =VLOOKUP(A6,Export!A:C,3,0) -> 3 | I6: =VLOOKUP(A6,Export!A:B,2,0) -> 76 | J6: =VLOOKUP(A6,Export!A:R,18,0) -> 253.024 | K6: =VLOOKUP(A6,Export!A:D,4,0) -> 1175169 | L6: =IF(G6="PAGO CUOTAS",H6*J6,K6) -> 759.072 | M6: 46171 | N6: PAGADO | P6: =+SUMIF(N6,"PAGADO",K6) -> 1175169 | Q6: pago una sola cuota | R6: =+VLOOKUP(A6,'[1]ORIGINAL '!D:E,2,0) -> 0 | S6: FALSE | T6: =VLOOKUP(A6,'OFICIO '!A:J,10,0) -> #N/A
A7: 2762947 | B7: =VLOOKUP(A7,Export!A:N,14,0) -> #N/A | C7: =VLOOKUP(A7,Export!A:P,16,0) -> #N/A | D7: =VLOOKUP(A7,Export!A:H,8,0) -> #N/A | E7: =VLOOKUP(A7,Export!A:I,9,0) -> #N/A | F7: =VLOOKUP(A7,Export!A:AH,34,0) -> #N/A | G7: PAGO CUOTAS | H7: =VLOOKUP(A7,Export!A:C,3,0) -> #N/A | I7: =VLOOKUP(A7,Export!A:B,2,0) -> #N/A | J7: =VLOOKUP(A7,Export!A:R,18,0) -> #N/A | K7: =VLOOKUP(A7,Export!A:D,4,0) -> #N/A | L7: =IF(G7="PAGO CUOTAS",H7*J7,K7) -> #N/A | M7: 46157 | N7: PAGADO | P7: =+SUMIF(N7,"PAGADO",K7) -> #N/A | R7: =+VLOOKUP(A7,'[1]ORIGINAL '!D:E,2,0) -> 0 | S7: FALSE | T7: =VLOOKUP(A7,'OFICIO '!A:J,10,0) -> #N/A
A8: 2832579 | B8: =VLOOKUP(A8,Export!A:N,14,0) -> #N/A | C8: =VLOOKUP(A8,Export!A:P,16,0) -> #N/A | D8: =VLOOKUP(A8,Export!A:H,8,0) -> #N/A | E8: =VLOOKUP(A8,Export!A:I,9,0) -> #N/A | F8: =VLOOKUP(A8,Export!A:AH,34,0) -> #N/A | G8: PAGO CUOTAS | H8: =VLOOKUP(A8,Export!A:C,3,0) -> #N/A | I8: =VLOOKUP(A8,Export!A:B,2,0) -> #N/A | J8: =VLOOKUP(A8,Export!A:R,18,0) -> #N/A | K8: =VLOOKUP(A8,Export!A:D,4,0) -> #N/A | L8: =IF(G8="PAGO CUOTAS",H8*J8,K8) -> #N/A | M8: 46147 | N8: PAGADO | P8: =+SUMIF(N8,"PAGADO",K8) -> #N/A | R8: =+VLOOKUP(A8,'[1]ORIGINAL '!D:E,2,0) -> 0 | S8: FALSE | T8: =VLOOKUP(A8,'OFICIO '!A:J,10,0) -> #N/A
A9: 2678831 | B9: =VLOOKUP(A9,Export!A:N,14,0) -> 26423358 | C9: =VLOOKUP(A9,Export!A:P,16,0) -> CARLOS EDUARDO GUERRA YAÑEZ | D9: =VLOOKUP(A9,Export!A:H,8,0) -> 31-60 | E9: =VLOOKUP(A9,Export!A:I,9,0) -> 31-60 | F9: =VLOOKUP(A9,Export!A:AH,34,0) -> CONTENIDO | G9: PAGO CUOTAS | H9: 2 | I9: =VLOOKUP(A9,Export!A:B,2,0) -> 40 | J9: =VLOOKUP(A9,Export!A:R,18,0) -> 203.815 | K9: =VLOOKUP(A9,Export!A:D,4,0) -> 2891119 | L9: =IF(G9="PAGO CUOTAS",H9*J9,K9) -> 407.63 | M9: 46169 | N9: PAGADO | O9: 46169 | P9: =+SUMIF(N9,"PAGADO",K9) -> 2891119 | R9: =+VLOOKUP(A9,'[1]ORIGINAL '!D:E,2,0) -> 0 | S9: FALSE | T9: =VLOOKUP(A9,'OFICIO '!A:J,10,0) -> 46054
A10: 2861527 | B10: =VLOOKUP(A10,Export!A:N,14,0) -> 15770754 | C10: =VLOOKUP(A10,Export!A:P,16,0) -> CARLA CRISTINA FUENTES CASTILLO | D10: =VLOOKUP(A10,Export!A:H,8,0) -> 46052 | E10: =VLOOKUP(A10,Export!A:I,9,0) -> 46052 | F10: =VLOOKUP(A10,Export!A:AH,34,0) -> CONTENIDO | G10: PAGO CUOTAS | H10: =VLOOKUP(A10,Export!A:C,3,0) -> 1 | I10: =VLOOKUP(A10,Export!A:B,2,0) -> 5 | J10: =VLOOKUP(A10,Export!A:R,18,0) -> 271.448 | K10: =VLOOKUP(A10,Export!A:D,4,0) -> 8608476 | L10: =IF(G10="PAGO CUOTAS",H10*J10,K10) -> 271.448 | M10: 46147 | N10: PAGADO | P10: =+SUMIF(N10,"PAGADO",K10) -> 8608476 | R10: =+VLOOKUP(A10,'[1]ORIGINAL '!D:E,2,0) -> 0 | S10: FALSE | T10: =VLOOKUP(A10,'OFICIO '!A:J,10,0) -> #N/A
A11: 2870557 | B11: =VLOOKUP(A11,Export!A:N,14,0) -> 16856352 | C11: =VLOOKUP(A11,Export!A:P,16,0) -> MILENA JOHANA VERGARA VERGARA | D11: =VLOOKUP(A11,Export!A:H,8,0) -> 31-60 | E11: =VLOOKUP(A11,Export!A:I,9,0) -> 61-90 | F11: =VLOOKUP(A11,Export!A:AH,34,0) -> NO RECUPERADO | G11: PAGO CUOTAS | H11: =VLOOKUP(A11,Export!A:C,3,0) -> 3 | I11: =VLOOKUP(A11,Export!A:B,2,0) -> 76 | J11: =VLOOKUP(A11,Export!A:R,18,0) -> 274.397 | K11: =VLOOKUP(A11,Export!A:D,4,0) -> 2513192 | L11: =IF(G11="PAGO CUOTAS",H11*J11,K11) -> 823.191 | M11: 46164 | N11: PAGADO | O11: 46165 | P11: =+SUMIF(N11,"PAGADO",K11) -> 2513192 | R11: =+VLOOKUP(A11,'[1]ORIGINAL '!D:E,2,0) -> 0 | S11: FALSE | T11: =VLOOKUP(A11,'OFICIO '!A:J,10,0) -> #N/A
A12: 2949458 | B12: =VLOOKUP(A12,Export!A:N,14,0) -> 12175985 | C12: =VLOOKUP(A12,Export!A:P,16,0) -> PAUL DENIS FRANCISCO CABEZAS LÓPEZ | D12: =VLOOKUP(A12,Export!A:H,8,0) -> 61-90 | E12: =VLOOKUP(A12,Export!A:I,9,0) -> 91-120 | F12: =VLOOKUP(A12,Export!A:AH,34,0) -> NO RECUPERADO | G12: PAGO CUOTAS | H12: =VLOOKUP(A12,Export!A:C,3,0) -> 4 | I12: =VLOOKUP(A12,Export!A:B,2,0) -> 91 | J12: =VLOOKUP(A12,Export!A:R,18,0) -> 300.184 | K12: =VLOOKUP(A12,Export!A:D,4,0) -> 2491616 | L12: =IF(G12="PAGO CUOTAS",H12*J12,K12) -> 1200.736 | M12: 46166 | N12: PAGADO | P12: =+SUMIF(N12,"PAGADO",K12) -> 2491616 | R12: =+VLOOKUP(A12,'[1]ORIGINAL '!D:E,2,0) -> 0 | S12: FALSE | T12: =VLOOKUP(A12,'OFICIO '!A:J,10,0) -> #N/A
A13: 2961244 | B13: =VLOOKUP(A13,Export!A:N,14,0) -> #N/A | C13: =VLOOKUP(A13,Export!A:P,16,0) -> #N/A | D13: =VLOOKUP(A13,Export!A:H,8,0) -> #N/A | E13: =VLOOKUP(A13,Export!A:I,9,0) -> #N/A | F13: =VLOOKUP(A13,Export!A:AH,34,0) -> #N/A | G13: PAGO CUOTAS | H13: =VLOOKUP(A13,Export!A:C,3,0) -> #N/A | I13: =VLOOKUP(A13,Export!A:B,2,0) -> #N/A | J13: =VLOOKUP(A13,Export!A:R,18,0) -> #N/A | K13: =VLOOKUP(A13,Export!A:D,4,0) -> #N/A | L13: =IF(G13="PAGO CUOTAS",H13*J13,K13) -> #N/A | M13: 15-05-2026 | N13: PAGADO | O13: 46157 | P13: =+SUMIF(N13,"PAGADO",K13) -> #N/A | R13: =+VLOOKUP(A13,'[1]ORIGINAL '!D:E,2,0) -> 0 | S13: FALSE | T13: =VLOOKUP(A13,'OFICIO '!A:J,10,0) -> #N/A
A14: 3159040 | B14: =VLOOKUP(A14,Export!A:N,14,0) -> 13872350 | C14: =VLOOKUP(A14,Export!A:P,16,0) -> ALEJANDRO PATRICIO NIETO SALFATE | D14: =VLOOKUP(A14,Export!A:H,8,0) -> 31-60 | E14: =VLOOKUP(A14,Export!A:I,9,0) -> 31-60 | F14: =VLOOKUP(A14,Export!A:AH,34,0) -> CONTENIDO | G14: PAGO CUOTAS | H14: 2 | I14: =VLOOKUP(A14,Export!A:B,2,0) -> 34 | J14: =VLOOKUP(A14,Export!A:R,18,0) -> 510.567 | K14: =VLOOKUP(A14,Export!A:D,4,0) -> 15663717 | L14: =IF(G14="PAGO CUOTAS",H14*J14,K14) -> 1021.134 | M14: 46153 | N14: PAGADO | P14: =+SUMIF(N14,"PAGADO",K14) -> 15663717 | R14: =+VLOOKUP(A14,'[1]ORIGINAL '!D:E,2,0) -> 0 | S14: FALSE | T14: =VLOOKUP(A14,'OFICIO '!A:J,10,0) -> #N/A
A15: 3344186 | B15: =VLOOKUP(A15,Export!A:N,14,0) -> 17766543 | C15: =VLOOKUP(A15,Export!A:P,16,0) -> MAURICIO ANDRÉS GATICA ÁLVAREZ | D15: =VLOOKUP(A15,Export!A:H,8,0) -> 91-120 | E15: =VLOOKUP(A15,Export!A:I,9,0) -> 121-150 | F15: =VLOOKUP(A15,Export!A:AH,34,0) -> NO RECUPERADO | G15: PAGO CUOTAS | H15: =VLOOKUP(A15,Export!A:C,3,0) -> 5 | I15: =VLOOKUP(A15,Export!A:B,2,0) -> 137 | J15: =VLOOKUP(A15,Export!A:R,18,0) -> 311.974 | K15: =VLOOKUP(A15,Export!A:D,4,0) -> 7912592 | L15: =IF(G15="PAGO CUOTAS",H15*J15,K15) -> 1559.87 | M15: 46172 | N15: PENDIENTE | P15: =+SUMIF(N15,"PAGADO",K15) -> 0 | R15: =+VLOOKUP(A15,'[1]ORIGINAL '!D:E,2,0) -> 0 | S15: FALSE | T15: =VLOOKUP(A15,'OFICIO '!A:J,10,0) -> #N/A
A16: 3352007 | B16: =VLOOKUP(A16,Export!A:N,14,0) -> #N/A | C16: =VLOOKUP(A16,Export!A:P,16,0) -> #N/A | D16: =VLOOKUP(A16,Export!A:H,8,0) -> #N/A | E16: =VLOOKUP(A16,Export!A:I,9,0) -> #N/A | F16: =VLOOKUP(A16,Export!A:AH,34,0) -> #N/A | G16: PAGO CUOTAS | H16: =VLOOKUP(A16,Export!A:C,3,0) -> #N/A | I16: =VLOOKUP(A16,Export!A:B,2,0) -> #N/A | J16: =VLOOKUP(A16,Export!A:R,18,0) -> #N/A | K16: =VLOOKUP(A16,Export!A:D,4,0) -> #N/A | L16: =IF(G16="PAGO CUOTAS",H16*J16,K16) -> #N/A | M16: 46157 | N16: PENDIENTE | P16: =+SUMIF(N16,"PAGADO",K16) -> 0 | R16: =+VLOOKUP(A16,'[1]ORIGINAL '!D:E,2,0) -> 0 | S16: FALSE | T16: =VLOOKUP(A16,'OFICIO '!A:J,10,0) -> #N/A
A17: 2431101 | B17: =VLOOKUP(A17,Export!A:N,14,0) -> 11624626 | C17: =VLOOKUP(A17,Export!A:P,16,0) -> FABIOLA ELIZABETH CHAPARRO CHAPARRO | D17: =VLOOKUP(A17,Export!A:H,8,0) -> 31-60 | E17: =VLOOKUP(A17,Export!A:I,9,0) -> 61-90 | F17: =VLOOKUP(A17,Export!A:AH,34,0) -> NO RECUPERADO | G17: PAGO CUOTAS | H17: 2 | I17: =VLOOKUP(A17,Export!A:B,2,0) -> 80 | J17: =VLOOKUP(A17,Export!A:R,18,0) -> 234.6 | K17: =VLOOKUP(A17,Export!A:D,4,0) -> 4935008 | L17: =IF(G17="PAGO CUOTAS",H17*J17,K17) -> 469.2 | M17: 46149 | N17: PAGADO | O17: 46150 | P17: =+SUMIF(N17,"PAGADO",K17) -> 4935008 | Q17: pago por transferencia | R17: =+VLOOKUP(A17,'[1]ORIGINAL '!D:E,2,0) -> 0 | S17: FALSE | T17: =VLOOKUP(A17,'OFICIO '!A:J,10,0) -> #N/A
A18: 3421001 | B18: =VLOOKUP(A18,Export!A:N,14,0) -> 11853996 | C18: =VLOOKUP(A18,Export!A:P,16,0) -> MARCELA VIVIANA OYARCE ILLANES | D18: =VLOOKUP(A18,Export!A:H,8,0) -> 31-60 | E18: =VLOOKUP(A18,Export!A:I,9,0) -> 46052 | F18: =VLOOKUP(A18,Export!A:AH,34,0) -> CONTENIDO | G18: PAGO CUOTAS | H18: 3 | I18: =VLOOKUP(A18,Export!A:B,2,0) -> 20 | J18: =VLOOKUP(A18,Export!A:R,18,0) -> 278.563 | K18: =VLOOKUP(A18,Export!A:D,4,0) -> 9431928 | L18: =IF(G18="PAGO CUOTAS",H18*J18,K18) -> 835.689 | M18: 46153 | N18: PAGADO | O18: 46153 | P18: =+SUMIF(#REF!,"PAGADO",K18) -> #REF! | Q18: se aplica pago a flokzu | R18: =+VLOOKUP(A18,'[1]ORIGINAL '!D:E,2,0) -> 0 | S18: FALSE | T18: =VLOOKUP(A18,'OFICIO '!A:J,10,0) -> #N/A
A19: 3128019 | B19: =VLOOKUP(A19,Export!A:N,14,0) -> 17376853 | C19: =VLOOKUP(A19,Export!A:P,16,0) -> FRANCISCA KARINA LINEROS GARRIDO | D19: =VLOOKUP(A19,Export!A:H,8,0) -> 31-60 | E19: =VLOOKUP(A19,Export!A:I,9,0) -> 46052 | F19: =VLOOKUP(A19,Export!A:AH,34,0) -> CONTENIDO | G19: PAGO CUOTAS | H19: 1 | I19: =VLOOKUP(A19,Export!A:B,2,0) -> 24 | J19: =VLOOKUP(A19,Export!A:R,18,0) -> 371.068 | K19: =VLOOKUP(A19,Export!A:D,4,0) -> 7296344 | L19: =IF(G19="PAGO CUOTAS",H19*J19,K19) -> 371.068 | N19: PAGADO | P19: =+SUMIF(N19,"PAGADO",K19) -> 7296344 | R19: =+VLOOKUP(A19,'[1]ORIGINAL '!D:E,2,0) -> 0 | S19: FALSE | T19: =VLOOKUP(A19,'OFICIO '!A:J,10,0) -> #N/A
A20: 3378278 | B20: =VLOOKUP(A20,Export!A:N,14,0) -> 10780067 | C20: =VLOOKUP(A20,Export!A:P,16,0) -> HERMAN ROGELIO VELIZ ITE | D20: =VLOOKUP(A20,Export!A:H,8,0) -> 91-120 | E20: =VLOOKUP(A20,Export!A:I,9,0) -> 121-150 | F20: =VLOOKUP(A20,Export!A:AH,34,0) -> NO RECUPERADO | G20: PAGO CUOTAS | H20: 2 | I20: =VLOOKUP(A20,Export!A:B,2,0) -> 137 | J20: =VLOOKUP(A20,Export!A:R,18,0) -> 253.855 | K20: =VLOOKUP(A20,Export!A:D,4,0) -> 7299234 | L20: =IF(G20="PAGO CUOTAS",H20*J20,K20) -> 507.71 | M20: 46171 | N20: PENDIENTE | P20: =+SUMIF(N20,"PAGADO",K20) -> 0 | R20: =+VLOOKUP(A20,'[1]ORIGINAL '!D:E,2,0) -> 0 | S20: FALSE | T20: =VLOOKUP(A20,'OFICIO '!A:J,10,0) -> #N/A
A21: 1846277 | B21: =VLOOKUP(A21,Export!A:N,14,0) -> #N/A | C21: =VLOOKUP(A21,Export!A:P,16,0) -> #N/A | D21: =VLOOKUP(A21,Export!A:H,8,0) -> #N/A | E21: =VLOOKUP(A21,Export!A:I,9,0) -> #N/A | F21: =VLOOKUP(A21,Export!A:AH,34,0) -> #N/A | G21: PAGO CUOTAS | H21: =VLOOKUP(A21,Export!A:C,3,0) -> #N/A | I21: =VLOOKUP(A21,Export!A:B,2,0) -> #N/A | J21: =VLOOKUP(A21,Export!A:R,18,0) -> #N/A | K21: =VLOOKUP(A21,Export!A:D,4,0) -> #N/A | L21: =IF(G21="PAGO CUOTAS",H21*J21,K21) -> #N/A | M21: 46150 | N21: PAGADO | P21: =+SUMIF(N21,"PAGADO",K21) -> #N/A | R21: =+VLOOKUP(A21,'[1]ORIGINAL '!D:E,2,0) -> 0 | S21: FALSE | T21: =VLOOKUP(A21,'OFICIO '!A:J,10,0) -> 46054
A22: 3014523 | B22: =VLOOKUP(A22,Export!A:N,14,0) -> 9880918 | C22: =VLOOKUP(A22,Export!A:P,16,0) -> MANUEL FERMÍN VERGARA ZAMORANO | D22: =VLOOKUP(A22,Export!A:H,8,0) -> 331-360 | E22: =VLOOKUP(A22,Export!A:I,9,0) -> 331-360 | F22: =VLOOKUP(A22,Export!A:AH,34,0) -> NO RECUPERADO | G22: PAGO CUOTAS | H22: =VLOOKUP(A22,Export!A:C,3,0) -> 12 | I22: =VLOOKUP(A22,Export!A:B,2,0) -> 353 | J22: =VLOOKUP(A22,Export!A:R,18,0) -> 269.808 | K22: =VLOOKUP(A22,Export!A:D,4,0) -> 6447948 | L22: =IF(G22="PAGO CUOTAS",H22*J22,K22) -> 3237.696 | M22: 46168 | N22: PENDIENTE | P22: =+SUMIF(N22,"PAGADO",K22) -> 0 | R22: =+VLOOKUP(A22,'[1]ORIGINAL '!D:E,2,0) -> 0 | S22: FALSE | T22: =VLOOKUP(A22,'OFICIO '!A:J,10,0) -> #N/A
A23: 3008575 | B23: =VLOOKUP(A23,Export!A:N,14,0) -> #N/A | C23: =VLOOKUP(A23,Export!A:P,16,0) -> #N/A | D23: =VLOOKUP(A23,Export!A:H,8,0) -> #N/A | E23: =VLOOKUP(A23,Export!A:I,9,0) -> #N/A | F23: =VLOOKUP(A23,Export!A:AH,34,0) -> #N/A | G23: PAGO CUOTAS | H23: 5 | I23: =VLOOKUP(A23,Export!A:B,2,0) -> #N/A | J23: =VLOOKUP(A23,Export!A:R,18,0) -> #N/A | K23: =VLOOKUP(A23,Export!A:D,4,0) -> #N/A | L23: 1833793 | M23: 46170 | N23: PENDIENTE | P23: =+SUMIF(N23,"PAGADO",K23) -> 0 | R23: =+VLOOKUP(A23,'[1]ORIGINAL '!D:E,2,0) -> 0 | S23: FALSE | T23: =VLOOKUP(A23,'OFICIO '!A:J,10,0) -> #N/A
A24: 1477948 | B24: =VLOOKUP(A24,Export!A:N,14,0) -> #N/A | C24: =VLOOKUP(A24,Export!A:P,16,0) -> #N/A | D24: =VLOOKUP(A24,Export!A:H,8,0) -> #N/A | E24: =VLOOKUP(A24,Export!A:I,9,0) -> #N/A | F24: =VLOOKUP(A24,Export!A:AH,34,0) -> #N/A | G24: PAGO CUOTAS | H24: =VLOOKUP(A24,Export!A:C,3,0) -> #N/A | I24: =VLOOKUP(A24,Export!A:B,2,0) -> #N/A | J24: =VLOOKUP(A24,Export!A:R,18,0) -> #N/A | K24: =VLOOKUP(A24,Export!A:D,4,0) -> #N/A | L24: =IF(G24="PAGO CUOTAS",H24*J24,K24) -> #N/A | M24: 46154 | N24: PAGADO | P24: =+SUMIF(N24,"PAGADO",K24) -> #N/A | R24: =+VLOOKUP(A24,'[1]ORIGINAL '!D:E,2,0) -> 0 | S24: FALSE | T24: =VLOOKUP(A24,'OFICIO '!A:J,10,0) -> 45779
A25: 2936686 | B25: =VLOOKUP(A25,Export!A:N,14,0) -> 13134455 | C25: =VLOOKUP(A25,Export!A:P,16,0) -> JOHANA ELIZABETH FUENTES VEJAR | D25: =VLOOKUP(A25,Export!A:H,8,0) -> 31-60 | E25: =VLOOKUP(A25,Export!A:I,9,0) -> 31-60 | F25: =VLOOKUP(A25,Export!A:AH,34,0) -> CONTENIDO | G25: PAGO CUOTAS | H25: =VLOOKUP(A25,Export!A:C,3,0) -> 2 | I25: =VLOOKUP(A25,Export!A:B,2,0) -> 35 | J25: =VLOOKUP(A25,Export!A:R,18,0) -> 257.487 | K25: =VLOOKUP(A25,Export!A:D,4,0) -> 6659468 | L25: =IF(G25="PAGO CUOTAS",H25*J25,K25) -> 514.974 | M25: 46157 | N25: PAGADO | P25: =+SUMIF(N25,"PAGADO",K25) -> 6659468 | R25: =+VLOOKUP(A25,'[1]ORIGINAL '!D:E,2,0) -> 0 | S25: FALSE | T25: =VLOOKUP(A25,'OFICIO '!A:J,10,0) -> #N/A
